Workbook

Sheet BALANCE
A1: BALANCE AL MES DE FEBRERO DE 2026
A3: N° | B3: APELLIDOS Y NOMBRES | C3: MESES | D3: FECHA DE PRÉSTAMO | E3: PRÉSTAMO ACUMULADO | F3: INTERES MENSUAL ACTUAL | G3: INTERES PARCIAL ACUMULADO | H3: INTERES PROYECTADO ACUMULADO | I3: SALDO ACTUAL
A4: 1 | B4: ALIAGA ARAUJO, Angel F. | C4: 84 MESES | D4: 45625 | E4: S/43,427.8 | F4: S/209.6 | G4: S/10,310.8 | H4: S/17,542.6 | I4: S/20,663.6
A5: 2 | B5: ALVAREZ DIAZ, Rene | C5: 60 MESES | D5: 46081 | E5: S/29,153.1 | F5: - | G5: S/8,520.1 | H5: S/8,891.5 | I5: S/29,153.1
A6: 3 | B6: ARAUJO SANCHEZ, Magda M. | C6: 84 MESES | D6: 45806 | E6: S/59,233.2 | F6: S/391.5 | G6: S/15,699.6 | H6: S/30,380.2 | I6: S/38,632.4
A7: 4 | B7: BARRANTES ROJAS, Luis E. | C7: 72 MESES | D7: 45045 | E7: S/44,154.4 | F7: S/239.2 | G7: S/11,571.9 | H7: S/16,115.8 | I7: S/23,302.2
A8: 5 | B8: BAZAN VASQUEZ, Mirtha L. | C8: 60 MESES | D8: 45898 | E8: S/42,148.5 | F8: S/285.9 | G8: S/5,773.0 | H8: S/13,493.8 | I8: S/28,073.8
A9: 6 | B9: CABANILLAS YZQUIERDO, Jorge Luis | C9: 84 MESES | D9: 45806 | E9: S/41,477.1 | F9: S/320.3 | G9: S/7,682.0 | H9: S/19,691.6 | I9: S/31,608.4
A10: 7 | B10: CHAVEZ ALVAREZ, Jorge A. | C10: 84 MESES | D10: 45867 | E10: S/34,118.8 | F10: S/235.8 | G10: S/8,404.7 | H10: S/17,484.8 | I10: S/23,279.7
A11: 8 | B11: CHAVEZ ALVAREZ, Luis F. | C11: 60 MESES | D11: 46081 | E11: S/37,389.2 | F11: S/141.4 | G11: S/4,501.7 | H11: S/13,311.1 | I11: S/28,883.6
A12: 9 | B12: CHAVEZ CHAVEZ, Jorge E. | C12: 84 MESES | D12: 45837 | E12: S/56,293.4 | F12: S/422.8 | G12: S/11,727.5 | H12: S/27,794.2 | I12: S/41,731.6
A13: 10 | B13: CHAVEZ CHAVEZ, Pedro | C13: 36 MESES | D13: 45959 | E13: S/30,907.5 | F13: S/187.9 | G13: S/4,070.0 | H13: S/7,076.8 | I13: S/18,223.3
A14: 11 | B14: CHAVEZ MARIN Edwin F. | C14: 84 MESES | D14: 45929 | E14: S/63,280.7 | F14: S/502.3 | G14: S/10,990.1 | H14: S/30,832.2 | I14: S/49,604.6
A15: 12* | B15: CHAVEZ QUEVEDO, Melba G. | C15: 12 MESES | D15: 46051 | E15: S/53,453.9 | F15: S/257.4 | G15: S/4,447.4 | H15: S/5,863.4 | I15: S/23,595.4
A16: 13 | B16: CHAVEZ SALAZAR, María E. | C16: 84 MESES | D16: 45716 | E16: S/34,457.0 | F16: S/210.9 | G16: S/7,612.5 | H16: S/15,203.7 | I16: S/20,799.2
A17: 14 | B17: DIAZ ALBARRAN, Carlos F. | C17: 84 MESES | D17: 45259 | E17: S/33,883.7 | F17: S/234.0 | G17: S/7,732.8 | H17: S/14,400.0 | I17: S/22,991.9
A18: 15 | B18: DIAZ ALBARRAN, Juan S. | C18: 48 MESES | D18: 45837 | E18: S/29,666.4 | F18: S/175.8 | G18: S/4,648.2 | H18: S/8,164.7 | I18: S/17,152.7
A19: 16 | B19: DIAZ ALIAGA, Kevin A. | C19: 60 MESES | D19: 46081 | E19: S/32,964.1 | F19: S/127.2 | G19: S/3,287.6 | H19: S/10,327.9 | I19: S/23,085.0
A20: 17* | B20: DÍAZ QUIROZ, Maritza Y. | C20: 84 MESES | D20: 46051 | E20: S/45,768.7 | F20: S/330.0 | G20: S/9,801.1 | H20: S/23,496.3 | I20: S/32,609.2
A21: 18 | B21: DÍAZ VERA, Jackeline M. | C21: 72 MESES | D21: 45502 | E21: S/66,034.5 | F21: S/392.7 | G21: S/15,731.7 | H21: S/26,137.9 | I21: S/38,541.4
A22: 19 | B22: DÍAZ VERA, Tania J. | C22: 60 MESES | D22: 45716 | E22: S/59,208.6 | F22: S/326.8 | G22: S/14,724.5 | H22: S/22,567.0 | I22: S/32,008.5
A23: 20 | B23: MONTOYA CHÁVEZ, Wilser F. | C23: 84 MESES | D23: 45898 | E23: S/66,140.8 | F23: S/525.8 | G23: S/11,407.0 | H23: S/31,912.8 | I23: S/51,911.3
A24: 21 | B24: MONTOYA CRISOLOGO, Luis F. | C24: 60 MESES | D24: 45776 | E24: S/47,061.6 | F24: S/313.9 | G24: S/8,585.4 | H24: S/16,432.3 | I24: S/30,771.1
A25: 22 | B25: MONTOYA MACHUCA, Hugo D. | C25: 60 MESES | D25: 45958 | E25: S/29,080.9 | F25: S/194.2 | G25: S/4,868.8 | H25: S/10,307.0 | I25: S/19,080.2
A26: 23* | B26: PEREYRA CHAVEZ, Jhonatan G. | C26: 84 MESES | D26: 46051 | E26: S/34,971.7 | F26: S/210.0 | G26: S/6,960.7 | H26: S/18,758.8 | I26: S/20,751.4
A27: 24** | B27: PEREYRA RODRIGUEZ, Bertha E. | C27: 60 MESES | D27: 46020 | E27: S/33,557.2 | F27: S/218.6 | G27: S/4,013.0 | H27: S/10,352.4 | I27: S/21,492.0
A28: 25 | B28: PEREYRA RODRIGUEZ, Hilda L. | C28: 84 MESES | D28: 45837 | E28: S/33,058.1 | F28: S/211.1 | G28: S/6,328.8 | H28: S/14,349.1 | I28: S/20,835.5
A29: 26*** | B29: RONCAL ALBARRAN, Alejandro | C29: 36 MESES | D29: 45990 | E29: S/61,300.5 | F29: S/439.0 | G29: S/7,082.6 | H29: S/14,325.5 | I29: S/42,605.9
A30: 27 | B30: SANCHEZ ZAVALETA, Luis A. | C30: 84 MESES | D30: 45928 | E30: S/52,896.8 | F30: S/405.9 | G30: S/10,115.7 | H30: S/26,151.4 | I30: S/40,086.9
A31: 28 | B31: TAMBO RABANAL, Esperanza | C31: 84 MESES | D31: 45806 | E31: S/40,647.9 | F31: S/309.7 | G31: S/7,395.6 | H31: S/19,006.5 | I31: S/30,559.6
A32: 29 | B32: TAPIA DIAZ, Jhonatan E. | C32: 84 MESES | D32: 45928 | E32: S/50,061.6 | F32: S/285.0 | G32: S/10,329.8 | H32: S/21,586.0 | I32: S/28,144.0
A33: 30 | B33: VERA ARAUJO, Cristina | C33: 36 MESES | D33: 45686 | E33: S/40,896.4 | F33: S/143.1 | G33: S/8,064.5 | H33: S/12,581.6 | I33: S/24,415.6
A34: FEBRERO DE 2026 - TOTAL | E34: S/1,414,246.8 | F34: S/8,614.9 | G34: S/252,389.1 | H34: S/524,538.9 | I34: S/874,593.1

Sheet SOCIOS
A1: RELACIÓN DE PRÉSTAMOS DE LOS INTEGRANTES DE LA ASOCIACIÓN
A2: N° | B2: APELLIDOS Y NOMBRES | C2: N° MESES | D2: FECHA PRESTAMO | E2: SALDO | F2: MES/2026 | G2: REUNIÓN | H2: PERMISOS
A3: 1 | B3: ALIAGA ARAUJO, Angel Fernando | C3: 60 meses | D3: 45625 | E3: ='1'!G19 -> 20663.6 | G3: 46204 | H3: 46054
A4: 2 | B4: ALVAREZ DÍAZ, René | C4: 60 meses | D4: 46081 | E4: ='2'!G4 -> 29153.1 | F4: FEBRERO
A5: 3 | B5: ARAUJO SANCHEZ, Magda Mercedes | C5: 84 meses | D5: 45806 | E5: ='3'!G13 -> 38632.4 | G5: 46235 | H5: -
A6: 4 | B6: BARRANTES ROJAS, Luis Euler | C6: 72 meses | D6: 45045 | E6: ='4'!G38 -> 23302.2 | G6: 46266 | H6: 46054
A7: 5 | B7: BAZAN VASQUEZ, Mirtha Lusnilda | C7: 60 meses | D7: 45898 | E7: ='5'!G10 -> 28073.8 | G7: 46296 | H7: 46054
A8: 6 | B8: CABANILLAS YZQUIERDO, Jorge Luis | C8: 84 meses | D8: 45806 | E8: ='6'!G13 -> 31608.4 | G8: 46327 | H8: -
A9: 7 | B9: CHAVEZ ALVAREZ, Jorge Arturo | C9: 84 meses | D9: 45898 | E9: ='7'!G11 -> 23279.7 | G9: 46357 | H9: -
A10: 8 | B10: CHAVEZ ALVAREZ, Luis Fernando | C10: 60 meses | D10: 46081 | E10: ='8'!G69 -> 28883.6 | F10: FEBRERO | G10: 46388 | H10: -
A11: 9 | B11: CHAVEZ CHAVEZ, Jorge Emiliano | C11: 84 meses | D11: 45837 | E11: ='9'!G12 -> 41731.6 | G11: 46419 | H11: -
A12: 10 | B12: CHAVEZ CHAVEZ, Pedro | C12: 36 meses | D12: 45959 | E12: ='10'!G62 -> 18223.3 | G12: 46447 | H12: 46054
A13: 11 | B13: CHAVEZ MARIN Edwin Felix | C13: 84 meses | D13: 45929 | E13: ='11'!G9 -> 49604.6 | G13: 46478 | H13: 46054
A14: 12 | B14: CHAVEZ QUEVEDO, Melba Gladis | C14: 12 meses | D14: 46051 | E14: ='12'!G71 -> 23595.4 | F14: ENERO | G14: 46508 | H14: 45962
A15: 13 | B15: CHAVEZ SALAZAR, María Elizabeth | C15: 84 meses | D15: 29/02/2025 | E15: ='13'!G16 -> 20799.2 | G15: 46539 | H15: -
A16: 14 | B16: DIAZ ALBARRAN, Carlos Felipe | C16: 84 meses | D16: 45259 | E16: ='14'!G31 -> 22991.9 | G16: 46569 | H16: 46054
A17: 15 | B17: DIAZ ALBARRAN, Juan de la Salle | C17: 48 meses | D17: 45837 | E17: ='15'!G12 -> 17152.7 | G17: 21/12/2025 - 7 PM | H17: -
A18: 16 | B18: DIAZ ALIAGA, Kevin Airton | C18: 60 meses | D18: 46081 | E18: ='16'!G57 -> 23085 | F18: FEBRERO | G18: 46631 | H18: -
A19: 17 | B19: DÍAZ QUIROZ, Maritza Yolanda | C19: 84 meses | D19: 46051 | E19: ='17'!G95 -> 32609.2 | F19: ENERO | G19: 46661 | H19: -
A20: 18 | B20: DÍAZ VERA, Jackeline Magdalena | C20: 72 meses | D20: 45502 | E20: ='18'!G23 -> 38541.4 | G20: 46692 | H20: -
A21: 19 | B21: DÍAZ VERA, Tania Janet | C21: 60 meses | D21: 29/02/2025 | E21: ='19'!G16 -> 32008.5 | G21: 46722 | H21: -
A22: 20 | B22: MONTOYA CHÁVEZ, Wilser Filadelfo | C22: 84 meses | D22: 45898 | E22: ='20'!G10 -> 51911.3 | G22: 46784 | H22: NOVIEMBRE 2025 FEBRERO 2026
A23: 21 | B23: MONTOYA CRISOLOGO, Luis Fernando | C23: 60 meses | D23: 45776 | E23: ='21'!G14 -> 30771.1 | G23: 46813 | H23: 46054
A24: 22 | B24: MONTOYA MACHUCA, Hugo Delesmiro | C24: 60 meses | D24: 45959 | E24: ='22'!G75 -> 19080.2 | G24: 46844 | H24: 45962
A25: 23 | B25: PEREYRA CHAVEZ, Jhonatan Guillermo | C25: 84 meses | D25: 46051 | E25: ='23'!G71 -> 20751.4 | F25: ENERO | G25: 30/11/2025 - 7 PM | H25: -
A26: 24 | B26: PEREYRA RODRIGUEZ, Bertha Esther | C26: 60 meses | D26: 46020 | E26: ='24'!G60 -> 21492 | G26: NO SE REALIZÓ | H26: 46054
A27: 25 | B27: PEREYRA RODRIGUEZ, Hilda Lucila | C27: 84 meses | D27: 45837 | E27: ='25'!G12 -> 20835.5 | H27: 46054
A28: 26 | B28: RONCAL ALBARRAN, Alejandro | C28: 36 meses | D28: 45990 | E28: ='26'!G61 -> 42605.9 | G28: 28/02/2026 - 7 PM | H28: -
A29: 27 | B29: SANCHEZ ZAVALETA, Luis Alberto | C29: 84 meses | D29: 45929 | E29: ='27'!G9 -> 40086.9 | G29: 46082 | H29: -
A30: 28 | B30: TAMBO RABANAL, Esperanza | C30: 84 meses | D30: 45806 | E30: ='28'!G13 -> 30559.6 | G30: 46113 | H30: 46054
A31: 29 | B31: TAPIA DIAZ, Jhonatan Edinson | C31: 84 meses | D31: 45929 | E31: ='29'!G9 -> 28144 | G31: 46143 | H31: -
A32: 30 | B32: VERA ARAUJO, Cristina | C32: 36 meses | D32: 46081 | E32: ='30'!G46 -> 24415.6 | F32: FEBRERO | G32: 46174 | H32: -
A33: TOTAL | E33: =SUM(E3:E32) -> 874593.1
A34: ACCIONES POR SOCIO | E34: =E33/A32 -> 29153.103
A83: APORTACIÓN MARZO DE 2026
A84: RELACIÓN DE CUOTAS DE LOS INTEGRANTES DE LA ASOCIACIÓN
A85: N° | B85: APELLIDOS Y NOMBRES | C85: N° MESES | D85: FECHA | E85: PRÉSTAMO | F85: APORTACIÓN | G85: TOTAL
A86: 1 | B86: ALIAGA ARAUJO, Angel Fernando | C86: 60 meses | D86: 45625 | E86: S/506.1 | F86: S/150.0 | G86: S/656.1
A87: 2 | B87: ALVAREZ DÍAZ, René | C87: 60 meses | D87: 46081 | E87: S/777.4 | F87: S/150.0 | G87: S/927.4
A88: 3 | B88: ARAUJO SANCHEZ, Magda Mercedes | C88: 84 meses | D88: 45806 | E88: S/901.4 | F88: S/150.0 | G88: S/1,051.4
A89: 4 | B89: BARRANTES ROJAS, Luis Euler | C89: 72 meses | D89: 45045 | E89: S/846.3 | F89: S/150.0 | G89: S/996.3
A90: 5 | B90: BAZAN VASQUEZ, Mirtha Lusnilda | C90: 60 meses | D90: 45898 | E90: S/800.6 | F90: S/150.0 | G90: S/950.6
A91: 6 | B91: CABANILLAS YZQUIERDO, Jorge Luis | C91: 84 meses | D91: 45806 | E91: S/737.6 | F91: S/150.0 | G91: S/887.6
A92: 7 | B92: CHAVEZ ALVAREZ, Jorge Arturo | C92: 84 meses | D92: 45898 | E92: S/535.1 | F92: S/150.0 | G92: S/685.1
A93: 8 | B93: CHAVEZ ALVAREZ, Luis Fernando | C93: 60 meses | D93: 46081 | E93: S/770.2 | F93: S/150.0 | G93: S/920.2
A94: 9 | B94: CHAVEZ CHAVEZ, Jorge Emiliano | C94: 84 meses | D94: 45837 | E94: S/966.4 | F94: S/150.0 | G94: S/1,116.4
A95: 10 | B95: CHAVEZ CHAVEZ, Pedro | C95: 36 meses | D95: 45959 | E95: S/751.7 | F95: S/150.0 | G95: S/901.7
A96: 11 | B96: CHAVEZ MARIN Edwin Felix | C96: 84 meses | D96: 45929 | E96: S/1,123.9 | F96: S/150.0 | G96: S/1,273.9
A97: 12 | B97: CHAVEZ QUEVEDO, Melba Gladis | C97: 60 meses | D97: 45594 | E97: S/2,381.0 | F97: S/150.0 | G97: S/2,531.0
A98: 13 | B98: CHAVEZ SALAZAR, María Elizabeth | C98: 84 meses | D98: 29/02/2025 | E98: S/496.9 | F98: S/150.0 | G98: S/646.9
A99: 14 | B99: DIAZ ALBARRAN, Carlos Felipe | C99: 84 meses | D99: 45259 | E99: S/633.3 | F99: S/150.0 | G99: S/783.3
A100: 15 | B100: DIAZ ALBARRAN, Juan de la Salle | C100: 48 meses | D100: 45837 | E100: S/600.3 | F100: S/150.0 | G100: S/750.3
A101: 16 | B101: DIAZ ALIAGA, Kevin Airton | C101: 36 meses | D101: 45745 | E101: S/615.7 | F101: S/150.0 | G101: S/765.7
A102: 17 | B102: DÍAZ QUIROZ, Maritza Yolanda | C102: 84 meses | D102: 45837 | E102: S/719.0 | F102: S/150.0 | G102: S/869.0
A103: 18 | B103: DÍAZ VERA, Jackeline Magdalena | C103: 72 meses | D103: 45502 | E103: S/1,112.6 | F103: S/150.0 | G103: S/1,262.6
A104: 19 | B104: DÍAZ VERA, Tania Janet | C104: 60 meses | D104: 29/02/2025 | E104: S/986.9 | F104: S/150.0 | G104: S/1,136.9
A105: 20 | B105: MONTOYA CHÁVEZ, Wilser Filadelfo | C105: 84 meses | D105: 45898 | E105: S/1,184.6 | F105: S/150.0 | G105: S/1,334.6
A106: 21 | B106: MONTOYA CRISOLOGO, Luis Fernando | C106: 60 meses | D106: 45776 | E106: S/923.1 | F106: S/150.0 | G106: S/1,073.1
A107: 22 | B107: MONTOYA MACHUCA, Hugo Delesmiro | C107: 60 meses | D107: 45959 | E107: S/531.5 | F107: S/150.0 | G107: S/681.5
A108: 23 | B108: PEREYRA CHAVEZ, Jhonatan Guillermo | C108: 60 meses | D108: 45594 | E108: S/457.5 | F108: S/150.0 | G108: S/607.5
A109: 24 | B109: PEREYRA RODRIGUEZ, Bertha Esther | C109: 60 meses | D109: 46020 | E109: S/585.5 | F109: S/150.0 | G109: S/735.5
A110: 25 | B110: PEREYRA RODRIGUEZ, Hilda Lucila | C110: 84 meses | D110: 45837 | E110: S/482.6 | F110: S/150.0 | G110: S/632.6
A111: 26 | B111: RONCAL ALBARRAN, Alejandro | C111: 36 meses | D111: 45990 | E111: S/1,717.2 | F111: S/150.0 | G111: S/1,867.2
A112: 27 | B112: SANCHEZ ZAVALETA, Luis Alberto | C112: 84 meses | D112: 45929 | E112: S/908.3 | F112: S/150.0 | G112: S/1,058.3
A113: 28 | B113: TAMBO RABANAL, Esperanza | C113: 84 meses | D113: 45806 | E113: S/713.1 | F113: S/150.0 | G113: S/863.1
A114: 29 | B114: TAPIA DIAZ, Jhonatan Edinson | C114: 84 meses | D114: 45929 | E114: S/637.7 | F114: S/150.0 | G114: S/787.7
A115: 30 | B115: VERA ARAUJO, Cristina | C115: 36 meses | D115: 45686 | E115: S/922.4 | F115: S/150.0 | G115: S/1,072.4
A116: MARZO DE 2026 - TOTAL | E116: S/25,325.9 | F116: S/4,500.0 | G116: S/29,825.9

Sheet 1
A1: SOCIO: ANGEL FERNANDO ALIAGA ARAUJO
A2: NOVIEMBRE 2024 - PRÉSTAMO
A3: PLAZO | B3: FECHA | C3: PRÉSTAMO S/. | D3: INTERES | E3: ABONO DE CAPITAL | F3: CUOTA | G3: SALDO
A4: 0 | B4: 45625 | C4: =+J7 -> 25156.1 | D4: 0.01 | G4: =+C4 -> 25156.1
A5: 1 | B5: 45655 | D5: =+ROUND(G4*0.01,1) -> 251.6 | E5: =ROUNDUP($C$4/84,1) -> 299.5 | F5: =+ROUND(D5+E5,1) -> 551.1 | G5: =+ROUND(G4-E5,1) -> 24856.6 | I5: SALDO | J5: 5560.8
A6: 2 | B6: 45686 | D6: =+ROUND(G5*0.01,1) -> 248.6 | E6: =ROUNDUP($C$4/84,1) -> 299.5 | F6: =+ROUND(D6+E6,1) -> 548.1 | G6: =+ROUND(G5-E6,1) -> 24557.1 | I6: PRESTAMO | J6: 19595.3
A7: 3 | B7: 45716 | D7: =+ROUND(G6*0.01,1) -> 245.6 | E7: =ROUNDUP($C$4/84,1) -> 299.5 | F7: =+ROUND(D7+E7,1) -> 545.1 | G7: =+ROUND(G6-E7,1) -> 24257.6 | I7: TOTAL | J7: =+SUM(J5:J6) -> 25156.1
A8: 4 | B8: 45745 | D8: =+ROUND(G7*0.01,1) -> 242.6 | E8: =ROUNDUP($C$4/84,1) -> 299.5 | F8: =+ROUND(D8+E8,1) -> 542.1 | G8: =+ROUND(G7-E8,1) -> 23958.1
A9: 5 | B9: 45776 | D9: =+ROUND(G8*0.01,1) -> 239.6 | E9: =ROUNDUP($C$4/84,1) -> 299.5 | F9: =+ROUND(D9+E9,1) -> 539.1 | G9: =+ROUND(G8-E9,1) -> 23658.6
A10: 6 | B10: 45806 | D10: =+ROUND(G9*0.01,1) -> 236.6 | E10: =ROUNDUP($C$4/84,1) -> 299.5 | F10: =+ROUND(D10+E10,1) -> 536.1 | G10: =+ROUND(G9-E10,1) -> 23359.1
A11: 7 | B11: 45837 | D11: =+ROUND(G10*0.01,1) -> 233.6 | E11: =ROUNDUP($C$4/84,1) -> 299.5 | F11: =+ROUND(D11+E11,1) -> 533.1 | G11: =+ROUND(G10-E11,1) -> 23059.6
A12: 8 | B12: 45867 | D12: =+ROUND(G11*0.01,1) -> 230.6 | E12: =ROUNDUP($C$4/84,1) -> 299.5 | F12: =+ROUND(D12+E12,1) -> 530.1 | G12: =+ROUND(G11-E12,1) -> 22760.1
A13: 9 | B13: 45898 | D13: =+ROUND(G12*0.01,1) -> 227.6 | E13: =ROUNDUP($C$4/84,1) -> 299.5 | F13: =+ROUND(D13+E13,1) -> 527.1 | G13: =+ROUND(G12-E13,1) -> 22460.6
A14: 10 | B14: 45929 | D14: =+ROUND(G13*0.01,1) -> 224.6 | E14: =ROUNDUP($C$4/84,1) -> 299.5 | F14: =+ROUND(D14+E14,1) -> 524.1 | G14: =+ROUND(G13-E14,1) -> 22161.1
A15: 11 | B15: 45959 | D15: =+ROUND(G14*0.01,1) -> 221.6 | E15: =ROUNDUP($C$4/84,1) -> 299.5 | F15: =+ROUND(D15+E15,1) -> 521.1 | G15: =+ROUND(G14-E15,1) -> 21861.6
A16: 12 | B16: 45990 | D16: =+ROUND(G15*0.01,1) -> 218.6 | E16: =ROUNDUP($C$4/84,1) -> 299.5 | F16: =+ROUND(D16+E16,1) -> 518.1 | G16: =+ROUND(G15-E16,1) -> 21562.1
A17: 13 | B17: 46020 | D17: =+ROUND(G16*0.01,1) -> 215.6 | E17: =ROUNDUP($C$4/84,1) -> 299.5 | F17: =+ROUND(D17+E17,1) -> 515.1 | G17: =+ROUND(G16-E17,1) -> 21262.6
A18: 14 | B18: 46051 | D18: =+ROUND(G17*0.01,1) -> 212.6 | E18: =ROUNDUP($C$4/84,1) -> 299.5 | F18: =+ROUND(D18+E18,1) -> 512.1 | G18: =+ROUND(G17-E18,1) -> 20963.1
A19: 15 | B19: 46081 | D19: =+ROUND(G18*0.01,1) -> 209.6 | E19: =ROUNDUP($C$4/84,1) -> 299.5 | F19: =+ROUND(D19+E19,1) -> 509.1 | G19: =+ROUND(G18-E19,1) -> 20663.6
... A87: 83 | B87: 48150 | D87: =+ROUND(G86*0.01,1) -> 6 | E87: =ROUNDUP($C$4/84,1) -> 299.5 | F87: =+ROUND(D87+E87,1) -> 305.5 | G87: =+ROUND(G86-E87,1) -> 297.6
A88: 84 | B88: 48181 | D88: =+ROUND(G87*0.01,1) -> 3 | E88: =ROUNDUP($C$4/84,1)-1.9 -> 297.6 | F88: =+ROUND(D88+E88,1) -> 300.6 | G88: =+ROUND(G87-E88,1) -> 0
A89: TOTAL | D89: =+SUM(D5:D88) -> 10690.8 | E89: =+SUM(E5:E88) -> 25156.1 | F89: =+SUM(F5:F88) -> 35846.9

Sheet 2
A1: SOCIA: ALVAREZ DÍAZ, RENÉ
A2: FEBRERO 2026 - PRÉSTAMO
A3: PLAZO | B3: FECHA | C3: PRÉSTAMO S/. | D3: INTERES | E3: ABONO DE CAPITAL | F3: CUOTA | G3: SALDO
A4: 0 | B4: 46081 | C4: =+J7 -> 29153.1 | D4: 0.01 | G4: =+C4 -> 29153.1
A5: 1 | B5: 46110 | D5: =+ROUND(G4*0.01,1) -> 291.5 | E5: =ROUNDUP($C$4/60,1) -> 485.9 | F5: =+ROUND(D5+E5,1) -> 777.4 | G5: =+ROUND(G4-E5,1) -> 28667.2 | I5: SALDO | J5: 0
A6: 2 | B6: 46141 | D6: =+ROUND(G5*0.01,1) -> 286.7 | E6: =ROUNDUP($C$4/60,1) -> 485.9 | F6: =+ROUND(D6+E6,1) -> 772.6 | G6: =+ROUND(G5-E6,1) -> 28181.3 | I6: PRESTAMO | J6: 29153.1
A7: 3 | B7: 46171 | D7: =+ROUND(G6*0.01,1) -> 281.8 | E7: =ROUNDUP($C$4/60,1) -> 485.9 | F7: =+ROUND(D7+E7,1) -> 767.7 | G7: =+ROUND(G6-E7,1) -> 27695.4 | I7: TOTAL | J7: =+SUM(J5:J6) -> 29153.1
A8: 4 | B8: 46202 | D8: =+ROUND(G7*0.01,1) -> 277 | E8: =ROUNDUP($C$4/60,1) -> 485.9 | F8: =+ROUND(D8+E8,1) -> 762.9 | G8: =+ROUND(G7-E8,1) -> 27209.5
A9: 5 | B9: 46232 | D9: =+ROUND(G8*0.01,1) -> 272.1 | E9: =ROUNDUP($C$4/60,1) -> 485.9 | F9: =+ROUND(D9+E9,1) -> 758 | G9: =+ROUND(G8-E9,1) -> 26723.6
A10: 6 | B10: 46263 | D10: =+ROUND(G9*0.01,1) -> 267.2 | E10: =ROUNDUP($C$4/60,1) -> 485.9 | F10: =+ROUND(D10+E10,1) -> 753.1 | G10: =+ROUND(G9-E10,1) -> 26237.7
A11: 7 | B11: 46294 | D11: =+ROUND(G10*0.01,1) -> 262.4 | E11: =ROUNDUP($C$4/60,1) -> 485.9 | F11: =+ROUND(D11+E11,1) -> 748.3 | G11: =+ROUND(G10-E11,1) -> 25751.8
A12: 8 | B12: 46324 | D12: =+ROUND(G11*0.01,1) -> 257.5 | E12: =ROUNDUP($C$4/60,1) -> 485.9 | F12: =+ROUND(D12+E12,1) -> 743.4 | G12: =+ROUND(G11-E12,1) -> 25265.9
A13: 9 | B13: 46355 | D13: =+ROUND(G12*0.01,1) -> 252.7 | E13: =ROUNDUP($C$4/60,1) -> 485.9 | F13: =+ROUND(D13+E13,1) -> 738.6 | G13: =+ROUND(G12-E13,1) -> 24780
A14: 10 | B14: 46385 | D14: =+ROUND(G13*0.01,1) -> 247.8 | E14: =ROUNDUP($C$4/60,1) -> 485.9 | F14: =+ROUND(D14+E14,1) -> 733.7 | G14: =+ROUND(G13-E14,1) -> 24294.1
A15: 11 | B15: 46416 | D15: =+ROUND(G14*0.01,1) -> 242.9 | E15: =ROUNDUP($C$4/60,1) -> 485.9 | F15: =+ROUND(D15+E15,1) -> 728.8 | G15: =+ROUND(G14-E15,1) -> 23808.2
A16: 12 | B16: 46446 | D16: =+ROUND(G15*0.01,1) -> 238.1 | E16: =ROUNDUP($C$4/60,1) -> 485.9 | F16: =+ROUND(D16+E16,1) -> 724 | G16: =+ROUND(G15-E16,1) -> 23322.3
A17: 13 | B17: 46475 | D17: =+ROUND(G16*0.01,1) -> 233.2 | E17: =ROUNDUP($C$4/60,1) -> 485.9 | F17: =+ROUND(D17+E17,1) -> 719.1 | G17: =+ROUND(G16-E17,1) -> 22836.4
A18: 14 | B18: 46506 | D18: =+ROUND(G17*0.01,1) -> 228.4 | E18: =ROUNDUP($C$4/60,1) -> 485.9 | F18: =+ROUND(D18+E18,1) -> 714.3 | G18: =+ROUND(G17-E18,1) -> 22350.5
A19: 15 | B19: 46536 | D19: =+ROUND(G18*0.01,1) -> 223.5 | E19: =ROUNDUP($C$4/60,1) -> 485.9 | F19: =+ROUND(D19+E19,1) -> 709.4 | G19: =+ROUND(G18-E19,1) -> 21864.6
... A63: 59 | B63: 47877 | D63: =+ROUND(G62*0.01,1) -> 9.7 | E63: =ROUNDUP($C$4/60,1) -> 485.9 | F63: =+ROUND(D63+E63,1) -> 495.6 | G63: =+ROUND(G62-E63,1) -> 485
A64: 60 | B64: 47907 | D64: =+ROUND(G63*0.01,1) -> 4.9 | E64: =ROUNDUP($C$4/60,1)-0.9 -> 485 | F64: =+ROUND(D64+E64,1) -> 489.9 | G64: =+ROUND(G63-E64,1) -> 0
A65: TOTAL | D65: =+SUM(D5:D64) -> 8891.5 | E65: =+SUM(E5:E64) -> 29153.1 | F65: =+SUM(F5:F64) -> 38044.6

Sheet 3
A1: SOCIA: MAGDA ARAUJO SANCHEZ
A2: MAYO 2025 - PRÉSTAMO
A3: PLAZO | B3: FECHA | C3: PRÉSTAMO S/. | D3: INTERES | E3: ABONO DE CAPITAL | F3: CUOTA | G3: SALDO
A4: 0 | B4: 45806 | C4: =+J7 -> 43268.3 | D4: 0.01 | G4: =+C4 -> 43268.3
A5: 1 | B5: 45837 | D5: =+ROUND(G4*0.01,1) -> 432.7 | E5: =ROUNDUP(C4/84,1) -> 515.1 | F5: =+ROUND(D5+E5,1) -> 947.8 | G5: =+ROUND(G4-E5,1) -> 42753.2 | I5: SALDO | J5: 40268.3
A6: 2 | B6: 45867 | D6: =+ROUND(G5*0.01,1) -> 427.5 | E6: =ROUNDUP($C$4/84,1) -> 515.1 | F6: =+ROUND(D6+E6,1) -> 942.6 | G6: =+ROUND(G5-E6,1) -> 42238.1 | I6: PRESTAMO | J6: 3000
A7: 3 | B7: 45898 | D7: =+ROUND(G6*0.01,1) -> 422.4 | E7: =ROUNDUP($C$4/84,1) -> 515.1 | F7: =+ROUND(D7+E7,1) -> 937.5 | G7: =+ROUND(G6-E7,1) -> 41723 | I7: TOTAL | J7: =+SUM(J5:J6) -> 43268.3
A8: 4 | B8: 45929 | D8: =+ROUND(G7*0.01,1) -> 417.2 | E8: =ROUNDUP($C$4/84,1) -> 515.1 | F8: =+ROUND(D8+E8,1) -> 932.3 | G8: =+ROUND(G7-E8,1) -> 41207.9
A9: 5 | B9: 45959 | D9: =+ROUND(G8*0.01,1) -> 412.1 | E9: =ROUNDUP($C$4/84,1) -> 515.1 | F9: =+ROUND(D9+E9,1) -> 927.2 | G9: =+ROUND(G8-E9,1) -> 40692.8
A10: 6 | B10: 45990 | D10: =+ROUND(G9*0.01,1) -> 406.9 | E10: =ROUNDUP($C$4/84,1) -> 515.1 | F10: =+ROUND(D10+E10,1) -> 922 | G10: =+ROUND(G9-E10,1) -> 40177.7
A11: 7 | B11: 46020 | D11: =+ROUND(G10*0.01,1) -> 401.8 | E11: =ROUNDUP($C$4/84,1) -> 515.1 | F11: =+ROUND(D11+E11,1) -> 916.9 | G11: =+ROUND(G10-E11,1) -> 39662.6
A12: 8 | B12: 46051 | D12: =+ROUND(G11*0.01,1) -> 396.6 | E12: =ROUNDUP($C$4/84,1) -> 515.1 | F12: =+ROUND(D12+E12,1) -> 911.7 | G12: =+ROUND(G11-E12,1) -> 39147.5
A13: 9 | B13: 46081 | D13: =+ROUND(G12*0.01,1) -> 391.5 | E13: =ROUNDUP($C$4/84,1) -> 515.1 | F13: =+ROUND(D13+E13,1) -> 906.6 | G13: =+ROUND(G12-E13,1) -> 38632.4
A14: 10 | B14: 46110 | D14: =+ROUND(G13*0.01,1) -> 386.3 | E14: =ROUNDUP($C$4/84,1) -> 515.1 | F14: =+ROUND(D14+E14,1) -> 901.4 | G14: =+ROUND(G13-E14,1) -> 38117.3
A15: 11 | B15: 46141 | D15: =+ROUND(G14*0.01,1) -> 381.2 | E15: =ROUNDUP($C$4/84,1) -> 515.1 | F15: =+ROUND(D15+E15,1) -> 896.3 | G15: =+ROUND(G14-E15,1) -> 37602.2
A16: 12 | B16: 46171 | D16: =+ROUND(G15*0.01,1) -> 376 | E16: =ROUNDUP($C$4/84,1) -> 515.1 | F16: =+ROUND(D16+E16,1) -> 891.1 | G16: =+ROUND(G15-E16,1) -> 37087.1
A17: 13 | B17: 46202 | D17: =+ROUND(G16*0.01,1) -> 370.9 | E17: =ROUNDUP($C$4/84,1) -> 515.1 | F17: =+ROUND(D17+E17,1) -> 886 | G17: =+ROUND(G16-E17,1) -> 36572
A18: 14 | B18: 46232 | D18: =+ROUND(G17*0.01,1) -> 365.7 | E18: =ROUNDUP($C$4/84,1) -> 515.1 | F18: =+ROUND(D18+E18,1) -> 880.8 | G18: =+ROUND(G17-E18,1) -> 36056.9
A19: 15 | B19: 46263 | D19: =+ROUND(G18*0.01,1) -> 360.6 | E19: =ROUNDUP($C$4/84,1) -> 515.1 | F19: =+ROUND(D19+E19,1) -> 875.7 | G19: =+ROUND(G18-E19,1) -> 35541.8
... A87: 83 | B87: 48333 | D87: =+ROUND(G86*0.01,1) -> 10.3 | E87: =ROUNDUP($C$4/84,1) -> 515.1 | F87: =+ROUND(D87+E87,1) -> 525.4 | G87: =+ROUND(G86-E87,1) -> 515
A88: 84 | B88: 48363 | D88: =+ROUND(G87*0.01,1) -> 5.2 | E88: 515 | F88: =+ROUND(D88+E88,1) -> 520.2 | G88: =+ROUND(G87-E88,1) -> 0
A89: TOTAL | D89: =+SUM(D5:D88) -> 18389.3 | E89: =+SUM(E5:E88) -> 43268.3 | F89: =+SUM(F5:F88) -> 61657.6

Sheet 4
A1: SOCIO: LUIS BARRANTES ROJAS
A2: ABRIL 2023 - PRÉSTAMO
A3: PLAZO | B3: FECHA | C3: PRÉSTAMO S/. | D3: INTERES | E3: ABONO DE CAPITAL | F3: CUOTA | G3: SALDO
A4: 0 | B4: 45045 | C4: =+J7 -> 44154.4 | D4: 0.01 | G4: =+C4 -> 44154.4
A5: 1 | B5: 45075 | D5: =+ROUND(G4*0.01,1) -> 441.5 | E5: =ROUNDUP(C4/72,1) -> 613.3 | F5: =+ROUND(D5+E5,1) -> 1054.8 | G5: =+ROUND(G4-E5,1) -> 43541.1 | I5: SALDO | J5: 44154.4
A6: 2 | B6: 45106 | D6: =+ROUND(G5*0.01,1) -> 435.4 | E6: =ROUNDUP($C$4/72,1) -> 613.3 | F6: =+ROUND(D6+E6,1) -> 1048.7 | G6: =+ROUND(G5-E6,1) -> 42927.8 | I6: PRESTAMO | J6: 0
A7: 3 | B7: 45136 | D7: =+ROUND(G6*0.01,1) -> 429.3 | E7: =ROUNDUP($C$4/72,1) -> 613.3 | F7: =+ROUND(D7+E7,1) -> 1042.6 | G7: =+ROUND(G6-E7,1) -> 42314.5 | I7: TOTAL | J7: =+SUM(J5:J6) -> 44154.4
A8: 4 | B8: 45167 | D8: =+ROUND(G7*0.01,1) -> 423.1 | E8: =ROUNDUP($C$4/72,1) -> 613.3 | F8: =+ROUND(D8+E8,1) -> 1036.4 | G8: =+ROUND(G7-E8,1) -> 41701.2
A9: 5 | B9: 45198 | D9: =+ROUND(G8*0.01,1) -> 417 | E9: =ROUNDUP($C$4/72,1) -> 613.3 | F9: =+ROUND(D9+E9,1) -> 1030.3 | G9: =+ROUND(G8-E9,1) -> 41087.9
A10: 6 | B10: 45228 | D10: =+ROUND(G9*0.01,1) -> 410.9 | E10: =ROUNDUP($C$4/72,1) -> 613.3 | F10: =+ROUND(D10+E10,1) -> 1024.2 | G10: =+ROUND(G9-E10,1) -> 40474.6
A11: 7 | B11: 45259 | D11: =+ROUND(G10*0.01,1) -> 404.7 | E11: =ROUNDUP($C$4/72,1) -> 613.3 | F11: =+ROUND(D11+E11,1) -> 1018 | G11: =+ROUND(G10-E11,1) -> 39861.3
A12: 8 | B12: 45289 | D12: =+ROUND(G11*0.01,1) -> 398.6 | E12: =ROUNDUP($C$4/72,1) -> 613.3 | F12: =+ROUND(D12+E12,1) -> 1011.9 | G12: =+ROUND(G11-E12,1) -> 39248
A13: 9 | B13: 45320 | D13: =+ROUND(G12*0.01,1) -> 392.5 | E13: =ROUNDUP($C$4/72,1) -> 613.3 | F13: =+ROUND(D13+E13,1) -> 1005.8 | G13: =+ROUND(G12-E13,1) -> 38634.7
A14: 10 | B14: 45351 | D14: =+ROUND(G13*0.01,1) -> 386.3 | E14: =ROUNDUP($C$4/72,1) -> 613.3 | F14: =+ROUND(D14+E14,1) -> 999.6 | G14: =+ROUND(G13-E14,1) -> 38021.4
A15: 11 | B15: 45380 | D15: =+ROUND(G14*0.01,1) -> 380.2 | E15: =ROUNDUP($C$4/72,1) -> 613.3 | F15: =+ROUND(D15+E15,1) -> 993.5 | G15: =+ROUND(G14-E15,1) -> 37408.1
A16: 12 | B16: 45411 | D16: =+ROUND(G15*0.01,1) -> 374.1 | E16: =ROUNDUP($C$4/72,1) -> 613.3 | F16: =+ROUND(D16+E16,1) -> 987.4 | G16: =+ROUND(G15-E16,1) -> 36794.8
A17: 13 | B17: 45441 | D17: =+ROUND(G16*0.01,1) -> 367.9 | E17: =ROUNDUP($C$4/72,1) -> 613.3 | F17: =+ROUND(D17+E17,1) -> 981.2 | G17: =+ROUND(G16-E17,1) -> 36181.5
A18: 14 | B18: 45472 | D18: =+ROUND(G17*0.01,1) -> 361.8 | E18: =ROUNDUP($C$4/72,1) -> 613.3 | F18: =+ROUND(D18+E18,1) -> 975.1 | G18: =+ROUND(G17-E18,1) -> 35568.2
A19: 15 | B19: 45502 | D19: =+ROUND(G18*0.01,1) -> 355.7 | E19: =ROUNDUP($C$4/72,1) -> 613.3 | F19: =+ROUND(D19+E19,1) -> 969 | G19: =+ROUND(G18-E19,1) -> 34954.9
... A44: 40 | B44: 46263 | D44: =+ROUND(G43*0.01,1) -> 202.4 | E44: =ROUNDUP($C$4/72,1) -> 613.3 | F44: =+ROUND(D44+E44,1) -> 815.7 | G44: =+ROUND(G43-E44,1) -> 19622.4
A45: 41 | B45: 46294 | D45: =+ROUND(G44*0.01,1) -> 196.2 | E45: =ROUNDDOWN($C$4/72,1) -> 613.2 | F45: =+ROUND(D45+E45,1) -> 809.4 | G45: =+ROUND(G44-E45,1) -> 19009.2
A46: 42 | B46: 46324 | D46: =+ROUND(G45*0.01,1) -> 190.1 | E46: =ROUNDDOWN($C$4/72,1) -> 613.2 | F46: =+ROUND(D46+E46,1) -> 803.3 | G46: =+ROUND(G45-E46,1) -> 18396
A47: 43 | B47: 46355 | D47: =+ROUND(G46*0.01,1) -> 184 | E47: =ROUNDDOWN($C$4/72,1) -> 613.2 | F47: =+ROUND(D47+E47,1) -> 797.2 | G47: =+ROUND(G46-E47,1) -> 17782.8
A48: 44 | B48: 46385 | D48: =+ROUND(G47*0.01,1) -> 177.8 | E48: =ROUNDDOWN($C$4/72,1) -> 613.2 | F48: =+ROUND(D48+E48,1) -> 791 | G48: =+ROUND(G47-E48,1) -> 17169.6
A49: 45 | B49: 46416 | D49: =+ROUND(G48*0.01,1) -> 171.7 | E49: =ROUNDDOWN($C$4/72,1) -> 613.2 | F49: =+ROUND(D49+E49,1) -> 784.9 | G49: =+ROUND(G48-E49,1) -> 16556.4
A50: 46 | B50: 46446 | D50: =+ROUND(G49*0.01,1) -> 165.6 | E50: =ROUNDDOWN($C$4/72,1) -> 613.2 | F50: =+ROUND(D50+E50,1) -> 778.8 | G50: =+ROUND(G49-E50,1) -> 15943.2
A51: 47 | B51: 46475 | D51: =+ROUND(G50*0.01,1) -> 159.4 | E51: =ROUNDDOWN($C$4/72,1) -> 613.2 | F51: =+ROUND(D51+E51,1) -> 772.6 | G51: =+ROUND(G50-E51,1) -> 15330
A52: 48 | B52: 46506 | D52: =+ROUND(G51*0.01,1) -> 153.3 | E52: =ROUNDDOWN($C$4/72,1) -> 613.2 | F52: =+ROUND(D52+E52,1) -> 766.5 | G52: =+ROUND(G51-E52,1) -> 14716.8
A53: 49 | B53: 46536 | D53: =+ROUND(G52*0.01,1) -> 147.2 | E53: =ROUNDDOWN($C$4/72,1) -> 613.2 | F53: =+ROUND(D53+E53,1) -> 760.4 | G53: =+ROUND(G52-E53,1) -> 14103.6
A54: 50 | B54: 46567 | D54: =+ROUND(G53*0.01,1) -> 141 | E54: =ROUNDDOWN($C$4/72,1) -> 613.2 | F54: =+ROUND(D54+E54,1) -> 754.2 | G54: =+ROUND(G53-E54,1) -> 13490.4
A55: 51 | B55: 46597 | D55: =+ROUND(G54*0.01,1) -> 134.9 | E55: =ROUNDDOWN($C$4/72,1) -> 613.2 | F55: =+ROUND(D55+E55,1) -> 748.1 | G55: =+ROUND(G54-E55,1) -> 12877.2
A56: 52 | B56: 46628 | D56: =+ROUND(G55*0.01,1) -> 128.8 | E56: =ROUNDDOWN($C$4/72,1) -> 613.2 | F56: =+ROUND(D56+E56,1) -> 742 | G56: =+ROUND(G55-E56,1) -> 12264
... A76: 72 | B76: 47237 | D76: =+ROUND(G75*0.01,1) -> 6.1 | E76: =ROUNDDOWN($C$4/72,1) -> 613.2 | F76: =+ROUND(D76+E76,1) -> 619.3 | G76: =+ROUND(G75-E76,1) -> 0
A77: TOTAL | D77: =+SUM(D5:D76) -> 16115.8 | E77: =+SUM(E5:E76) -> 44154.4 | F77: =+SUM(F5:F76) -> 60270.2

Sheet 5
A1: SOCIA: BAZAN VASQUEZ, MIRTHA LUSNILDA
A2: AGOSTO 2025 - PRÉSTAMO
A3: PLAZO | B3: FECHA | C3: PRÉSTAMO S/. | D3: INTERES | E3: ABONO DE CAPITAL | F3: CUOTA | G3: SALDO
A4: 0 | B4: 45898 | C4: =+J7 -> 31193.2 | D4: 0.01 | G4: =+C4 -> 31193.2
A5: 1 | B5: 45929 | D5: =+ROUND(G4*0.01,1) -> 311.9 | E5: =ROUNDUP($C$4/60,1) -> 519.9 | F5: =+ROUND(D5+E5,1) -> 831.8 | G5: =+ROUND(G4-E5,1) -> 30673.3 | I5: SALDO | J5: 11193.2
A6: 2 | B6: 45959 | D6: =+ROUND(G5*0.01,1) -> 306.7 | E6: =ROUNDUP($C$4/60,1) -> 519.9 | F6: =+ROUND(D6+E6,1) -> 826.6 | G6: =+ROUND(G5-E6,1) -> 30153.4 | I6: PRESTAMO | J6: 20000
A7: 3 | B7: 45990 | D7: =+ROUND(G6*0.01,1) -> 301.5 | E7: =ROUNDUP($C$4/60,1) -> 519.9 | F7: =+ROUND(D7+E7,1) -> 821.4 | G7: =+ROUND(G6-E7,1) -> 29633.5 | I7: TOTAL | J7: =+SUM(J5:J6) -> 31193.2
A8: 4 | B8: 46020 | D8: =+ROUND(G7*0.01,1) -> 296.3 | E8: =ROUNDUP($C$4/60,1) -> 519.9 | F8: =+ROUND(D8+E8,1) -> 816.2 | G8: =+ROUND(G7-E8,1) -> 29113.6
A9: 5 | B9: 46051 | D9: =+ROUND(G8*0.01,1) -> 291.1 | E9: =ROUNDUP($C$4/60,1) -> 519.9 | F9: =+ROUND(D9+E9,1) -> 811 | G9: =+ROUND(G8-E9,1) -> 28593.7
A10: 6 | B10: 46081 | D10: =+ROUND(G9*0.01,1) -> 285.9 | E10: =ROUNDUP($C$4/60,1) -> 519.9 | F10: =+ROUND(D10+E10,1) -> 805.8 | G10: =+ROUND(G9-E10,1) -> 28073.8
A11: 7 | B11: 46110 | D11: =+ROUND(G10*0.01,1) -> 280.7 | E11: =ROUNDUP($C$4/60,1) -> 519.9 | F11: =+ROUND(D11+E11,1) -> 800.6 | G11: =+ROUND(G10-E11,1) -> 27553.9
A12: 8 | B12: 46141 | D12: =+ROUND(G11*0.01,1) -> 275.5 | E12: =ROUNDUP($C$4/60,1) -> 519.9 | F12: =+ROUND(D12+E12,1) -> 795.4 | G12: =+ROUND(G11-E12,1) -> 27034
A13: 9 | B13: 46171 | D13: =+ROUND(G12*0.01,1) -> 270.3 | E13: =ROUNDUP($C$4/60,1) -> 519.9 | F13: =+ROUND(D13+E13,1) -> 790.2 | G13: =+ROUND(G12-E13,1) -> 26514.1
A14: 10 | B14: 46202 | D14: =+ROUND(G13*0.01,1) -> 265.1 | E14: =ROUNDUP($C$4/60,1) -> 519.9 | F14: =+ROUND(D14+E14,1) -> 785 | G14: =+ROUND(G13-E14,1) -> 25994.2
A15: 11 | B15: 46232 | D15: =+ROUND(G14*0.01,1) -> 259.9 | E15: =ROUNDUP($C$4/60,1) -> 519.9 | F15: =+ROUND(D15+E15,1) -> 779.8 | G15: =+ROUND(G14-E15,1) -> 25474.3
A16: 12 | B16: 46263 | D16: =+ROUND(G15*0.01,1) -> 254.7 | E16: =ROUNDUP($C$4/60,1) -> 519.9 | F16: =+ROUND(D16+E16,1) -> 774.6 | G16: =+ROUND(G15-E16,1) -> 24954.4
A17: 13 | B17: 46294 | D17: =+ROUND(G16*0.01,1) -> 249.5 | E17: =ROUNDUP($C$4/60,1) -> 519.9 | F17: =+ROUND(D17+E17,1) -> 769.4 | G17: =+ROUND(G16-E17,1) -> 24434.5
A18: 14 | B18: 46324 | D18: =+ROUND(G17*0.01,1) -> 244.3 | E18: =ROUNDUP($C$4/60,1) -> 519.9 | F18: =+ROUND(D18+E18,1) -> 764.2 | G18: =+ROUND(G17-E18,1) -> 23914.6
A19: 15 | B19: 46355 | D19: =+ROUND(G18*0.01,1) -> 239.1 | E19: =ROUNDUP($C$4/60,1) -> 519.9 | F19: =+ROUND(D19+E19,1) -> 759 | G19: =+ROUND(G18-E19,1) -> 23394.7
... A63: 59 | B63: 47693 | D63: =+ROUND(G62*0.01,1) -> 10.4 | E63: =ROUNDUP($C$4/60,1) -> 519.9 | F63: =+ROUND(D63+E63,1) -> 530.3 | G63: =+ROUND(G62-E63,1) -> 519.1
A64: 60 | B64: 47724 | D64: =+ROUND(G63*0.01,1) -> 5.2 | E64: =ROUNDUP($C$4/60,1)-0.8 -> 519.1 | F64: =+ROUND(D64+E64,1) -> 524.3 | G64: =+ROUND(G63-E64,1) -> 0
A65: TOTAL | D65: =+SUM(D5:D64) -> 9514.2 | E65: =+SUM(E5:E64) -> 31193.2 | F65: =+SUM(F5:F64) -> 40707.4

Sheet 6
A1: SOCIO: JORGE CABANILLAS IZQUIERDO
A2: MAYO 2025 - PRÉSTAMO
A3: PLAZO | B3: FECHA | C3: PRÉSTAMO S/. | D3: INTERES | E3: ABONO DE CAPITAL | F3: CUOTA | G3: SALDO
A4: 0 | B4: 45806 | C4: =+J7 -> 35401.9 | D4: 0.01 | G4: =+C4 -> 35401.9
A5: 1 | B5: 45837 | D5: =+ROUND(G4*0.01,1) -> 354 | E5: =ROUNDUP(C4/84,1) -> 421.5 | F5: =+ROUND(D5+E5,1) -> 775.5 | G5: =+ROUND(G4-E5,1) -> 34980.4 | I5: SALDO | J5: 25818.6
A6: 2 | B6: 45867 | D6: =+ROUND(G5*0.01,1) -> 349.8 | E6: =ROUNDUP($C$4/84,1) -> 421.5 | F6: =+ROUND(D6+E6,1) -> 771.3 | G6: =+ROUND(G5-E6,1) -> 34558.9 | I6: PRESTAMO | J6: 9583.3
A7: 3 | B7: 45898 | D7: =+ROUND(G6*0.01,1) -> 345.6 | E7: =ROUNDUP($C$4/84,1) -> 421.5 | F7: =+ROUND(D7+E7,1) -> 767.1 | G7: =+ROUND(G6-E7,1) -> 34137.4 | I7: TOTAL | J7: =+SUM(J5:J6) -> 35401.9
A8: 4 | B8: 45929 | D8: =+ROUND(G7*0.01,1) -> 341.4 | E8: =ROUNDUP($C$4/84,1) -> 421.5 | F8: =+ROUND(D8+E8,1) -> 762.9 | G8: =+ROUND(G7-E8,1) -> 33715.9
A9: 5 | B9: 45959 | D9: =+ROUND(G8*0.01,1) -> 337.2 | E9: =ROUNDUP($C$4/84,1) -> 421.5 | F9: =+ROUND(D9+E9,1) -> 758.7 | G9: =+ROUND(G8-E9,1) -> 33294.4
A10: 6 | B10: 45990 | D10: =+ROUND(G9*0.01,1) -> 332.9 | E10: =ROUNDUP($C$4/84,1) -> 421.5 | F10: =+ROUND(D10+E10,1) -> 754.4 | G10: =+ROUND(G9-E10,1) -> 32872.9
A11: 7 | B11: 46020 | D11: =+ROUND(G10*0.01,1) -> 328.7 | E11: =ROUNDUP($C$4/84,1) -> 421.5 | F11: =+ROUND(D11+E11,1) -> 750.2 | G11: =+ROUND(G10-E11,1) -> 32451.4
A12: 8 | B12: 46051 | D12: =+ROUND(G11*0.01,1) -> 324.5 | E12: =ROUNDUP($C$4/84,1) -> 421.5 | F12: =+ROUND(D12+E12,1) -> 746 | G12: =+ROUND(G11-E12,1) -> 32029.9
A13: 9 | B13: 46081 | D13: =+ROUND(G12*0.01,1) -> 320.3 | E13: =ROUNDUP($C$4/84,1) -> 421.5 | F13: =+ROUND(D13+E13,1) -> 741.8 | G13: =+ROUND(G12-E13,1) -> 31608.4
A14: 10 | B14: 46110 | D14: =+ROUND(G13*0.01,1) -> 316.1 | E14: =ROUNDUP($C$4/84,1) -> 421.5 | F14: =+ROUND(D14+E14,1) -> 737.6 | G14: =+ROUND(G13-E14,1) -> 31186.9
A15: 11 | B15: 46141 | D15: =+ROUND(G14*0.01,1) -> 311.9 | E15: =ROUNDUP($C$4/84,1) -> 421.5 | F15: =+ROUND(D15+E15,1) -> 733.4 | G15: =+ROUND(G14-E15,1) -> 30765.4
A16: 12 | B16: 46171 | D16: =+ROUND(G15*0.01,1) -> 307.7 | E16: =ROUNDUP($C$4/84,1) -> 421.5 | F16: =+ROUND(D16+E16,1) -> 729.2 | G16: =+ROUND(G15-E16,1) -> 30343.9
A17: 13 | B17: 46202 | D17: =+ROUND(G16*0.01,1) -> 303.4 | E17: =ROUNDUP($C$4/84,1) -> 421.5 | F17: =+ROUND(D17+E17,1) -> 724.9 | G17: =+ROUND(G16-E17,1) -> 29922.4
A18: 14 | B18: 46232 | D18: =+ROUND(G17*0.01,1) -> 299.2 | E18: =ROUNDUP($C$4/84,1) -> 421.5 | F18: =+ROUND(D18+E18,1) -> 720.7 | G18: =+ROUND(G17-E18,1) -> 29500.9
A19: 15 | B19: 46263 | D19: =+ROUND(G18*0.01,1) -> 295 | E19: =ROUNDUP($C$4/84,1) -> 421.5 | F19: =+ROUND(D19+E19,1) -> 716.5 | G19: =+ROUND(G18-E19,1) -> 29079.4
... A87: 83 | B87: 48333 | D87: =+ROUND(G86*0.01,1) -> 8.4 | E87: =ROUNDUP($C$4/84,1) -> 421.5 | F87: =+ROUND(D87+E87,1) -> 429.9 | G87: =+ROUND(G86-E87,1) -> 417.4
A88: 84 | B88: 48363 | D88: =+ROUND(G87*0.01,1) -> 4.2 | E88: =ROUNDUP($C$4/84,1)-4.1 -> 417.4 | F88: =+ROUND(D88+E88,1) -> 421.6 | G88: =+ROUND(G87-E88,1) -> 0
A89: TOTAL | D89: =+SUM(D5:D88) -> 15044 | E89: =+SUM(E5:E88) -> 35401.9 | F89: =+SUM(F5:F88) -> 50445.9

Sheet 7
A1: SOCIO: JORGE ARTURO CHAVEZ ALVAREZ
A2: JULIO 2025 - PRÉSTAMO
A3: PLAZO | B3: FECHA | C3: PRÉSTAMO S/. | D3: INTERES | E3: ABONO DE CAPITAL | F3: CUOTA | G3: SALDO
A4: 0 | B4: 45867 | C4: =+J7 -> 25395.8 | D4: 0.01 | G4: =+C4 -> 25395.8
A5: 1 | B5: 45898 | D5: =+ROUND(G4*0.01,1) -> 254 | E5: =ROUNDDOWN(C4/84,1) -> 302.3 | F5: =+ROUND(D5+E5,1) -> 556.3 | G5: =+ROUND(G4-E5,1) -> 25093.5 | I5: SALDO | J5: 26995.8
A6: 2 | B6: 45929 | D6: =+ROUND(G5*0.01,1) -> 250.9 | E6: =ROUNDDOWN($C$4/84,1) -> 302.3 | F6: =+ROUND(D6+E6,1) -> 553.2 | G6: =+ROUND(G5-E6,1) -> 24791.2 | I6: DEVOLUCIÓN | J6: -1600
A7: 3 | B7: 45959 | D7: =+ROUND(G6*0.01,1) -> 247.9 | E7: =ROUNDDOWN($C$4/84,1) -> 302.3 | F7: =+ROUND(D7+E7,1) -> 550.2 | G7: =+ROUND(G6-E7,1) -> 24488.9 | I7: TOTAL | J7: =+SUM(J5:J6) -> 25395.8
A8: 4 | B8: 45990 | D8: =+ROUND(G7*0.01,1) -> 244.9 | E8: =ROUNDDOWN($C$4/84,1) -> 302.3 | F8: =+ROUND(D8+E8,1) -> 547.2 | G8: =+ROUND(G7-E8,1) -> 24186.6
A9: 5 | B9: 46020 | D9: =+ROUND(G8*0.01,1) -> 241.9 | E9: =ROUNDDOWN($C$4/84,1) -> 302.3 | F9: =+ROUND(D9+E9,1) -> 544.2 | G9: =+ROUND(G8-E9,1) -> 23884.3
A10: 6 | B10: 46051 | D10: =+ROUND(G9*0.01,1) -> 238.8 | E10: =ROUNDDOWN($C$4/84,1) -> 302.3 | F10: =+ROUND(D10+E10,1) -> 541.1 | G10: =+ROUND(G9-E10,1) -> 23582
A11: 7 | B11: 46081 | D11: =+ROUND(G10*0.01,1) -> 235.8 | E11: =ROUNDDOWN($C$4/84,1) -> 302.3 | F11: =+ROUND(D11+E11,1) -> 538.1 | G11: =+ROUND(G10-E11,1) -> 23279.7
A12: 8 | B12: 46110 | D12: =+ROUND(G11*0.01,1) -> 232.8 | E12: =ROUNDDOWN($C$4/84,1) -> 302.3 | F12: =+ROUND(D12+E12,1) -> 535.1 | G12: =+ROUND(G11-E12,1) -> 22977.4
A13: 9 | B13: 46141 | D13: =+ROUND(G12*0.01,1) -> 229.8 | E13: =ROUNDDOWN($C$4/84,1) -> 302.3 | F13: =+ROUND(D13+E13,1) -> 532.1 | G13: =+ROUND(G12-E13,1) -> 22675.1
A14: 10 | B14: 46171 | D14: =+ROUND(G13*0.01,1) -> 226.8 | E14: =ROUNDDOWN($C$4/84,1) -> 302.3 | F14: =+ROUND(D14+E14,1) -> 529.1 | G14: =+ROUND(G13-E14,1) -> 22372.8
A15: 11 | B15: 46202 | D15: =+ROUND(G14*0.01,1) -> 223.7 | E15: =ROUNDDOWN($C$4/84,1) -> 302.3 | F15: =+ROUND(D15+E15,1) -> 526 | G15: =+ROUND(G14-E15,1) -> 22070.5
A16: 12 | B16: 46232 | D16: =+ROUND(G15*0.01,1) -> 220.7 | E16: =ROUNDDOWN($C$4/84,1) -> 302.3 | F16: =+ROUND(D16+E16,1) -> 523 | G16: =+ROUND(G15-E16,1) -> 21768.2
A17: 13 | B17: 46263 | D17: =+ROUND(G16*0.01,1) -> 217.7 | E17: =ROUNDDOWN($C$4/84,1) -> 302.3 | F17: =+ROUND(D17+E17,1) -> 520 | G17: =+ROUND(G16-E17,1) -> 21465.9
A18: 14 | B18: 46294 | D18: =+ROUND(G17*0.01,1) -> 214.7 | E18: =ROUNDDOWN($C$4/84,1) -> 302.3 | F18: =+ROUND(D18+E18,1) -> 517 | G18: =+ROUND(G17-E18,1) -> 21163.6
A19: 15 | B19: 46324 | D19: =+ROUND(G18*0.01,1) -> 211.6 | E19: =ROUNDDOWN($C$4/84,1) -> 302.3 | F19: =+ROUND(D19+E19,1) -> 513.9 | G19: =+ROUND(G18-E19,1) -> 20861.3
... A87: 83 | B87: 48394 | D87: =+ROUND(G86*0.01,1) -> 6.1 | E87: =ROUNDDOWN($C$4/84,1) -> 302.3 | F87: =+ROUND(D87+E87,1) -> 308.4 | G87: =+ROUND(G86-E87,1) -> 304.9
A88: 84 | B88: 48424 | D88: =+ROUND(G87*0.01,1) -> 3 | E88: =ROUNDDOWN($C$4/84,1)+2.6 -> 304.9 | F88: =+ROUND(D88+E88,1) -> 307.9 | G88: =+ROUND(G87-E88,1) -> 0
A89: TOTAL | D89: =+SUM(D5:D88) -> 10794.3 | E89: =+SUM(E5:E88) -> 25395.8 | F89: =+SUM(F5:F88) -> 36190.1

Sheet 8
A1: SOCIO: LUIS FERNANDO CHAVEZ ALVAREZ
A2: AGOSTO 2025 - PRÉSTAMO
A3: PLAZO | B3: FECHA | C3: PRÉSTAMO S/. | D3: INTERES | E3: ABONO DE CAPITAL | F3: CUOTA | G3: SALDO
A4: 0 | B4: 45898 | C4: =+J7 -> 15426.2 | D4: 0.01 | G4: =+C4 -> 15426.2
A5: 1 | B5: 45929 | D5: =+ROUND(G4*0.01,1) -> 154.3 | E5: =ROUNDDOWN($C$4/60,1) -> 257.1 | F5: =+ROUND(D5+E5,1) -> 411.4 | G5: =+ROUND(G4-E5,1) -> 15169.1 | I5: SALDO | J5: 12584.8
A6: 2 | B6: 45959 | D6: =+ROUND(G5*0.01,1) -> 151.7 | E6: =ROUNDDOWN($C$4/60,1) -> 257.1 | F6: =+ROUND(D6+E6,1) -> 408.8 | G6: =+ROUND(G5-E6,1) -> 14912 | I6: PRESTAMO | J6: 2841.4
A7: 3 | B7: 45990 | D7: =+ROUND(G6*0.01,1) -> 149.1 | E7: =ROUNDDOWN($C$4/60,1) -> 257.1 | F7: =+ROUND(D7+E7,1) -> 406.2 | G7: =+ROUND(G6-E7,1) -> 14654.9 | I7: TOTAL | J7: =+SUM(J5:J6) -> 15426.2
A8: 4 | B8: 46020 | D8: =+ROUND(G7*0.01,1) -> 146.5 | E8: =ROUNDDOWN($C$4/60,1) -> 257.1 | F8: =+ROUND(D8+E8,1) -> 403.6 | G8: =+ROUND(G7-E8,1) -> 14397.8
A9: 5 | B9: 46051 | D9: =+ROUND(G8*0.01,1) -> 144 | E9: =ROUNDDOWN($C$4/60,1) -> 257.1 | F9: =+ROUND(D9+E9,1) -> 401.1 | G9: =+ROUND(G8-E9,1) -> 14140.7 | I9: INTERES | J9: =SUM(D5:D10) -> 887
A10: 6 | B10: 46081 | D10: =+ROUND(G9*0.01,1) -> 141.4 | E10: =ROUNDDOWN($C$4/60,1) -> 257.1 | F10: =+ROUND(D10+E10,1) -> 398.5 | G10: =+ROUND(G9-E10,1) -> 13883.6 | I10: SALDO | J10: =G10 -> 13883.6
A11: 7 | B11: 46110 | D11: =+ROUND(G10*0.01,1) -> 138.8 | E11: =ROUNDDOWN($C$4/60,1) -> 257.1 | F11: =+ROUND(D11+E11,1) -> 395.9 | G11: =+ROUND(G10-E11,1) -> 13626.5
A12: 8 | B12: 46141 | D12: =+ROUND(G11*0.01,1) -> 136.3 | E12: =ROUNDDOWN($C$4/60,1) -> 257.1 | F12: =+ROUND(D12+E12,1) -> 393.4 | G12: =+ROUND(G11-E12,1) -> 13369.4
A13: 9 | B13: 46171 | D13: =+ROUND(G12*0.01,1) -> 133.7 | E13: =ROUNDDOWN($C$4/60,1) -> 257.1 | F13: =+ROUND(D13+E13,1) -> 390.8 | G13: =+ROUND(G12-E13,1) -> 13112.3
A14: 10 | B14: 46202 | D14: =+ROUND(G13*0.01,1) -> 131.1 | E14: =ROUNDDOWN($C$4/60,1) -> 257.1 | F14: =+ROUND(D14+E14,1) -> 388.2 | G14: =+ROUND(G13-E14,1) -> 12855.2
A15: 11 | B15: 46232 | D15: =+ROUND(G14*0.01,1) -> 128.6 | E15: =ROUNDDOWN($C$4/60,1) -> 257.1 | F15: =+ROUND(D15+E15,1) -> 385.7 | G15: =+ROUND(G14-E15,1) -> 12598.1
A16: 12 | B16: 46263 | D16: =+ROUND(G15*0.01,1) -> 126 | E16: =ROUNDDOWN($C$4/60,1) -> 257.1 | F16: =+ROUND(D16+E16,1) -> 383.1 | G16: =+ROUND(G15-E16,1) -> 12341
A17: 13 | B17: 46294 | D17: =+ROUND(G16*0.01,1) -> 123.4 | E17: =ROUNDDOWN($C$4/60,1) -> 257.1 | F17: =+ROUND(D17+E17,1) -> 380.5 | G17: =+ROUND(G16-E17,1) -> 12083.9
A18: 14 | B18: 46324 | D18: =+ROUND(G17*0.01,1) -> 120.8 | E18: =ROUNDDOWN($C$4/60,1) -> 257.1 | F18: =+ROUND(D18+E18,1) -> 377.9 | G18: =+ROUND(G17-E18,1) -> 11826.8
A19: 15 | B19: 46355 | D19: =+ROUND(G18*0.01,1) -> 118.3 | E19: =ROUNDDOWN($C$4/60,1) -> 257.1 | F19: =+ROUND(D19+E19,1) -> 375.4 | G19: =+ROUND(G18-E19,1) -> 11569.7
A20: 16 | B20: 46385 | D20: =+ROUND(G19*0.01,1) -> 115.7 | E20: =ROUNDDOWN($C$4/60,1) -> 257.1 | F20: =+ROUND(D20+E20,1) -> 372.8 | G20: =+ROUND(G19-E20,1) -> 11312.6
A21: 17 | B21: 46416 | D21: =+ROUND(G20*0.01,1) -> 113.1 | E21: =ROUNDDOWN($C$4/60,1) -> 257.1 | F21: =+ROUND(D21+E21,1) -> 370.2 | G21: =+ROUND(G20-E21,1) -> 11055.5
A22: 18 | B22: 46446 | D22: =+ROUND(G21*0.01,1) -> 110.6 | E22: =ROUNDDOWN($C$4/60,1) -> 257.1 | F22: =+ROUND(D22+E22,1) -> 367.7 | G22: =+ROUND(G21-E22,1) -> 10798.4
... A63: 59 | B63: 47693 | D63: =+ROUND(G62*0.01,1) -> 5.1 | E63: =ROUNDDOWN($C$4/60,1) -> 257.1 | F63: =+ROUND(D63+E63,1) -> 262.2 | G63: =+ROUND(G62-E63,1) -> 257.3
A64: 60 | B64: 47724 | D64: =+ROUND(G63*0.01,1) -> 2.6 | E64: =ROUNDDOWN($C$4/60,1)+0.2 -> 257.3 | F64: =+ROUND(D64+E64,1) -> 259.9 | G64: =+ROUND(G63-E64,1) -> 0
A65: TOTAL | D65: =+SUM(D5:D64) -> 4705.1 | E65: =+SUM(E5:E64) -> 15426.2 | F65: =+SUM(F5:F64) -> 20131.3
A67: FEBRERO 2026 - PRÉSTAMO
A68: PLAZO | B68: FECHA | C68: PRÉSTAMO S/. | D68: INTERES | E68: ABONO DE CAPITAL | F68: CUOTA | G68: SALDO
A69: 0 | B69: 45898 | C69: =+J72 -> 28883.6 | D69: 0.01 | G69: =+C69 -> 28883.6
A70: 1 | B70: 45929 | D70: =+ROUND(G69*0.01,1) -> 288.8 | E70: =ROUND($C$69/60,1) -> 481.4 | F70: =+ROUND(D70+E70,1) -> 770.2 | G70: =+ROUND(G69-E70,1) -> 28402.2 | I70: SALDO | J70: =J10 -> 13883.6
A71: 2 | B71: 45959 | D71: =+ROUND(G70*0.01,1) -> 284 | E71: =ROUND($C$69/60,1) -> 481.4 | F71: =+ROUND(D71+E71,1) -> 765.4 | G71: =+ROUND(G70-E71,1) -> 27920.8 | I71: PRESTAMO | J71: 15000
A72: 3 | B72: 45990 | D72: =+ROUND(G71*0.01,1) -> 279.2 | E72: =ROUND($C$69/60,1) -> 481.4 | F72: =+ROUND(D72+E72,1) -> 760.6 | G72: =+ROUND(G71-E72,1) -> 27439.4 | I72: TOTAL | J72: =+SUM(J70:J71) -> 28883.6
A73: 4 | B73: 46020 | D73: =+ROUND(G72*0.01,1) -> 274.4 | E73: =ROUND($C$69/60,1) -> 481.4 | F73: =+ROUND(D73+E73,1) -> 755.8 | G73: =+ROUND(G72-E73,1) -> 26958
A74: 5 | B74: 46051 | D74: =+ROUND(G73*0.01,1) -> 269.6 | E74: =ROUND($C$69/60,1) -> 481.4 | F74: =+ROUND(D74+E74,1) -> 751 | G74: =+ROUND(G73-E74,1) -> 26476.6
A75: 6 | B75: 46081 | D75: =+ROUND(G74*0.01,1) -> 264.8 | E75: =ROUND($C$69/60,1) -> 481.4 | F75: =+ROUND(D75+E75,1) -> 746.2 | G75: =+ROUND(G74-E75,1) -> 25995.2
A76: 7 | B76: 46110 | D76: =+ROUND(G75*0.01,1) -> 260 | E76: =ROUND($C$69/60,1) -> 481.4 | F76: =+ROUND(D76+E76,1) -> 741.4 | G76: =+ROUND(G75-E76,1) -> 25513.8
A77: 8 | B77: 46141 | D77: =+ROUND(G76*0.01,1) -> 255.1 | E77: =ROUND($C$69/60,1) -> 481.4 | F77: =+ROUND(D77+E77,1) -> 736.5 | G77: =+ROUND(G76-E77,1) -> 25032.4
A78: 9 | B78: 46171 | D78: =+ROUND(G77*0.01,1) -> 250.3 | E78: =ROUND($C$69/60,1) -> 481.4 | F78: =+ROUND(D78+E78,1) -> 731.7 | G78: =+ROUND(G77-E78,1) -> 24551
A79: 10 | B79: 46202 | D79: =+ROUND(G78*0.01,1) -> 245.5 | E79: =ROUND($C$69/60,1) -> 481.4 | F79: =+ROUND(D79+E79,1) -> 726.9 | G79: =+ROUND(G78-E79,1) -> 24069.6
A80: 11 | B80: 46232 | D80: =+ROUND(G79*0.01,1) -> 240.7 | E80: =ROUND($C$69/60,1) -> 481.4 | F80: =+ROUND(D80+E80,1) -> 722.1 | G80: =+ROUND(G79-E80,1) -> 23588.2
A81: 12 | B81: 46263 | D81: =+ROUND(G80*0.01,1) -> 235.9 | E81: =ROUND($C$69/60,1) -> 481.4 | F81: =+ROUND(D81+E81,1) -> 717.3 | G81: =+ROUND(G80-E81,1) -> 23106.8
A82: 13 | B82: 46294 | D82: =+ROUND(G81*0.01,1) -> 231.1 | E82: =ROUND($C$69/60,1) -> 481.4 | F82: =+ROUND(D82+E82,1) -> 712.5 | G82: =+ROUND(G81-E82,1) -> 22625.4
A83: 14 | B83: 46324 | D83: =+ROUND(G82*0.01,1) -> 226.3 | E83: =ROUND($C$69/60,1) -> 481.4 | F83: =+ROUND(D83+E83,1) -> 707.7 | G83: =+ROUND(G82-E83,1) -> 22144
A84: 15 | B84: 46355 | D84: =+ROUND(G83*0.01,1) -> 221.4 | E84: =ROUND($C$69/60,1) -> 481.4 | F84: =+ROUND(D84+E84,1) -> 702.8 | G84: =+ROUND(G83-E84,1) -> 21662.6
... A128: 59 | B128: 47693 | D128: =+ROUND(G127*0.01,1) -> 9.6 | E128: =ROUND($C$69/60,1) -> 481.4 | F128: =+ROUND(D128+E128,1) -> 491 | G128: =+ROUND(G127-E128,1) -> 481
A129: 60 | B129: 47724 | D129: =+ROUND(G128*0.01,1) -> 4.8 | E129: =ROUND($C$69/60,1)-0.4 -> 481 | F129: =+ROUND(D129+E129,1) -> 485.8 | G129: =+ROUND(G128-E129,1) -> 0
A130: TOTAL | D130: =+SUM(D70:D129) -> 8809.4 | E130: =+SUM(E70:E129) -> 28883.6 | F130: =+SUM(F70:F129) -> 37693

Sheet 9
A1: SOCIO: JORGE EMILIANO CHAVEZ CHAVEZ
A2: JUNIO 2025 - PRÉSTAMO
A3: PLAZO | B3: FECHA | C3: PRÉSTAMO S/. | D3: INTERES | E3: ABONO DE CAPITAL | F3: CUOTA | G3: SALDO
A4: 0 | B4: 45837 | C4: =+J7 -> 46124.4 | D4: 0.01 | G4: =+C4 -> 46124.4
A5: 1 | B5: 45867 | D5: =+ROUND(G4*0.01,1) -> 461.2 | E5: =ROUNDDOWN(C4/84,1) -> 549.1 | F5: =+ROUND(D5+E5,1) -> 1010.3 | G5: =+ROUND(G4-E5,1) -> 45575.3 | I5: SALDO | J5: 51124.4
A6: 2 | B6: 45898 | D6: =+ROUND(G5*0.01,1) -> 455.8 | E6: =ROUNDDOWN($C$4/84,1) -> 549.1 | F6: =+ROUND(D6+E6,1) -> 1004.9 | G6: =+ROUND(G5-E6,1) -> 45026.2 | I6: DEVOLUCIÓN | J6: -5000
A7: 3 | B7: 45929 | D7: =+ROUND(G6*0.01,1) -> 450.3 | E7: =ROUNDDOWN($C$4/84,1) -> 549.1 | F7: =+ROUND(D7+E7,1) -> 999.4 | G7: =+ROUND(G6-E7,1) -> 44477.1 | I7: TOTAL | J7: =+SUM(J5:J6) -> 46124.4
A8: 4 | B8: 45959 | D8: =+ROUND(G7*0.01,1) -> 444.8 | E8: =ROUNDDOWN($C$4/84,1) -> 549.1 | F8: =+ROUND(D8+E8,1) -> 993.9 | G8: =+ROUND(G7-E8,1) -> 43928
A9: 5 | B9: 45990 | D9: =+ROUND(G8*0.01,1) -> 439.3 | E9: =ROUNDDOWN($C$4/84,1) -> 549.1 | F9: =+ROUND(D9+E9,1) -> 988.4 | G9: =+ROUND(G8-E9,1) -> 43378.9
A10: 6 | B10: 46020 | D10: =+ROUND(G9*0.01,1) -> 433.8 | E10: =ROUNDDOWN($C$4/84,1) -> 549.1 | F10: =+ROUND(D10+E10,1) -> 982.9 | G10: =+ROUND(G9-E10,1) -> 42829.8
A11: 7 | B11: 46051 | D11: =+ROUND(G10*0.01,1) -> 428.3 | E11: =ROUNDDOWN($C$4/84,1) -> 549.1 | F11: =+ROUND(D11+E11,1) -> 977.4 | G11: =+ROUND(G10-E11,1) -> 42280.7
A12: 8 | B12: 46081 | D12: =+ROUND(G11*0.01,1) -> 422.8 | E12: =ROUNDDOWN($C$4/84,1) -> 549.1 | F12: =+ROUND(D12+E12,1) -> 971.9 | G12: =+ROUND(G11-E12,1) -> 41731.6
A13: 9 | B13: 46110 | D13: =+ROUND(G12*0.01,1) -> 417.3 | E13: =ROUNDDOWN($C$4/84,1) -> 549.1 | F13: =+ROUND(D13+E13,1) -> 966.4 | G13: =+ROUND(G12-E13,1) -> 41182.5
A14: 10 | B14: 46141 | D14: =+ROUND(G13*0.01,1) -> 411.8 | E14: =ROUNDDOWN($C$4/84,1) -> 549.1 | F14: =+ROUND(D14+E14,1) -> 960.9 | G14: =+ROUND(G13-E14,1) -> 40633.4
A15: 11 | B15: 46171 | D15: =+ROUND(G14*0.01,1) -> 406.3 | E15: =ROUNDDOWN($C$4/84,1) -> 549.1 | F15: =+ROUND(D15+E15,1) -> 955.4 | G15: =+ROUND(G14-E15,1) -> 40084.3
A16: 12 | B16: 46202 | D16: =+ROUND(G15*0.01,1) -> 400.8 | E16: =ROUNDDOWN($C$4/84,1) -> 549.1 | F16: =+ROUND(D16+E16,1) -> 949.9 | G16: =+ROUND(G15-E16,1) -> 39535.2
A17: 13 | B17: 46232 | D17: =+ROUND(G16*0.01,1) -> 395.4 | E17: =ROUNDDOWN($C$4/84,1) -> 549.1 | F17: =+ROUND(D17+E17,1) -> 944.5 | G17: =+ROUND(G16-E17,1) -> 38986.1
A18: 14 | B18: 46263 | D18: =+ROUND(G17*0.01,1) -> 389.9 | E18: =ROUNDDOWN($C$4/84,1) -> 549.1 | F18: =+ROUND(D18+E18,1) -> 939 | G18: =+ROUND(G17-E18,1) -> 38437
A19: 15 | B19: 46294 | D19: =+ROUND(G18*0.01,1) -> 384.4 | E19: =ROUNDDOWN($C$4/84,1) -> 549.1 | F19: =+ROUND(D19+E19,1) -> 933.5 | G19: =+ROUND(G18-E19,1) -> 37887.9
... A88: 84 | B88: 48394 | D88: =+ROUND(G87*0.01,1) -> 5.5 | E88: =ROUNDDOWN($C$4/84,1) -> 549.1 | F88: =+ROUND(D88+E88,1) -> 554.6 | G88: =+ROUND(G87-E88,1) -> 0
A89: TOTAL | D89: =+SUM(D5:D88) -> 19603 | E89: =+SUM(E5:E88) -> 46124.4 | F89: =+SUM(F5:F88) -> 65727.4

Sheet 10
A1: SOCIO: CHAVEZ CHAVEZ PEDRO
A2: AGOSTO 2024 - PRÉSTAMO
A3: PLAZO | B3: FECHA | C3: PRÉSTAMO S/. | D3: INTERES | E3: ABONO DE CAPITAL | F3: CUOTA | G3: SALDO
A4: 0 | B4: 45533 | C4: =+J7 -> 14825.9 | D4: 0.01 | G4: =+C4 -> 14825.9
A5: 1 | B5: 45564 | D5: =+ROUND(G4*0.01,1) -> 148.3 | E5: =ROUNDUP($C$4/48,1) -> 308.9 | F5: =+ROUND(D5+E5,1) -> 457.2 | G5: =+ROUND(G4-E5,1) -> 14517 | I5: SALDO | J5: 3039.9
A6: 2 | B6: 45594 | D6: =+ROUND(G5*0.01,1) -> 145.2 | E6: =ROUNDUP($C$4/48,1) -> 308.9 | F6: =+ROUND(D6+E6,1) -> 454.1 | G6: =+ROUND(G5-E6,1) -> 14208.1 | I6: PRESTAMO | J6: 11786
A7: 3 | B7: 45625 | D7: =+ROUND(G6*0.01,1) -> 142.1 | E7: =ROUNDUP($C$4/48,1) -> 308.9 | F7: =+ROUND(D7+E7,1) -> 451 | G7: =+ROUND(G6-E7,1) -> 13899.2 | I7: TOTAL | J7: =+SUM(J5:J6) -> 14825.9
A8: 4 | B8: 45655 | D8: =+ROUND(G7*0.01,1) -> 139 | E8: =ROUNDUP($C$4/48,1) -> 308.9 | F8: =+ROUND(D8+E8,1) -> 447.9 | G8: =+ROUND(G7-E8,1) -> 13590.3
A9: 5 | B9: 45686 | D9: =+ROUND(G8*0.01,1) -> 135.9 | E9: =ROUNDUP($C$4/48,1) -> 308.9 | F9: =+ROUND(D9+E9,1) -> 444.8 | G9: =+ROUND(G8-E9,1) -> 13281.4
A10: 6 | B10: 45716 | D10: =+ROUND(G9*0.01,1) -> 132.8 | E10: =ROUNDUP($C$4/48,1) -> 308.9 | F10: =+ROUND(D10+E10,1) -> 441.7 | G10: =+ROUND(G9-E10,1) -> 12972.5
A11: 7 | B11: 45745 | D11: =+ROUND(G10*0.01,1) -> 129.7 | E11: =ROUNDUP($C$4/48,1) -> 308.9 | F11: =+ROUND(D11+E11,1) -> 438.6 | G11: =+ROUND(G10-E11,1) -> 12663.6
A12: 8 | B12: 45776 | D12: =+ROUND(G11*0.01,1) -> 126.6 | E12: =ROUNDUP($C$4/48,1) -> 308.9 | F12: =+ROUND(D12+E12,1) -> 435.5 | G12: =+ROUND(G11-E12,1) -> 12354.7
A13: 9 | B13: 45806 | D13: =+ROUND(G12*0.01,1) -> 123.5 | E13: =ROUNDUP($C$4/48,1) -> 308.9 | F13: =+ROUND(D13+E13,1) -> 432.4 | G13: =+ROUND(G12-E13,1) -> 12045.8
A14: 10 | B14: 45837 | D14: =+ROUND(G13*0.01,1) -> 120.5 | E14: =ROUNDUP($C$4/48,1) -> 308.9 | F14: =+ROUND(D14+E14,1) -> 429.4 | G14: =+ROUND(G13-E14,1) -> 11736.9
A15: 11 | B15: 45867 | D15: =+ROUND(G14*0.01,1) -> 117.4 | E15: =ROUNDUP($C$4/48,1) -> 308.9 | F15: =+ROUND(D15+E15,1) -> 426.3 | G15: =+ROUND(G14-E15,1) -> 11428
A16: 12 | B16: 45898 | D16: =+ROUND(G15*0.01,1) -> 114.3 | E16: =ROUNDUP($C$4/48,1) -> 308.9 | F16: =+ROUND(D16+E16,1) -> 423.2 | G16: =+ROUND(G15-E16,1) -> 11119.1
A17: 13 | B17: 45929 | D17: =+ROUND(G16*0.01,1) -> 111.2 | E17: =ROUNDUP($C$4/48,1) -> 308.9 | F17: =+ROUND(D17+E17,1) -> 420.1 | G17: =+ROUND(G16-E17,1) -> 10810.2 | I17: INTERES | J17: =SUM(D5:D18) -> 1794.6
A18: 14 | B18: 45959 | D18: =+ROUND(G17*0.01,1) -> 108.1 | E18: =ROUNDUP($C$4/48,1) -> 308.9 | F18: =+ROUND(D18+E18,1) -> 417 | G18: =+ROUND(G17-E18,1) -> 10501.3 | I18: SALDO | J18: =G18 -> 10501.3
A19: 15 | B19: 45990 | D19: =+ROUND(G18*0.01,1) -> 105 | E19: =ROUNDUP($C$4/48,1) -> 308.9 | F19: =+ROUND(D19+E19,1) -> 413.9 | G19: =+ROUND(G18-E19,1) -> 10192.4
A20: 16 | B20: 46020 | D20: =+ROUND(G19*0.01,1) -> 101.9 | E20: =ROUNDUP($C$4/48,1) -> 308.9 | F20: =+ROUND(D20+E20,1) -> 410.8 | G20: =+ROUND(G19-E20,1) -> 9883.5
A21: 17 | B21: 46051 | D21: =+ROUND(G20*0.01,1) -> 98.8 | E21: =ROUNDUP($C$4/48,1) -> 308.9 | F21: =+ROUND(D21+E21,1) -> 407.7 | G21: =+ROUND(G20-E21,1) -> 9574.6
A22: 18 | B22: 46081 | D22: =+ROUND(G21*0.01,1) -> 95.7 | E22: =ROUNDUP($C$4/48,1) -> 308.9 | F22: =+ROUND(D22+E22,1) -> 404.6 | G22: =+ROUND(G21-E22,1) -> 9265.7
A23: 19 | B23: 46110 | D23: =+ROUND(G22*0.01,1) -> 92.7 | E23: =ROUNDUP($C$4/48,1) -> 308.9 | F23: =+ROUND(D23+E23,1) -> 401.6 | G23: =+ROUND(G22-E23,1) -> 8956.8
A24: 20 | B24: 46141 | D24: =+ROUND(G23*0.01,1) -> 89.6 | E24: =ROUNDUP($C$4/48,1) -> 308.9 | F24: =+ROUND(D24+E24,1) -> 398.5 | G24: =+ROUND(G23-E24,1) -> 8647.9
A25: 21 | B25: 46171 | D25: =+ROUND(G24*0.01,1) -> 86.5 | E25: =ROUNDUP($C$4/48,1) -> 308.9 | F25: =+ROUND(D25+E25,1) -> 395.4 | G25: =+ROUND(G24-E25,1) -> 8339
A26: 22 | B26: 46202 | D26: =+ROUND(G25*0.01,1) -> 83.4 | E26: =ROUNDUP($C$4/48,1) -> 308.9 | F26: =+ROUND(D26+E26,1) -> 392.3 | G26: =+ROUND(G25-E26,1) -> 8030.1
A27: 23 | B27: 46232 | D27: =+ROUND(G26*0.01,1) -> 80.3 | E27: =ROUNDUP($C$4/48,1) -> 308.9 | F27: =+ROUND(D27+E27,1) -> 389.2 | G27: =+ROUND(G26-E27,1) -> 7721.2
A28: 24 | B28: 46263 | D28: =+ROUND(G27*0.01,1) -> 77.2 | E28: =ROUNDUP($C$4/48,1) -> 308.9 | F28: =+ROUND(D28+E28,1) -> 386.1 | G28: =+ROUND(G27-E28,1) -> 7412.3
A29: 25 | B29: 46294 | D29: =+ROUND(G28*0.01,1) -> 74.1 | E29: =ROUNDUP($C$4/48,1) -> 308.9 | F29: =+ROUND(D29+E29,1) -> 383 | G29: =+ROUND(G28-E29,1) -> 7103.4
A30: 26 | B30: 46324 | D30: =+ROUND(G29*0.01,1) -> 71 | E30: =ROUNDUP($C$4/48,1) -> 308.9 | F30: =+ROUND(D30+E30,1) -> 379.9 | G30: =+ROUND(G29-E30,1) -> 6794.5
... A51: 47 | B51: 46963 | D51: =+ROUND(G50*0.01,1) -> 6.2 | E51: =ROUNDUP($C$4/48,1) -> 308.9 | F51: =+ROUND(D51+E51,1) -> 315.1 | G51: =+ROUND(G50-E51,1) -> 307.6
A52: 48 | B52: 46994 | D52: =+ROUND(G51*0.01,1) -> 3.1 | E52: =ROUNDUP($C$4/48,1)-1.3 -> 307.6 | F52: =+ROUND(D52+E52,1) -> 310.7 | G52: =+ROUND(G51-E52,1) -> 0
A53: TOTAL | D53: =+SUM(D5:D52) -> 3632.1 | E53: =+SUM(E5:E52) -> 14825.9 | F53: =+SUM(F5:F52) -> 18458
A55: SOCIO: CHAVEZ CHAVEZ PEDRO
A56: OCTUBRE 2025 - PRÉSTAMO
A57: PLAZO | B57: FECHA | C57: PRÉSTAMO S/. | D57: INTERES | E57: ABONO DE CAPITAL | F57: CUOTA | G57: SALDO
A58: 0 | B58: 45959 | C58: =+J61 -> 20501.3 | D58: 0.01 | G58: =+C58 -> 20501.3
A59: 1 | B59: 45990 | D59: =+ROUND(G58*0.01,1) -> 205 | E59: =ROUNDUP($C$58/36,1) -> 569.5 | F59: =+ROUND(D59+E59,1) -> 774.5 | G59: =+ROUND(G58-E59,1) -> 19931.8 | I59: SALDO | J59: =G18 -> 10501.3
A60: 2 | B60: 46020 | D60: =+ROUND(G59*0.01,1) -> 199.3 | E60: =ROUNDUP($C$58/36,1) -> 569.5 | F60: =+ROUND(D60+E60,1) -> 768.8 | G60: =+ROUND(G59-E60,1) -> 19362.3 | I60: PRESTAMO | J60: 10000
A61: 3 | B61: 46051 | D61: =+ROUND(G60*0.01,1) -> 193.6 | E61: =ROUNDUP($C$58/36,1) -> 569.5 | F61: =+ROUND(D61+E61,1) -> 763.1 | G61: =+ROUND(G60-E61,1) -> 18792.8 | I61: TOTAL | J61: =+SUM(J59:J60) -> 20501.3
A62: 4 | B62: 46081 | D62: =+ROUND(G61*0.01,1) -> 187.9 | E62: =ROUNDUP($C$58/36,1) -> 569.5 | F62: =+ROUND(D62+E62,1) -> 757.4 | G62: =+ROUND(G61-E62,1) -> 18223.3
A63: 5 | B63: 46110 | D63: =+ROUND(G62*0.01,1) -> 182.2 | E63: =ROUNDUP($C$58/36,1) -> 569.5 | F63: =+ROUND(D63+E63,1) -> 751.7 | G63: =+ROUND(G62-E63,1) -> 17653.8
A64: 6 | B64: 46141 | D64: =+ROUND(G63*0.01,1) -> 176.5 | E64: =ROUNDUP($C$58/36,1) -> 569.5 | F64: =+ROUND(D64+E64,1) -> 746 | G64: =+ROUND(G63-E64,1) -> 17084.3
A65: 7 | B65: 46171 | D65: =+ROUND(G64*0.01,1) -> 170.8 | E65: =ROUNDUP($C$58/36,1) -> 569.5 | F65: =+ROUND(D65+E65,1) -> 740.3 | G65: =+ROUND(G64-E65,1) -> 16514.8
A66: 8 | B66: 46202 | D66: =+ROUND(G65*0.01,1) -> 165.1 | E66: =ROUNDUP($C$58/36,1) -> 569.5 | F66: =+ROUND(D66+E66,1) -> 734.6 | G66: =+ROUND(G65-E66,1) -> 15945.3
A67: 9 | B67: 46232 | D67: =+ROUND(G66*0.01,1) -> 159.5 | E67: =ROUNDUP($C$58/36,1) -> 569.5 | F67: =+ROUND(D67+E67,1) -> 729 | G67: =+ROUND(G66-E67,1) -> 15375.8
A68: 10 | B68: 46263 | D68: =+ROUND(G67*0.01,1) -> 153.8 | E68: =ROUNDUP($C$58/36,1) -> 569.5 | F68: =+ROUND(D68+E68,1) -> 723.3 | G68: =+ROUND(G67-E68,1) -> 14806.3
A69: 11 | B69: 46294 | D69: =+ROUND(G68*0.01,1) -> 148.1 | E69: =ROUNDUP($C$58/36,1) -> 569.5 | F69: =+ROUND(D69+E69,1) -> 717.6 | G69: =+ROUND(G68-E69,1) -> 14236.8
A70: 12 | B70: 46324 | D70: =+ROUND(G69*0.01,1) -> 142.4 | E70: =ROUNDUP($C$58/36,1) -> 569.5 | F70: =+ROUND(D70+E70,1) -> 711.9 | G70: =+ROUND(G69-E70,1) -> 13667.3
A71: 13 | B71: 46355 | D71: =+ROUND(G70*0.01,1) -> 136.7 | E71: =ROUNDUP($C$58/36,1) -> 569.5 | F71: =+ROUND(D71+E71,1) -> 706.2 | G71: =+ROUND(G70-E71,1) -> 13097.8
A72: 14 | B72: 46385 | D72: =+ROUND(G71*0.01,1) -> 131 | E72: =ROUNDUP($C$58/36,1) -> 569.5 | F72: =+ROUND(D72+E72,1) -> 700.5 | G72: =+ROUND(G71-E72,1) -> 12528.3
A73: 15 | B73: 46416 | D73: =+ROUND(G72*0.01,1) -> 125.3 | E73: =ROUNDUP($C$58/36,1) -> 569.5 | F73: =+ROUND(D73+E73,1) -> 694.8 | G73: =+ROUND(G72-E73,1) -> 11958.8
... A93: 35 | B93: 47025 | D93: =+ROUND(G92*0.01,1) -> 11.4 | E93: =ROUNDUP($C$58/36,1) -> 569.5 | F93: =+ROUND(D93+E93,1) -> 580.9 | G93: =+ROUND(G92-E93,1) -> 568.8
A94: 36 | B94: 47055 | D94: =+ROUND(G93*0.01,1) -> 5.7 | E94: =ROUNDUP($C$58/36,1)-0.7 -> 568.8 | F94: =+ROUND(D94+E94,1) -> 574.5 | G94: =+ROUND(G93-E94,1) -> 0
A95: TOTAL | D95: =+SUM(D59:D94) -> 3792.6 | E95: =+SUM(E59:E94) -> 20501.3 | F95: =+SUM(F59:F94) -> 24293.9

Sheet 11
A1: SOCIO: EDWIN FELIX CHAVEZ MARIN
A2: SETIEMBRE 2025 - PRÉSTAMO
A3: PLAZO | B3: FECHA | C3: PRÉSTAMO S/. | D3: INTERES | E3: ABONO DE CAPITAL | F3: CUOTA | G3: SALDO
A4: 0 | B4: 45929 | C4: =+J7 -> 52744.1 | D4: 0.01 | G4: =+C4 -> 52744.1
A5: 1 | B5: 45959 | D5: =+ROUND(G4*0.01,1) -> 527.4 | E5: =ROUNDDOWN(C4/84,1) -> 627.9 | F5: =+ROUND(D5+E5,1) -> 1155.3 | G5: =+ROUND(G4-E5,1) -> 52116.2 | I5: SALDO | J5: 42953
A6: 2 | B6: 45990 | D6: =+ROUND(G5*0.01,1) -> 521.2 | E6: =ROUNDDOWN($C$4/84,1) -> 627.9 | F6: =+ROUND(D6+E6,1) -> 1149.1 | G6: =+ROUND(G5-E6,1) -> 51488.3 | I6: PRESTAMO | J6: 9791.1
A7: 3 | B7: 46020 | D7: =+ROUND(G6*0.01,1) -> 514.9 | E7: =ROUNDDOWN($C$4/84,1) -> 627.9 | F7: =+ROUND(D7+E7,1) -> 1142.8 | G7: =+ROUND(G6-E7,1) -> 50860.4 | I7: TOTAL | J7: =+SUM(J5:J6) -> 52744.1
A8: 4 | B8: 46051 | D8: =+ROUND(G7*0.01,1) -> 508.6 | E8: =ROUNDDOWN($C$4/84,1) -> 627.9 | F8: =+ROUND(D8+E8,1) -> 1136.5 | G8: =+ROUND(G7-E8,1) -> 50232.5
A9: 5 | B9: 46081 | D9: =+ROUND(G8*0.01,1) -> 502.3 | E9: =ROUNDDOWN($C$4/84,1) -> 627.9 | F9: =+ROUND(D9+E9,1) -> 1130.2 | G9: =+ROUND(G8-E9,1) -> 49604.6
A10: 6 | B10: 46110 | D10: =+ROUND(G9*0.01,1) -> 496 | E10: =ROUNDDOWN($C$4/84,1) -> 627.9 | F10: =+ROUND(D10+E10,1) -> 1123.9 | G10: =+ROUND(G9-E10,1) -> 48976.7
A11: 7 | B11: 46141 | D11: =+ROUND(G10*0.01,1) -> 489.8 | E11: =ROUNDDOWN($C$4/84,1) -> 627.9 | F11: =+ROUND(D11+E11,1) -> 1117.7 | G11: =+ROUND(G10-E11,1) -> 48348.8
A12: 8 | B12: 46171 | D12: =+ROUND(G11*0.01,1) -> 483.5 | E12: =ROUNDDOWN($C$4/84,1) -> 627.9 | F12: =+ROUND(D12+E12,1) -> 1111.4 | G12: =+ROUND(G11-E12,1) -> 47720.9
A13: 9 | B13: 46202 | D13: =+ROUND(G12*0.01,1) -> 477.2 | E13: =ROUNDDOWN($C$4/84,1) -> 627.9 | F13: =+ROUND(D13+E13,1) -> 1105.1 | G13: =+ROUND(G12-E13,1) -> 47093
A14: 10 | B14: 46232 | D14: =+ROUND(G13*0.01,1) -> 470.9 | E14: =ROUNDDOWN($C$4/84,1) -> 627.9 | F14: =+ROUND(D14+E14,1) -> 1098.8 | G14: =+ROUND(G13-E14,1) -> 46465.1
A15: 11 | B15: 46263 | D15: =+ROUND(G14*0.01,1) -> 464.7 | E15: =ROUNDDOWN($C$4/84,1) -> 627.9 | F15: =+ROUND(D15+E15,1) -> 1092.6 | G15: =+ROUND(G14-E15,1) -> 45837.2
A16: 12 | B16: 46294 | D16: =+ROUND(G15*0.01,1) -> 458.4 | E16: =ROUNDDOWN($C$4/84,1) -> 627.9 | F16: =+ROUND(D16+E16,1) -> 1086.3 | G16: =+ROUND(G15-E16,1) -> 45209.3
A17: 13 | B17: 46324 | D17: =+ROUND(G16*0.01,1) -> 452.1 | E17: =ROUNDDOWN($C$4/84,1) -> 627.9 | F17: =+ROUND(D17+E17,1) -> 1080 | G17: =+ROUND(G16-E17,1) -> 44581.4
A18: 14 | B18: 46355 | D18: =+ROUND(G17*0.01,1) -> 445.8 | E18: =ROUNDDOWN($C$4/84,1) -> 627.9 | F18: =+ROUND(D18+E18,1) -> 1073.7 | G18: =+ROUND(G17-E18,1) -> 43953.5
A19: 15 | B19: 46385 | D19: =+ROUND(G18*0.01,1) -> 439.5 | E19: =ROUNDDOWN($C$4/84,1) -> 627.9 | F19: =+ROUND(D19+E19,1) -> 1067.4 | G19: =+ROUND(G18-E19,1) -> 43325.6
... A87: 83 | B87: 48455 | D87: =+ROUND(G86*0.01,1) -> 12.6 | E87: =ROUNDDOWN($C$4/84,1) -> 627.9 | F87: =+ROUND(D87+E87,1) -> 640.5 | G87: =+ROUND(G86-E87,1) -> 628.4
A88: 84 | B88: 48486 | D88: =+ROUND(G87*0.01,1) -> 6.3 | E88: =ROUNDDOWN($C$4/84,1)+0.5 -> 628.4 | F88: =+ROUND(D88+E88,1) -> 634.7 | G88: =+ROUND(G87-E88,1) -> 0
A89: TOTAL | D89: =+SUM(D5:D88) -> 22416.5 | E89: =+SUM(E5:E88) -> 52744.1 | F89: =+SUM(F5:F88) -> 75160.6

Sheet 12
A1: SOCIO: MELBA GLADIS CHAVEZ QUEVEDO
A2: OCTUBRE 2024 - PRÉSTAMO
A3: PLAZO | B3: FECHA | C3: PRÉSTAMO S/. | D3: INTERES | E3: ABONO DE CAPITAL | F3: CUOTA | G3: SALDO
A4: 0 | B4: 45594 | C4: =+J6 -> 14320.9 | D4: 0.01 | G4: =+C4 -> 14320.9
A5: 1 | B5: 45625 | D5: =+ROUND(G4*0.01,1) -> 143.2 | E5: =ROUNDUP($C$4/60,1) -> 238.7 | F5: =+ROUND(D5+E5,1) -> 381.9 | G5: =+ROUND(G4-E5,1) -> 14082.2 | I5: PRÉSTAMO | J5: 14320.9
A6: 2 | B6: 45655 | D6: =+ROUND(G5*0.01,1) -> 140.8 | E6: =ROUNDUP($C$4/60,1) -> 238.7 | F6: =+ROUND(D6+E6,1) -> 379.5 | G6: =+ROUND(G5-E6,1) -> 13843.5 | I6: TOTAL | J6: =+SUM(J5) -> 14320.9
A7: 3 | B7: 45686 | D7: =+ROUND(G6*0.01,1) -> 138.4 | E7: =ROUNDUP($C$4/60,1) -> 238.7 | F7: =+ROUND(D7+E7,1) -> 377.1 | G7: =+ROUND(G6-E7,1) -> 13604.8
A8: 4 | B8: 45716 | D8: =+ROUND(G7*0.01,1) -> 136 | E8: =ROUNDUP($C$4/60,1) -> 238.7 | F8: =+ROUND(D8+E8,1) -> 374.7 | G8: =+ROUND(G7-E8,1) -> 13366.1
A9: 5 | B9: 45745 | D9: =+ROUND(G8*0.01,1) -> 133.7 | E9: =ROUNDUP($C$4/60,1) -> 238.7 | F9: =+ROUND(D9+E9,1) -> 372.4 | G9: =+ROUND(G8-E9,1) -> 13127.4
A10: 6 | B10: 45776 | D10: =+ROUND(G9*0.01,1) -> 131.3 | E10: =ROUNDUP($C$4/60,1) -> 238.7 | F10: =+ROUND(D10+E10,1) -> 370 | G10: =+ROUND(G9-E10,1) -> 12888.7
A11: 7 | B11: 45806 | D11: =+ROUND(G10*0.01,1) -> 128.9 | E11: =ROUNDUP($C$4/60,1) -> 238.7 | F11: =+ROUND(D11+E11,1) -> 367.6 | G11: =+ROUND(G10-E11,1) -> 12650
A12: 8 | B12: 45837 | D12: =+ROUND(G11*0.01,1) -> 126.5 | E12: =ROUNDUP($C$4/60,1) -> 238.7 | F12: =+ROUND(D12+E12,1) -> 365.2 | G12: =+ROUND(G11-E12,1) -> 12411.3
A13: 9 | B13: 45867 | D13: =+ROUND(G12*0.01,1) -> 124.1 | E13: =ROUNDUP($C$4/60,1) -> 238.7 | F13: =+ROUND(D13+E13,1) -> 362.8 | G13: =+ROUND(G12-E13,1) -> 12172.6
A14: 10 | B14: 45898 | D14: =+ROUND(G13*0.01,1) -> 121.7 | E14: =ROUNDUP($C$4/60,1) -> 238.7 | F14: =+ROUND(D14+E14,1) -> 360.4 | G14: =+ROUND(G13-E14,1) -> 11933.9
A15: 11 | B15: 45929 | D15: =+ROUND(G14*0.01,1) -> 119.3 | E15: =ROUNDUP($C$4/60,1) -> 238.7 | F15: =+ROUND(D15+E15,1) -> 358 | G15: =+ROUND(G14-E15,1) -> 11695.2
A16: 12 | B16: 45959 | D16: =+ROUND(G15*0.01,1) -> 117 | E16: =ROUNDUP($C$4/60,1) -> 238.7 | F16: =+ROUND(D16+E16,1) -> 355.7 | G16: =+ROUND(G15-E16,1) -> 11456.5
A17: 13 | B17: 45990 | D17: =+ROUND(G16*0.01,1) -> 114.6 | E17: =ROUNDUP($C$4/60,1) -> 238.7 | F17: =+ROUND(D17+E17,1) -> 353.3 | G17: =+ROUND(G16-E17,1) -> 11217.8
A18: 14 | B18: 46020 | D18: =+ROUND(G17*0.01,1) -> 112.2 | E18: =ROUNDUP($C$4/60,1) -> 238.7 | F18: =+ROUND(D18+E18,1) -> 350.9 | G18: =+ROUND(G17-E18,1) -> 10979.1 | I18: INTERES | J18: =SUM(D5:D19) -> 1897.5
A19: 15 | B19: 46051 | D19: =+ROUND(G18*0.01,1) -> 109.8 | E19: =ROUNDUP($C$4/60,1) -> 238.7 | F19: =+ROUND(D19+E19,1) -> 348.5 | G19: =+ROUND(G18-E19,1) -> 10740.4 | I19: SALDO | J19: =G19 -> 10740.4
A20: 16 | B20: 46081 | D20: =+ROUND(G19*0.01,1) -> 107.4 | E20: =ROUNDUP($C$4/60,1) -> 238.7 | F20: =+ROUND(D20+E20,1) -> 346.1 | G20: =+ROUND(G19-E20,1) -> 10501.7
A21: 17 | B21: 46110 | D21: =+ROUND(G20*0.01,1) -> 105 | E21: =ROUNDUP($C$4/60,1) -> 238.7 | F21: =+ROUND(D21+E21,1) -> 343.7 | G21: =+ROUND(G20-E21,1) -> 10263
A22: 18 | B22: 46141 | D22: =+ROUND(G21*0.01,1) -> 102.6 | E22: =ROUNDUP($C$4/60,1) -> 238.7 | F22: =+ROUND(D22+E22,1) -> 341.3 | G22: =+ROUND(G21-E22,1) -> 10024.3
A23: 19 | B23: 46171 | D23: =+ROUND(G22*0.01,1) -> 100.2 | E23: =ROUNDUP($C$4/60,1) -> 238.7 | F23: =+ROUND(D23+E23,1) -> 338.9 | G23: =+ROUND(G22-E23,1) -> 9785.6
A24: 20 | B24: 46202 | D24: =+ROUND(G23*0.01,1) -> 97.9 | E24: =ROUNDUP($C$4/60,1) -> 238.7 | F24: =+ROUND(D24+E24,1) -> 336.6 | G24: =+ROUND(G23-E24,1) -> 9546.9
A25: 21 | B25: 46232 | D25: =+ROUND(G24*0.01,1) -> 95.5 | E25: =ROUNDUP($C$4/60,1) -> 238.7 | F25: =+ROUND(D25+E25,1) -> 334.2 | G25: =+ROUND(G24-E25,1) -> 9308.2
A26: 22 | B26: 46263 | D26: =+ROUND(G25*0.01,1) -> 93.1 | E26: =ROUNDUP($C$4/60,1) -> 238.7 | F26: =+ROUND(D26+E26,1) -> 331.8 | G26: =+ROUND(G25-E26,1) -> 9069.5
A27: 23 | B27: 46294 | D27: =+ROUND(G26*0.01,1) -> 90.7 | E27: =ROUNDUP($C$4/60,1) -> 238.7 | F27: =+ROUND(D27+E27,1) -> 329.4 | G27: =+ROUND(G26-E27,1) -> 8830.8
A28: 24 | B28: 46324 | D28: =+ROUND(G27*0.01,1) -> 88.3 | E28: =ROUNDUP($C$4/60,1) -> 238.7 | F28: =+ROUND(D28+E28,1) -> 327 | G28: =+ROUND(G27-E28,1) -> 8592.1
A29: 25 | B29: 46355 | D29: =+ROUND(G28*0.01,1) -> 85.9 | E29: =ROUNDUP($C$4/60,1) -> 238.7 | F29: =+ROUND(D29+E29,1) -> 324.6 | G29: =+ROUND(G28-E29,1) -> 8353.4
A30: 26 | B30: 46385 | D30: =+ROUND(G29*0.01,1) -> 83.5 | E30: =ROUNDUP($C$4/60,1) -> 238.7 | F30: =+ROUND(D30+E30,1) -> 322.2 | G30: =+ROUND(G29-E30,1) -> 8114.7
A31: 27 | B31: 46416 | D31: =+ROUND(G30*0.01,1) -> 81.1 | E31: =ROUNDUP($C$4/60,1) -> 238.7 | F31: =+ROUND(D31+E31,1) -> 319.8 | G31: =+ROUND(G30-E31,1) -> 7876
... A63: 59 | B63: 47390 | D63: =+ROUND(G62*0.01,1) -> 4.8 | E63: =ROUNDUP($C$4/60,1) -> 238.7 | F63: =+ROUND(D63+E63,1) -> 243.5 | G63: =+ROUND(G62-E63,1) -> 237.6
A64: 60 | B64: 47420 | D64: =+ROUND(G63*0.01,1) -> 2.4 | E64: =ROUNDUP($C$4/60,1)-1.1 -> 237.6 | F64: =+ROUND(D64+E64,1) -> 240 | G64: =+ROUND(G63-E64,1) -> 0
A65: TOTAL | D65: =+SUM(D5:D64) -> 4367.6 | E65: =+SUM(E5:E64) -> 14320.9 | F65: =+SUM(F5:F64) -> 18688.5
A67: SOCIO: MELBA GLADIS CHAVEZ QUEVEDO
A68: OCTUBRE 2024 - PRÉSTAMO
A69: PLAZO | B69: FECHA | C69: PRÉSTAMO S/. | D69: INTERES | E69: ABONO DE CAPITAL | F69: CUOTA | G69: SALDO
A70: 0 | B70: 45686 | C70: =+J73 -> 25740.4 | D70: 0.01 | G70: =+C70 -> 25740.4
A71: 1 | B71: 45716 | D71: =+ROUND(G70*0.01,1) -> 257.4 | E71: =ROUND($C$70/12,1) -> 2145 | F71: =+ROUND(D71+E71,1) -> 2402.4 | G71: =+ROUND(G70-E71,1) -> 23595.4 | I71: SALDO | J71: =G19 -> 10740.4
A72: 2 | B72: 45745 | D72: =+ROUND(G71*0.01,1) -> 236 | E72: =ROUND($C$70/12,1) -> 2145 | F72: =+ROUND(D72+E72,1) -> 2381 | G72: =+ROUND(G71-E72,1) -> 21450.4 | I72: PRESTAMO | J72: 15000
A73: 3 | B73: 45776 | D73: =+ROUND(G72*0.01,1) -> 214.5 | E73: =ROUND($C$70/12,1) -> 2145 | F73: =+ROUND(D73+E73,1) -> 2359.5 | G73: =+ROUND(G72-E73,1) -> 19305.4 | I73: TOTAL | J73: =+SUM(J71:J72) -> 25740.4
A74: 4 | B74: 45806 | D74: =+ROUND(G73*0.01,1) -> 193.1 | E74: =ROUND($C$70/12,1) -> 2145 | F74: =+ROUND(D74+E74,1) -> 2338.1 | G74: =+ROUND(G73-E74,1) -> 17160.4
A75: 5 | B75: 45837 | D75: =+ROUND(G74*0.01,1) -> 171.6 | E75: =ROUND($C$70/12,1) -> 2145 | F75: =+ROUND(D75+E75,1) -> 2316.6 | G75: =+ROUND(G74-E75,1) -> 15015.4
A76: 6 | B76: 45867 | D76: =+ROUND(G75*0.01,1) -> 150.2 | E76: =ROUND($C$70/12,1) -> 2145 | F76: =+ROUND(D76+E76,1) -> 2295.2 | G76: =+ROUND(G75-E76,1) -> 12870.4
A77: 7 | B77: 45898 | D77: =+ROUND(G76*0.01,1) -> 128.7 | E77: =ROUND($C$70/12,1) -> 2145 | F77: =+ROUND(D77+E77,1) -> 2273.7 | G77: =+ROUND(G76-E77,1) -> 10725.4
A78: 8 | B78: 45929 | D78: =+ROUND(G77*0.01,1) -> 107.3 | E78: =ROUND($C$70/12,1) -> 2145 | F78: =+ROUND(D78+E78,1) -> 2252.3 | G78: =+ROUND(G77-E78,1) -> 8580.4
A79: 9 | B79: 45959 | D79: =+ROUND(G78*0.01,1) -> 85.8 | E79: =ROUND($C$70/12,1) -> 2145 | F79: =+ROUND(D79+E79,1) -> 2230.8 | G79: =+ROUND(G78-E79,1) -> 6435.4
A80: 10 | B80: 45990 | D80: =+ROUND(G79*0.01,1) -> 64.4 | E80: =ROUND($C$70/12,1) -> 2145 | F80: =+ROUND(D80+E80,1) -> 2209.4 | G80: =+ROUND(G79-E80,1) -> 4290.4
A81: 11 | B81: 46020 | D81: =+ROUND(G80*0.01,1) -> 42.9 | E81: =ROUND($C$70/12,1) -> 2145 | F81: =+ROUND(D81+E81,1) -> 2187.9 | G81: =+ROUND(G80-E81,1) -> 2145.4
A82: 12 | B82: 46051 | D82: =+ROUND(G81*0.01,1) -> 21.5 | E82: =ROUND($C$70/12,1)+0.4 -> 2145.4 | F82: =+ROUND(D82+E82,1) -> 2166.9 | G82: =+ROUND(G81-E82,1) -> 0
A83: TOTAL | D83: =+SUM(D71:D82) -> 1673.4 | E83: =+SUM(E71:E82) -> 25740.4 | F83: =+SUM(F71:F82) -> 27413.8

Sheet 13
A1: SOCIO: MARIA ELIZABETH CHAVEZ SALAZAR
A2: FEBRERO 2025 - PRÉSTAMO
A3: PLAZO | B3: FECHA | C3: PRÉSTAMO S/. | D3: INTERES | E3: ABONO DE CAPITAL | F3: CUOTA | G3: SALDO
A4: 0 | B4: 29/02/2025 | C4: =+J7 -> 24266 | D4: 0.01 | G4: =+C4 -> 24266
A5: 1 | B5: 45745 | D5: =+ROUND(G4*0.01,1) -> 242.7 | E5: =ROUNDUP(C4/84,1) -> 288.9 | F5: =+ROUND(D5+E5,1) -> 531.6 | G5: =+ROUND(G4-E5,1) -> 23977.1 | I5: SALDO | J5: 14266
A6: 2 | B6: 45776 | D6: =+ROUND(G5*0.01,1) -> 239.8 | E6: =ROUNDUP($C$4/84,1) -> 288.9 | F6: =+ROUND(D6+E6,1) -> 528.7 | G6: =+ROUND(G5-E6,1) -> 23688.2 | I6: PRESTAMO | J6: 10000
A7: 3 | B7: 45806 | D7: =+ROUND(G6*0.01,1) -> 236.9 | E7: =ROUNDUP($C$4/84,1) -> 288.9 | F7: =+ROUND(D7+E7,1) -> 525.8 | G7: =+ROUND(G6-E7,1) -> 23399.3 | I7: TOTAL | J7: =+SUM(J5:J6) -> 24266
A8: 4 | B8: 45837 | D8: =+ROUND(G7*0.01,1) -> 234 | E8: =ROUNDUP($C$4/84,1) -> 288.9 | F8: =+ROUND(D8+E8,1) -> 522.9 | G8: =+ROUND(G7-E8,1) -> 23110.4
A9: 5 | B9: 45867 | D9: =+ROUND(G8*0.01,1) -> 231.1 | E9: =ROUNDUP($C$4/84,1) -> 288.9 | F9: =+ROUND(D9+E9,1) -> 520 | G9: =+ROUND(G8-E9,1) -> 22821.5
A10: 6 | B10: 45898 | D10: =+ROUND(G9*0.01,1) -> 228.2 | E10: =ROUNDUP($C$4/84,1) -> 288.9 | F10: =+ROUND(D10+E10,1) -> 517.1 | G10: =+ROUND(G9-E10,1) -> 22532.6
A11: 7 | B11: 45929 | D11: =+ROUND(G10*0.01,1) -> 225.3 | E11: =ROUNDUP($C$4/84,1) -> 288.9 | F11: =+ROUND(D11+E11,1) -> 514.2 | G11: =+ROUND(G10-E11,1) -> 22243.7
A12: 8 | B12: 45959 | D12: =+ROUND(G11*0.01,1) -> 222.4 | E12: =ROUNDUP($C$4/84,1) -> 288.9 | F12: =+ROUND(D12+E12,1) -> 511.3 | G12: =+ROUND(G11-E12,1) -> 21954.8
A13: 9 | B13: 45990 | D13: =+ROUND(G12*0.01,1) -> 219.5 | E13: =ROUNDUP($C$4/84,1) -> 288.9 | F13: =+ROUND(D13+E13,1) -> 508.4 | G13: =+ROUND(G12-E13,1) -> 21665.9
A14: 10 | B14: 46020 | D14: =+ROUND(G13*0.01,1) -> 216.7 | E14: =ROUNDUP($C$4/84,1) -> 288.9 | F14: =+ROUND(D14+E14,1) -> 505.6 | G14: =+ROUND(G13-E14,1) -> 21377
A15: 11 | B15: 46051 | D15: =+ROUND(G14*0.01,1) -> 213.8 | E15: =ROUNDUP($C$4/84,1) -> 288.9 | F15: =+ROUND(D15+E15,1) -> 502.7 | G15: =+ROUND(G14-E15,1) -> 21088.1
A16: 12 | B16: 46081 | D16: =+ROUND(G15*0.01,1) -> 210.9 | E16: =ROUNDUP($C$4/84,1) -> 288.9 | F16: =+ROUND(D16+E16,1) -> 499.8 | G16: =+ROUND(G15-E16,1) -> 20799.2
A17: 13 | B17: 46110 | D17: =+ROUND(G16*0.01,1) -> 208 | E17: =ROUNDUP($C$4/84,1) -> 288.9 | F17: =+ROUND(D17+E17,1) -> 496.9 | G17: =+ROUND(G16-E17,1) -> 20510.3
A18: 14 | B18: 46141 | D18: =+ROUND(G17*0.01,1) -> 205.1 | E18: =ROUNDUP($C$4/84,1) -> 288.9 | F18: =+ROUND(D18+E18,1) -> 494 | G18: =+ROUND(G17-E18,1) -> 20221.4
A19: 15 | B19: 46171 | D19: =+ROUND(G18*0.01,1) -> 202.2 | E19: =ROUNDUP($C$4/84,1) -> 288.9 | F19: =+ROUND(D19+E19,1) -> 491.1 | G19: =+ROUND(G18-E19,1) -> 19932.5
... A87: 83 | B87: 48242 | D87: =+ROUND(G86*0.01,1) -> 5.8 | E87: =ROUNDUP($C$4/84,1) -> 288.9 | F87: =+ROUND(D87+E87,1) -> 294.7 | G87: =+ROUND(G86-E87,1) -> 287.3
A88: 84 | B88: 48273 | D88: =+ROUND(G87*0.01,1) -> 2.9 | E88: =ROUNDUP($C$4/84,1)-1.6 -> 287.3 | F88: =+ROUND(D88+E88,1) -> 290.2 | G88: =+ROUND(G87-E88,1) -> 0
A89: TOTAL | D89: =+SUM(D5:D88) -> 10312.5 | E89: =+SUM(E5:E88) -> 24266 | F89: =+SUM(F5:F88) -> 34578.5

Sheet 14
A1: SOCIO: CARLOS DÍAZ ALBARRAN
A2: NOVIEMBRE 2023 - PRÉSTAMO
A3: PLAZO | B3: FECHA | C3: PRÉSTAMO S/. | D3: INTERES | E3: ABONO DE CAPITAL | F3: CUOTA | G3: SALDO
A4: 0 | B4: 45259 | C4: =+J7 -> 33883.7 | D4: 0.01 | G4: =+C4 -> 33883.7
A5: 1 | B5: 45289 | D5: =+ROUND(G4*0.01,1) -> 338.8 | E5: =ROUNDUP(C4/84,1) -> 403.4 | F5: =+ROUND(D5+E5,1) -> 742.2 | G5: =+ROUND(G4-E5,1) -> 33480.3 | I5: SALDO | J5: 33883.7
A6: 2 | B6: 45320 | D6: =+ROUND(G5*0.01,1) -> 334.8 | E6: =ROUNDUP($C$4/84,1) -> 403.4 | F6: =+ROUND(D6+E6,1) -> 738.2 | G6: =+ROUND(G5-E6,1) -> 33076.9 | I6: PRESTAMO | J6: 0
A7: 3 | B7: 45351 | D7: =+ROUND(G6*0.01,1) -> 330.8 | E7: =ROUNDUP($C$4/84,1) -> 403.4 | F7: =+ROUND(D7+E7,1) -> 734.2 | G7: =+ROUND(G6-E7,1) -> 32673.5 | I7: TOTAL | J7: =+SUM(J5:J6) -> 33883.7
A8: 4 | B8: 45380 | D8: =+ROUND(G7*0.01,1) -> 326.7 | E8: =ROUNDUP($C$4/84,1) -> 403.4 | F8: =+ROUND(D8+E8,1) -> 730.1 | G8: =+ROUND(G7-E8,1) -> 32270.1
A9: 5 | B9: 45411 | D9: =+ROUND(G8*0.01,1) -> 322.7 | E9: =ROUNDUP($C$4/84,1) -> 403.4 | F9: =+ROUND(D9+E9,1) -> 726.1 | G9: =+ROUND(G8-E9,1) -> 31866.7
A10: 6 | B10: 45441 | D10: =+ROUND(G9*0.01,1) -> 318.7 | E10: =ROUNDUP($C$4/84,1) -> 403.4 | F10: =+ROUND(D10+E10,1) -> 722.1 | G10: =+ROUND(G9-E10,1) -> 31463.3
A11: 7 | B11: 45472 | D11: =+ROUND(G10*0.01,1) -> 314.6 | E11: =ROUNDUP($C$4/84,1) -> 403.4 | F11: =+ROUND(D11+E11,1) -> 718 | G11: =+ROUND(G10-E11,1) -> 31059.9
A12: 8 | B12: 45502 | D12: =+ROUND(G11*0.01,1) -> 310.6 | E12: =ROUNDUP($C$4/84,1) -> 403.4 | F12: =+ROUND(D12+E12,1) -> 714 | G12: =+ROUND(G11-E12,1) -> 30656.5
A13: 9 | B13: 45533 | D13: =+ROUND(G12*0.01,1) -> 306.6 | E13: =ROUNDUP($C$4/84,1) -> 403.4 | F13: =+ROUND(D13+E13,1) -> 710 | G13: =+ROUND(G12-E13,1) -> 30253.1
A14: 10 | B14: 45564 | D14: =+ROUND(G13*0.01,1) -> 302.5 | E14: =ROUNDUP($C$4/84,1) -> 403.4 | F14: =+ROUND(D14+E14,1) -> 705.9 | G14: =+ROUND(G13-E14,1) -> 29849.7
A15: 11 | B15: 45594 | D15: =+ROUND(G14*0.01,1) -> 298.5 | E15: =ROUNDUP($C$4/84,1) -> 403.4 | F15: =+ROUND(D15+E15,1) -> 701.9 | G15: =+ROUND(G14-E15,1) -> 29446.3
A16: 12 | B16: 45625 | D16: =+ROUND(G15*0.01,1) -> 294.5 | E16: =ROUNDUP($C$4/84,1) -> 403.4 | F16: =+ROUND(D16+E16,1) -> 697.9 | G16: =+ROUND(G15-E16,1) -> 29042.9
A17: 13 | B17: 45655 | D17: =+ROUND(G16*0.01,1) -> 290.4 | E17: =ROUNDUP($C$4/84,1) -> 403.4 | F17: =+ROUND(D17+E17,1) -> 693.8 | G17: =+ROUND(G16-E17,1) -> 28639.5
A18: 14 | B18: 45686 | D18: =+ROUND(G17*0.01,1) -> 286.4 | E18: =ROUNDUP($C$4/84,1) -> 403.4 | F18: =+ROUND(D18+E18,1) -> 689.8 | G18: =+ROUND(G17-E18,1) -> 28236.1
A19: 15 | B19: 45716 | D19: =+ROUND(G18*0.01,1) -> 282.4 | E19: =ROUNDUP($C$4/84,1) -> 403.4 | F19: =+ROUND(D19+E19,1) -> 685.8 | G19: =+ROUND(G18-E19,1) -> 27832.7
... A69: 65 | B69: 47237 | D69: =+ROUND(G68*0.01,1) -> 80.7 | E69: =ROUNDUP($C$4/84,1) -> 403.4 | F69: =+ROUND(D69+E69,1) -> 484.1 | G69: =+ROUND(G68-E69,1) -> 7662.7
A70: 66 | B70: 47267 | D70: =+ROUND(G69*0.01,1) -> 76.6 | E70: =ROUNDDOWN($C$4/84,1) -> 403.3 | F70: =+ROUND(D70+E70,1) -> 479.9 | G70: =+ROUND(G69-E70,1) -> 7259.4
A71: 67 | B71: 47298 | D71: =+ROUND(G70*0.01,1) -> 72.6 | E71: =ROUNDDOWN($C$4/84,1) -> 403.3 | F71: =+ROUND(D71+E71,1) -> 475.9 | G71: =+ROUND(G70-E71,1) -> 6856.1
A72: 68 | B72: 47328 | D72: =+ROUND(G71*0.01,1) -> 68.6 | E72: =ROUNDDOWN($C$4/84,1) -> 403.3 | F72: =+ROUND(D72+E72,1) -> 471.9 | G72: =+ROUND(G71-E72,1) -> 6452.8
A73: 69 | B73: 47359 | D73: =+ROUND(G72*0.01,1) -> 64.5 | E73: =ROUNDDOWN($C$4/84,1) -> 403.3 | F73: =+ROUND(D73+E73,1) -> 467.8 | G73: =+ROUND(G72-E73,1) -> 6049.5
A74: 70 | B74: 47390 | D74: =+ROUND(G73*0.01,1) -> 60.5 | E74: =ROUNDDOWN($C$4/84,1) -> 403.3 | F74: =+ROUND(D74+E74,1) -> 463.8 | G74: =+ROUND(G73-E74,1) -> 5646.2
A75: 71 | B75: 47420 | D75: =+ROUND(G74*0.01,1) -> 56.5 | E75: =ROUNDDOWN($C$4/84,1) -> 403.3 | F75: =+ROUND(D75+E75,1) -> 459.8 | G75: =+ROUND(G74-E75,1) -> 5242.9
A76: 72 | B76: 47451 | D76: =+ROUND(G75*0.01,1) -> 52.4 | E76: =ROUNDDOWN($C$4/84,1) -> 403.3 | F76: =+ROUND(D76+E76,1) -> 455.7 | G76: =+ROUND(G75-E76,1) -> 4839.6
A77: 73 | B77: 47481 | D77: =+ROUND(G76*0.01,1) -> 48.4 | E77: =ROUNDDOWN($C$4/84,1) -> 403.3 | F77: =+ROUND(D77+E77,1) -> 451.7 | G77: =+ROUND(G76-E77,1) -> 4436.3
A78: 74 | B78: 47512 | D78: =+ROUND(G77*0.01,1) -> 44.4 | E78: =ROUNDDOWN($C$4/84,1) -> 403.3 | F78: =+ROUND(D78+E78,1) -> 447.7 | G78: =+ROUND(G77-E78,1) -> 4033
A79: 75 | B79: 47542 | D79: =+ROUND(G78*0.01,1) -> 40.3 | E79: =ROUNDDOWN($C$4/84,1) -> 403.3 | F79: =+ROUND(D79+E79,1) -> 443.6 | G79: =+ROUND(G78-E79,1) -> 3629.7
A80: 76 | B80: 47571 | D80: =+ROUND(G79*0.01,1) -> 36.3 | E80: =ROUNDDOWN($C$4/84,1) -> 403.3 | F80: =+ROUND(D80+E80,1) -> 439.6 | G80: =+ROUND(G79-E80,1) -> 3226.4
A81: 77 | B81: 47602 | D81: =+ROUND(G80*0.01,1) -> 32.3 | E81: =ROUNDDOWN($C$4/84,1) -> 403.3 | F81: =+ROUND(D81+E81,1) -> 435.6 | G81: =+ROUND(G80-E81,1) -> 2823.1
... A88: 84 | B88: 47816 | D88: =+ROUND(G87*0.01,1) -> 4 | E88: =ROUNDDOWN($C$4/84,1) -> 403.3 | F88: =+ROUND(D88+E88,1) -> 407.3 | G88: =+ROUND(G87-E88,1) -> 0
A89: TOTAL | D89: =+SUM(D5:D88) -> 14400 | E89: =+SUM(E5:E88) -> 33883.7 | F89: =+SUM(F5:F88) -> 48283.7

Sheet 15
A1: SOCIO: JUAN DE LA SALLE DIAZ ALBARRAN
A2: JUNIO 2025 - PRÉSTAMO
A3: PLAZO | B3: FECHA | C3: PRÉSTAMO S/. | D3: INTERES | E3: ABONO DE CAPITAL | F3: CUOTA | G3: SALDO
A4: 0 | B4: 45837 | C4: =+J7 -> 20583.1 | D4: 0.01 | G4: =+C4 -> 20583.1
A5: 1 | B5: 45867 | D5: =+ROUND(G4*0.01,1) -> 205.8 | E5: =ROUNDDOWN($C$4/48,1) -> 428.8 | F5: =+ROUND(D5+E5,1) -> 634.6 | G5: =+ROUND(G4-E5,1) -> 20154.3 | I5: SALDO | J5: 8000
A6: 2 | B6: 45898 | D6: =+ROUND(G5*0.01,1) -> 201.5 | E6: =ROUNDDOWN($C$4/48,1) -> 428.8 | F6: =+ROUND(D6+E6,1) -> 630.3 | G6: =+ROUND(G5-E6,1) -> 19725.5 | I6: PRESTAMO | J6: 12583.1
A7: 3 | B7: 45929 | D7: =+ROUND(G6*0.01,1) -> 197.3 | E7: =ROUNDDOWN($C$4/48,1) -> 428.8 | F7: =+ROUND(D7+E7,1) -> 626.1 | G7: =+ROUND(G6-E7,1) -> 19296.7 | I7: TOTAL | J7: =+SUM(J5:J6) -> 20583.1
A8: 4 | B8: 45959 | D8: =+ROUND(G7*0.01,1) -> 193 | E8: =ROUNDDOWN($C$4/48,1) -> 428.8 | F8: =+ROUND(D8+E8,1) -> 621.8 | G8: =+ROUND(G7-E8,1) -> 18867.9
A9: 5 | B9: 45990 | D9: =+ROUND(G8*0.01,1) -> 188.7 | E9: =ROUNDDOWN($C$4/48,1) -> 428.8 | F9: =+ROUND(D9+E9,1) -> 617.5 | G9: =+ROUND(G8-E9,1) -> 18439.1
A10: 6 | B10: 46020 | D10: =+ROUND(G9*0.01,1) -> 184.4 | E10: =ROUNDDOWN($C$4/48,1) -> 428.8 | F10: =+ROUND(D10+E10,1) -> 613.2 | G10: =+ROUND(G9-E10,1) -> 18010.3
A11: 7 | B11: 46051 | D11: =+ROUND(G10*0.01,1) -> 180.1 | E11: =ROUNDDOWN($C$4/48,1) -> 428.8 | F11: =+ROUND(D11+E11,1) -> 608.9 | G11: =+ROUND(G10-E11,1) -> 17581.5
A12: 8 | B12: 46081 | D12: =+ROUND(G11*0.01,1) -> 175.8 | E12: =ROUNDDOWN($C$4/48,1) -> 428.8 | F12: =+ROUND(D12+E12,1) -> 604.6 | G12: =+ROUND(G11-E12,1) -> 17152.7
A13: 9 | B13: 46110 | D13: =+ROUND(G12*0.01,1) -> 171.5 | E13: =ROUNDDOWN($C$4/48,1) -> 428.8 | F13: =+ROUND(D13+E13,1) -> 600.3 | G13: =+ROUND(G12-E13,1) -> 16723.9
A14: 10 | B14: 46141 | D14: =+ROUND(G13*0.01,1) -> 167.2 | E14: =ROUNDDOWN($C$4/48,1) -> 428.8 | F14: =+ROUND(D14+E14,1) -> 596 | G14: =+ROUND(G13-E14,1) -> 16295.1
A15: 11 | B15: 46171 | D15: =+ROUND(G14*0.01,1) -> 163 | E15: =ROUNDDOWN($C$4/48,1) -> 428.8 | F15: =+ROUND(D15+E15,1) -> 591.8 | G15: =+ROUND(G14-E15,1) -> 15866.3
A16: 12 | B16: 46202 | D16: =+ROUND(G15*0.01,1) -> 158.7 | E16: =ROUNDDOWN($C$4/48,1) -> 428.8 | F16: =+ROUND(D16+E16,1) -> 587.5 | G16: =+ROUND(G15-E16,1) -> 15437.5
A17: 13 | B17: 46232 | D17: =+ROUND(G16*0.01,1) -> 154.4 | E17: =ROUNDDOWN($C$4/48,1) -> 428.8 | F17: =+ROUND(D17+E17,1) -> 583.2 | G17: =+ROUND(G16-E17,1) -> 15008.7
A18: 14 | B18: 46263 | D18: =+ROUND(G17*0.01,1) -> 150.1 | E18: =ROUNDDOWN($C$4/48,1) -> 428.8 | F18: =+ROUND(D18+E18,1) -> 578.9 | G18: =+ROUND(G17-E18,1) -> 14579.9
A19: 15 | B19: 46294 | D19: =+ROUND(G18*0.01,1) -> 145.8 | E19: =ROUNDDOWN($C$4/48,1) -> 428.8 | F19: =+ROUND(D19+E19,1) -> 574.6 | G19: =+ROUND(G18-E19,1) -> 14151.1
... A51: 47 | B51: 47267 | D51: =+ROUND(G50*0.01,1) -> 8.6 | E51: =ROUNDDOWN($C$4/48,1) -> 428.8 | F51: =+ROUND(D51+E51,1) -> 437.4 | G51: =+ROUND(G50-E51,1) -> 429.5
A52: 48 | B52: 47298 | D52: =+ROUND(G51*0.01,1) -> 4.3 | E52: =ROUNDDOWN($C$4/48,1)+0.7 -> 429.5 | F52: =+ROUND(D52+E52,1) -> 433.8 | G52: =+ROUND(G51-E52,1) -> 0
A53: TOTAL | D53: =+SUM(D5:D52) -> 5043.1 | E53: =+SUM(E5:E52) -> 20583.1 | F53: =+SUM(F5:F52) -> 25626.2

Sheet 16
A1: SOCIO: KEVIN DIAZ ALIAGA
A2: MARZO 2025 - PRÉSTAMO
A3: PLAZO | B3: FECHA | C3: PRÉSTAMO S/. | D3: INTERES | E3: ABONO DE CAPITAL | F3: CUOTA | G3: SALDO
A4: 0 | B4: 45745 | C4: =+J7 -> 16064.3 | D4: 0.01 | G4: =+C4 -> 16064.3
A5: 1 | B5: 45776 | D5: =+ROUND(G4*0.01,1) -> 160.6 | E5: =ROUNDUP($C$4/48,1) -> 334.7 | F5: =+ROUND(D5+E5,1) -> 495.3 | G5: =+ROUND(G4-E5,1) -> 15729.6 | I5: SALDO | J5: 6198.9
A6: 2 | B6: 45806 | D6: =+ROUND(G5*0.01,1) -> 157.3 | E6: =ROUNDUP($C$4/48,1) -> 334.7 | F6: =+ROUND(D6+E6,1) -> 492 | G6: =+ROUND(G5-E6,1) -> 15394.9 | I6: PRESTAMO | J6: 9865.4
A7: 3 | B7: 45837 | D7: =+ROUND(G6*0.01,1) -> 153.9 | E7: =ROUNDUP($C$4/48,1) -> 334.7 | F7: =+ROUND(D7+E7,1) -> 488.6 | G7: =+ROUND(G6-E7,1) -> 15060.2 | I7: TOTAL | J7: =+SUM(J5:J6) -> 16064.3
A8: 4 | B8: 45867 | D8: =+ROUND(G7*0.01,1) -> 150.6 | E8: =ROUNDUP($C$4/48,1) -> 334.7 | F8: =+ROUND(D8+E8,1) -> 485.3 | G8: =+ROUND(G7-E8,1) -> 14725.5
A9: 5 | B9: 45898 | D9: =+ROUND(G8*0.01,1) -> 147.3 | E9: =ROUNDUP($C$4/48,1) -> 334.7 | F9: =+ROUND(D9+E9,1) -> 482 | G9: =+ROUND(G8-E9,1) -> 14390.8
A10: 6 | B10: 45929 | D10: =+ROUND(G9*0.01,1) -> 143.9 | E10: =ROUNDUP($C$4/48,1) -> 334.7 | F10: =+ROUND(D10+E10,1) -> 478.6 | G10: =+ROUND(G9-E10,1) -> 14056.1
A11: 7 | B11: 45959 | D11: =+ROUND(G10*0.01,1) -> 140.6 | E11: =ROUNDUP($C$4/48,1) -> 334.7 | F11: =+ROUND(D11+E11,1) -> 475.3 | G11: =+ROUND(G10-E11,1) -> 13721.4
A12: 8 | B12: 45990 | D12: =+ROUND(G11*0.01,1) -> 137.2 | E12: =ROUNDUP($C$4/48,1) -> 334.7 | F12: =+ROUND(D12+E12,1) -> 471.9 | G12: =+ROUND(G11-E12,1) -> 13386.7
A13: 9 | B13: 46020 | D13: =+ROUND(G12*0.01,1) -> 133.9 | E13: =ROUNDUP($C$4/48,1) -> 334.7 | F13: =+ROUND(D13+E13,1) -> 468.6 | G13: =+ROUND(G12-E13,1) -> 13052
A14: 10 | B14: 46051 | D14: =+ROUND(G13*0.01,1) -> 130.5 | E14: =ROUNDUP($C$4/48,1) -> 334.7 | F14: =+ROUND(D14+E14,1) -> 465.2 | G14: =+ROUND(G13-E14,1) -> 12717.3 | I14: INTERES | J14: =SUM(D10:D15) -> 813.3
A15: 11 | B15: 46081 | D15: =+ROUND(G14*0.01,1) -> 127.2 | E15: =ROUNDUP($C$4/48,1) -> 334.7 | F15: =+ROUND(D15+E15,1) -> 461.9 | G15: =+ROUND(G14-E15,1) -> 12382.6 | I15: SALDO | J15: =G15 -> 12382.6
A16: 12 | B16: 46110 | D16: =+ROUND(G15*0.01,1) -> 123.8 | E16: =ROUNDUP($C$4/48,1) -> 334.7 | F16: =+ROUND(D16+E16,1) -> 458.5 | G16: =+ROUND(G15-E16,1) -> 12047.9
A17: 13 | B17: 46141 | D17: =+ROUND(G16*0.01,1) -> 120.5 | E17: =ROUNDUP($C$4/48,1) -> 334.7 | F17: =+ROUND(D17+E17,1) -> 455.2 | G17: =+ROUND(G16-E17,1) -> 11713.2
A18: 14 | B18: 46171 | D18: =+ROUND(G17*0.01,1) -> 117.1 | E18: =ROUNDUP($C$4/48,1) -> 334.7 | F18: =+ROUND(D18+E18,1) -> 451.8 | G18: =+ROUND(G17-E18,1) -> 11378.5
A19: 15 | B19: 46202 | D19: =+ROUND(G18*0.01,1) -> 113.8 | E19: =ROUNDUP($C$4/48,1) -> 334.7 | F19: =+ROUND(D19+E19,1) -> 448.5 | G19: =+ROUND(G18-E19,1) -> 11043.8
A20: 16 | B20: 46232 | D20: =+ROUND(G19*0.01,1) -> 110.4 | E20: =ROUNDUP($C$4/48,1) -> 334.7 | F20: =+ROUND(D20+E20,1) -> 445.1 | G20: =+ROUND(G19-E20,1) -> 10709.1
A21: 17 | B21: 46263 | D21: =+ROUND(G20*0.01,1) -> 107.1 | E21: =ROUNDUP($C$4/48,1) -> 334.7 | F21: =+ROUND(D21+E21,1) -> 441.8 | G21: =+ROUND(G20-E21,1) -> 10374.4
A22: 18 | B22: 46294 | D22: =+ROUND(G21*0.01,1) -> 103.7 | E22: =ROUNDUP($C$4/48,1) -> 334.7 | F22: =+ROUND(D22+E22,1) -> 438.4 | G22: =+ROUND(G21-E22,1) -> 10039.7
A23: 19 | B23: 46324 | D23: =+ROUND(G22*0.01,1) -> 100.4 | E23: =ROUNDUP($C$4/48,1) -> 334.7 | F23: =+ROUND(D23+E23,1) -> 435.1 | G23: =+ROUND(G22-E23,1) -> 9705
A24: 20 | B24: 46355 | D24: =+ROUND(G23*0.01,1) -> 97.1 | E24: =ROUNDUP($C$4/48,1) -> 334.7 | F24: =+ROUND(D24+E24,1) -> 431.8 | G24: =+ROUND(G23-E24,1) -> 9370.3
A25: 21 | B25: 46385 | D25: =+ROUND(G24*0.01,1) -> 93.7 | E25: =ROUNDUP($C$4/48,1) -> 334.7 | F25: =+ROUND(D25+E25,1) -> 428.4 | G25: =+ROUND(G24-E25,1) -> 9035.6
A26: 22 | B26: 46416 | D26: =+ROUND(G25*0.01,1) -> 90.4 | E26: =ROUNDUP($C$4/48,1) -> 334.7 | F26: =+ROUND(D26+E26,1) -> 425.1 | G26: =+ROUND(G25-E26,1) -> 8700.9
A27: 23 | B27: 46446 | D27: =+ROUND(G26*0.01,1) -> 87 | E27: =ROUNDUP($C$4/48,1) -> 334.7 | F27: =+ROUND(D27+E27,1) -> 421.7 | G27: =+ROUND(G26-E27,1) -> 8366.2
... A51: 47 | B51: 47177 | D51: =+ROUND(G50*0.01,1) -> 6.7 | E51: =ROUNDUP($C$4/48,1) -> 334.7 | F51: =+ROUND(D51+E51,1) -> 341.4 | G51: =+ROUND(G50-E51,1) -> 333.4
A52: 48 | B52: 47206 | D52: =+ROUND(G51*0.01,1) -> 3.3 | E52: =ROUNDUP($C$4/48,1)-1.3 -> 333.4 | F52: =+ROUND(D52+E52,1) -> 336.7 | G52: =+ROUND(G51-E52,1) -> 0
A53: TOTAL | D53: =+SUM(D5:D52) -> 3935.5 | E53: =+SUM(E5:E52) -> 16064.3 | F53: =+SUM(F5:F52) -> 19999.8
A55: FEBRERO 2026 - PRÉSTAMO
A56: PLAZO | B56: FECHA | C56: PRÉSTAMO S/. | D56: INTERES | E56: ABONO DE CAPITAL | F56: CUOTA | G56: SALDO
A57: 0 | B57: 46081 | C57: =+J60 -> 23085 | D57: 0.01 | G57: =+C57 -> 23085
A58: 1 | B58: 46110 | D58: =+ROUND(G57*0.01,1) -> 230.9 | E58: =ROUND($C$57/60,1) -> 384.8 | F58: =+ROUND(D58+E58,1) -> 615.7 | G58: =+ROUND(G57-E58,1) -> 22700.2 | I58: SALDO | J58: =G15 -> 12382.6
A59: 2 | B59: 46141 | D59: =+ROUND(G58*0.01,1) -> 227 | E59: =ROUND($C$57/60,1) -> 384.8 | F59: =+ROUND(D59+E59,1) -> 611.8 | G59: =+ROUND(G58-E59,1) -> 22315.4 | I59: PRESTAMO | J59: 10702.4
A60: 3 | B60: 46171 | D60: =+ROUND(G59*0.01,1) -> 223.2 | E60: =ROUND($C$57/60,1) -> 384.8 | F60: =+ROUND(D60+E60,1) -> 608 | G60: =+ROUND(G59-E60,1) -> 21930.6 | I60: TOTAL | J60: =+SUM(J58:J59) -> 23085
A61: 4 | B61: 46202 | D61: =+ROUND(G60*0.01,1) -> 219.3 | E61: =ROUND($C$57/60,1) -> 384.8 | F61: =+ROUND(D61+E61,1) -> 604.1 | G61: =+ROUND(G60-E61,1) -> 21545.8
A62: 5 | B62: 46232 | D62: =+ROUND(G61*0.01,1) -> 215.5 | E62: =ROUND($C$57/60,1) -> 384.8 | F62: =+ROUND(D62+E62,1) -> 600.3 | G62: =+ROUND(G61-E62,1) -> 21161
A63: 6 | B63: 46263 | D63: =+ROUND(G62*0.01,1) -> 211.6 | E63: =ROUND($C$57/60,1) -> 384.8 | F63: =+ROUND(D63+E63,1) -> 596.4 | G63: =+ROUND(G62-E63,1) -> 20776.2
A64: 7 | B64: 46294 | D64: =+ROUND(G63*0.01,1) -> 207.8 | E64: =ROUND($C$57/60,1) -> 384.8 | F64: =+ROUND(D64+E64,1) -> 592.6 | G64: =+ROUND(G63-E64,1) -> 20391.4
A65: 8 | B65: 46324 | D65: =+ROUND(G64*0.01,1) -> 203.9 | E65: =ROUND($C$57/60,1) -> 384.8 | F65: =+ROUND(D65+E65,1) -> 588.7 | G65: =+ROUND(G64-E65,1) -> 20006.6
A66: 9 | B66: 46355 | D66: =+ROUND(G65*0.01,1) -> 200.1 | E66: =ROUND($C$57/60,1) -> 384.8 | F66: =+ROUND(D66+E66,1) -> 584.9 | G66: =+ROUND(G65-E66,1) -> 19621.8
A67: 10 | B67: 46385 | D67: =+ROUND(G66*0.01,1) -> 196.2 | E67: =ROUND($C$57/60,1) -> 384.8 | F67: =+ROUND(D67+E67,1) -> 581 | G67: =+ROUND(G66-E67,1) -> 19237
A68: 11 | B68: 46416 | D68: =+ROUND(G67*0.01,1) -> 192.4 | E68: =ROUND($C$57/60,1) -> 384.8 | F68: =+ROUND(D68+E68,1) -> 577.2 | G68: =+ROUND(G67-E68,1) -> 18852.2
A69: 12 | B69: 46446 | D69: =+ROUND(G68*0.01,1) -> 188.5 | E69: =ROUND($C$57/60,1) -> 384.8 | F69: =+ROUND(D69+E69,1) -> 573.3 | G69: =+ROUND(G68-E69,1) -> 18467.4
A70: 13 | B70: 46475 | D70: =+ROUND(G69*0.01,1) -> 184.7 | E70: =ROUND($C$57/60,1) -> 384.8 | F70: =+ROUND(D70+E70,1) -> 569.5 | G70: =+ROUND(G69-E70,1) -> 18082.6
A71: 14 | B71: 46506 | D71: =+ROUND(G70*0.01,1) -> 180.8 | E71: =ROUND($C$57/60,1) -> 384.8 | F71: =+ROUND(D71+E71,1) -> 565.6 | G71: =+ROUND(G70-E71,1) -> 17697.8
A72: 15 | B72: 46536 | D72: =+ROUND(G71*0.01,1) -> 177 | E72: =ROUND($C$57/60,1) -> 384.8 | F72: =+ROUND(D72+E72,1) -> 561.8 | G72: =+ROUND(G71-E72,1) -> 17313
... A116: 59 | B116: 47877 | D116: =+ROUND(G115*0.01,1) -> 7.7 | E116: =ROUND($C$57/60,1) -> 384.8 | F116: =+ROUND(D116+E116,1) -> 392.5 | G116: =+ROUND(G115-E116,1) -> 381.8
A117: 60 | B117: 47907 | D117: =+ROUND(G116*0.01,1) -> 3.8 | E117: =ROUND($C$57/60,1)-3 -> 381.8 | F117: =+ROUND(D117+E117,1) -> 385.6 | G117: =+ROUND(G116-E117,1) -> 0
A118: TOTAL | D118: =+SUM(D58:D117) -> 7040.3 | E118: =+SUM(E58:E117) -> 23085 | F118: =+SUM(F58:F117) -> 30125.3

Sheet 17
A1: SOCIA: MARITZA DIAZ QUIROZ
A2: JUNIO 2025 - PRÉSTAMO
A3: PLAZO | B3: FECHA | C3: PRÉSTAMO S/. | D3: INTERES | E3: ABONO DE CAPITAL | F3: CUOTA | G3: SALDO
A4: 0 | B4: 45837 | C4: =+J7 -> 30548 | D4: 0.01 | G4: =+C4 -> 30548
A5: 1 | B5: 45867 | D5: =+ROUND(G4*0.01,1) -> 305.5 | E5: =ROUNDUP($C$4/84,1) -> 363.7 | F5: =+ROUND(D5+E5,1) -> 669.2 | G5: =+ROUND(G4-E5,1) -> 30184.3 | I5: SALDO | J5: 25548
A6: 2 | B6: 45898 | D6: =+ROUND(G5*0.01,1) -> 301.8 | E6: =ROUNDUP($C$4/84,1) -> 363.7 | F6: =+ROUND(D6+E6,1) -> 665.5 | G6: =+ROUND(G5-E6,1) -> 29820.6 | I6: PRESTAMO | J6: 5000
A7: 3 | B7: 45929 | D7: =+ROUND(G6*0.01,1) -> 298.2 | E7: =ROUNDUP($C$4/84,1) -> 363.7 | F7: =+ROUND(D7+E7,1) -> 661.9 | G7: =+ROUND(G6-E7,1) -> 29456.9 | I7: TOTAL | J7: =+SUM(J5:J6) -> 30548
A8: 4 | B8: 45959 | D8: =+ROUND(G7*0.01,1) -> 294.6 | E8: =ROUNDUP($C$4/84,1) -> 363.7 | F8: =+ROUND(D8+E8,1) -> 658.3 | G8: =+ROUND(G7-E8,1) -> 29093.2
A9: 5 | B9: 45990 | D9: =+ROUND(G8*0.01,1) -> 290.9 | E9: =ROUNDUP($C$4/84,1) -> 363.7 | F9: =+ROUND(D9+E9,1) -> 654.6 | G9: =+ROUND(G8-E9,1) -> 28729.5
A10: 6 | B10: 46020 | D10: =+ROUND(G9*0.01,1) -> 287.3 | E10: =ROUNDUP($C$4/84,1) -> 363.7 | F10: =+ROUND(D10+E10,1) -> 651 | G10: =+ROUND(G9-E10,1) -> 28365.8 | I10: INTERES | J10: =SUM(D5:D11) -> 2062
A11: 7 | B11: 46051 | D11: =+ROUND(G10*0.01,1) -> 283.7 | E11: =ROUNDUP($C$4/84,1) -> 363.7 | F11: =+ROUND(D11+E11,1) -> 647.4 | G11: =+ROUND(G10-E11,1) -> 28002.1 | I11: SALDO | J11: =G11 -> 28002.1
A12: 8 | B12: 46081 | D12: =+ROUND(G11*0.01,1) -> 280 | E12: =ROUNDUP($C$4/84,1) -> 363.7 | F12: =+ROUND(D12+E12,1) -> 643.7 | G12: =+ROUND(G11-E12,1) -> 27638.4
A13: 9 | B13: 46110 | D13: =+ROUND(G12*0.01,1) -> 276.4 | E13: =ROUNDUP($C$4/84,1) -> 363.7 | F13: =+ROUND(D13+E13,1) -> 640.1 | G13: =+ROUND(G12-E13,1) -> 27274.7
A14: 10 | B14: 46141 | D14: =+ROUND(G13*0.01,1) -> 272.7 | E14: =ROUNDUP($C$4/84,1) -> 363.7 | F14: =+ROUND(D14+E14,1) -> 636.4 | G14: =+ROUND(G13-E14,1) -> 26911
A15: 11 | B15: 46171 | D15: =+ROUND(G14*0.01,1) -> 269.1 | E15: =ROUNDUP($C$4/84,1) -> 363.7 | F15: =+ROUND(D15+E15,1) -> 632.8 | G15: =+ROUND(G14-E15,1) -> 26547.3
A16: 12 | B16: 46202 | D16: =+ROUND(G15*0.01,1) -> 265.5 | E16: =ROUNDUP($C$4/84,1) -> 363.7 | F16: =+ROUND(D16+E16,1) -> 629.2 | G16: =+ROUND(G15-E16,1) -> 26183.6
A17: 13 | B17: 46232 | D17: =+ROUND(G16*0.01,1) -> 261.8 | E17: =ROUNDUP($C$4/84,1) -> 363.7 | F17: =+ROUND(D17+E17,1) -> 625.5 | G17: =+ROUND(G16-E17,1) -> 25819.9
A18: 14 | B18: 46263 | D18: =+ROUND(G17*0.01,1) -> 258.2 | E18: =ROUNDUP($C$4/84,1) -> 363.7 | F18: =+ROUND(D18+E18,1) -> 621.9 | G18: =+ROUND(G17-E18,1) -> 25456.2
A19: 15 | B19: 46294 | D19: =+ROUND(G18*0.01,1) -> 254.6 | E19: =ROUNDUP($C$4/84,1) -> 363.7 | F19: =+ROUND(D19+E19,1) -> 618.3 | G19: =+ROUND(G18-E19,1) -> 25092.5
A20: 16 | B20: 46324 | D20: =+ROUND(G19*0.01,1) -> 250.9 | E20: =ROUNDUP($C$4/84,1) -> 363.7 | F20: =+ROUND(D20+E20,1) -> 614.6 | G20: =+ROUND(G19-E20,1) -> 24728.8
A21: 17 | B21: 46355 | D21: =+ROUND(G20*0.01,1) -> 247.3 | E21: =ROUNDUP($C$4/84,1) -> 363.7 | F21: =+ROUND(D21+E21,1) -> 611 | G21: =+ROUND(G20-E21,1) -> 24365.1
A22: 18 | B22: 46385 | D22: =+ROUND(G21*0.01,1) -> 243.7 | E22: =ROUNDUP($C$4/84,1) -> 363.7 | F22: =+ROUND(D22+E22,1) -> 607.4 | G22: =+ROUND(G21-E22,1) -> 24001.4
A23: 19 | B23: 46416 | D23: =+ROUND(G22*0.01,1) -> 240 | E23: =ROUNDUP($C$4/84,1) -> 363.7 | F23: =+ROUND(D23+E23,1) -> 603.7 | G23: =+ROUND(G22-E23,1) -> 23637.7
... A87: 83 | B87: 48363 | D87: =+ROUND(G86*0.01,1) -> 7.2 | E87: =ROUNDUP($C$4/84,1) -> 363.7 | F87: =+ROUND(D87+E87,1) -> 370.9 | G87: =+ROUND(G86-E87,1) -> 360.9
A88: 84 | B88: 48394 | D88: =+ROUND(G87*0.01,1) -> 3.6 | E88: =ROUNDUP($C$4/84,1)-2.8 -> 360.9 | F88: =+ROUND(D88+E88,1) -> 364.5 | G88: =+ROUND(G87-E88,1) -> 0
A89: TOTAL | D89: =+SUM(D5:D88) -> 12981.7 | E89: =+SUM(E5:E88) -> 30548 | F89: =+SUM(F5:F88) -> 43529.7
A91: SOCIA: MARITZA DIAZ QUIROZ
A92: ENERO 2026 - PRÉSTAMO
A93: PLAZO | B93: FECHA | C93: PRÉSTAMO S/. | D93: INTERES | E93: ABONO DE CAPITAL | F93: CUOTA | G93: SALDO
A94: 0 | B94: 46051 | C94: =+J97 -> 33002.1 | D94: 0.01 | G94: =+C94 -> 33002.1
A95: 1 | B95: 46081 | D95: =+ROUND(G94*0.01,1) -> 330 | E95: =ROUND($C$94/84,1) -> 392.9 | F95: =+ROUND(D95+E95,1) -> 722.9 | G95: =+ROUND(G94-E95,1) -> 32609.2 | I95: SALDO | J95: =G11 -> 28002.1
A96: 2 | B96: 46110 | D96: =+ROUND(G95*0.01,1) -> 326.1 | E96: =ROUND($C$94/84,1) -> 392.9 | F96: =+ROUND(D96+E96,1) -> 719 | G96: =+ROUND(G95-E96,1) -> 32216.3 | I96: PRESTAMO | J96: 5000
A97: 3 | B97: 46141 | D97: =+ROUND(G96*0.01,1) -> 322.2 | E97: =ROUND($C$94/84,1) -> 392.9 | F97: =+ROUND(D97+E97,1) -> 715.1 | G97: =+ROUND(G96-E97,1) -> 31823.4 | I97: TOTAL | J97: =+SUM(J95:J96) -> 33002.1
A98: 4 | B98: 46171 | D98: =+ROUND(G97*0.01,1) -> 318.2 | E98: =ROUND($C$94/84,1) -> 392.9 | F98: =+ROUND(D98+E98,1) -> 711.1 | G98: =+ROUND(G97-E98,1) -> 31430.5
A99: 5 | B99: 46202 | D99: =+ROUND(G98*0.01,1) -> 314.3 | E99: =ROUND($C$94/84,1) -> 392.9 | F99: =+ROUND(D99+E99,1) -> 707.2 | G99: =+ROUND(G98-E99,1) -> 31037.6
A100: 6 | B100: 46232 | D100: =+ROUND(G99*0.01,1) -> 310.4 | E100: =ROUND($C$94/84,1) -> 392.9 | F100: =+ROUND(D100+E100,1) -> 703.3 | G100: =+ROUND(G99-E100,1) -> 30644.7
A101: 7 | B101: 46263 | D101: =+ROUND(G100*0.01,1) -> 306.4 | E101: =ROUND($C$94/84,1) -> 392.9 | F101: =+ROUND(D101+E101,1) -> 699.3 | G101: =+ROUND(G100-E101,1) -> 30251.8
A102: 8 | B102: 46294 | D102: =+ROUND(G101*0.01,1) -> 302.5 | E102: =ROUND($C$94/84,1) -> 392.9 | F102: =+ROUND(D102+E102,1) -> 695.4 | G102: =+ROUND(G101-E102,1) -> 29858.9
A103: 9 | B103: 46324 | D103: =+ROUND(G102*0.01,1) -> 298.6 | E103: =ROUND($C$94/84,1) -> 392.9 | F103: =+ROUND(D103+E103,1) -> 691.5 | G103: =+ROUND(G102-E103,1) -> 29466
A104: 10 | B104: 46355 | D104: =+ROUND(G103*0.01,1) -> 294.7 | E104: =ROUND($C$94/84,1) -> 392.9 | F104: =+ROUND(D104+E104,1) -> 687.6 | G104: =+ROUND(G103-E104,1) -> 29073.1
A105: 11 | B105: 46385 | D105: =+ROUND(G104*0.01,1) -> 290.7 | E105: =ROUND($C$94/84,1) -> 392.9 | F105: =+ROUND(D105+E105,1) -> 683.6 | G105: =+ROUND(G104-E105,1) -> 28680.2
A106: 12 | B106: 46416 | D106: =+ROUND(G105*0.01,1) -> 286.8 | E106: =ROUND($C$94/84,1) -> 392.9 | F106: =+ROUND(D106+E106,1) -> 679.7 | G106: =+ROUND(G105-E106,1) -> 28287.3
A107: 13 | B107: 46446 | D107: =+ROUND(G106*0.01,1) -> 282.9 | E107: =ROUND($C$94/84,1) -> 392.9 | F107: =+ROUND(D107+E107,1) -> 675.8 | G107: =+ROUND(G106-E107,1) -> 27894.4
A108: 14 | B108: 46475 | D108: =+ROUND(G107*0.01,1) -> 278.9 | E108: =ROUND($C$94/84,1) -> 392.9 | F108: =+ROUND(D108+E108,1) -> 671.8 | G108: =+ROUND(G107-E108,1) -> 27501.5
A109: 15 | B109: 46506 | D109: =+ROUND(G108*0.01,1) -> 275 | E109: =ROUND($C$94/84,1) -> 392.9 | F109: =+ROUND(D109+E109,1) -> 667.9 | G109: =+ROUND(G108-E109,1) -> 27108.6
... A177: 83 | B177: 48577 | D177: =+ROUND(G176*0.01,1) -> 7.8 | E177: =ROUND($C$94/84,1) -> 392.9 | F177: =+ROUND(D177+E177,1) -> 400.7 | G177: =+ROUND(G176-E177,1) -> 391.4
A178: 84 | B178: 48608 | D178: =+ROUND(G177*0.01,1) -> 3.9 | E178: =ROUND($C$94/84,1)-1.5 -> 391.4 | F178: =+ROUND(D178+E178,1) -> 395.3 | G178: =+ROUND(G177-E178,1) -> 0
A179: TOTAL | D179: =+SUM(D95:D178) -> 14025.2 | E179: =+SUM(E95:E178) -> 33002.1 | F179: =+SUM(F95:F178) -> 47027.3

Sheet 18
A1: SOCIA: DÍAZ VERA JACKELINE MAGDALENA
A2: JULIO 2024 - PRÉSTAMO
A3: PLAZO | B3: FECHA | C3: PRÉSTAMO S/. | D3: INTERES | E3: ABONO DE CAPITAL | F3: CUOTA | G3: SALDO
A4: 0 | B4: 45502 | C4: =+J7 -> 52358.2 | D4: 0.01 | G4: =+C4 -> 52358.2
A5: 1 | B5: 45533 | D5: =+ROUND(G4*0.01,1) -> 523.6 | E5: =ROUNDUP($C$4/72,1) -> 727.2 | F5: =+ROUND(D5+E5,1) -> 1250.8 | G5: =+ROUND(G4-E5,1) -> 51631 | I5: SALDO | J5: 40010.4
A6: 2 | B6: 45564 | D6: =+ROUND(G5*0.01,1) -> 516.3 | E6: =ROUNDUP($C$4/72,1) -> 727.2 | F6: =+ROUND(D6+E6,1) -> 1243.5 | G6: =+ROUND(G5-E6,1) -> 50903.8 | I6: PRÉSTAMO | J6: 12347.8
A7: 3 | B7: 45594 | D7: =+ROUND(G6*0.01,1) -> 509 | E7: =ROUNDUP($C$4/72,1) -> 727.2 | F7: =+ROUND(D7+E7,1) -> 1236.2 | G7: =+ROUND(G6-E7,1) -> 50176.6 | I7: TOTAL | J7: =+SUM(J5:J6) -> 52358.2
A8: 4 | B8: 45625 | D8: =+ROUND(G7*0.01,1) -> 501.8 | E8: =ROUNDUP($C$4/72,1) -> 727.2 | F8: =+ROUND(D8+E8,1) -> 1229 | G8: =+ROUND(G7-E8,1) -> 49449.4
A9: 5 | B9: 45655 | D9: =+ROUND(G8*0.01,1) -> 494.5 | E9: =ROUNDUP($C$4/72,1) -> 727.2 | F9: =+ROUND(D9+E9,1) -> 1221.7 | G9: =+ROUND(G8-E9,1) -> 48722.2
A10: 6 | B10: 45686 | D10: =+ROUND(G9*0.01,1) -> 487.2 | E10: =ROUNDUP($C$4/72,1) -> 727.2 | F10: =+ROUND(D10+E10,1) -> 1214.4 | G10: =+ROUND(G9-E10,1) -> 47995
A11: 7 | B11: 45716 | D11: =+ROUND(G10*0.01,1) -> 480 | E11: =ROUNDUP($C$4/72,1) -> 727.2 | F11: =+ROUND(D11+E11,1) -> 1207.2 | G11: =+ROUND(G10-E11,1) -> 47267.8
A12: 8 | B12: 45745 | D12: =+ROUND(G11*0.01,1) -> 472.7 | E12: =ROUNDUP($C$4/72,1) -> 727.2 | F12: =+ROUND(D12+E12,1) -> 1199.9 | G12: =+ROUND(G11-E12,1) -> 46540.6
A13: 9 | B13: 45776 | D13: =+ROUND(G12*0.01,1) -> 465.4 | E13: =ROUNDUP($C$4/72,1) -> 727.2 | F13: =+ROUND(D13+E13,1) -> 1192.6 | G13: =+ROUND(G12-E13,1) -> 45813.4
A14: 10 | B14: 45806 | D14: =+ROUND(G13*0.01,1) -> 458.1 | E14: =ROUNDUP($C$4/72,1) -> 727.2 | F14: =+ROUND(D14+E14,1) -> 1185.3 | G14: =+ROUND(G13-E14,1) -> 45086.2
A15: 11 | B15: 45837 | D15: =+ROUND(G14*0.01,1) -> 450.9 | E15: =ROUNDUP($C$4/72,1) -> 727.2 | F15: =+ROUND(D15+E15,1) -> 1178.1 | G15: =+ROUND(G14-E15,1) -> 44359
A16: 12 | B16: 45867 | D16: =+ROUND(G15*0.01,1) -> 443.6 | E16: =ROUNDUP($C$4/72,1) -> 727.2 | F16: =+ROUND(D16+E16,1) -> 1170.8 | G16: =+ROUND(G15-E16,1) -> 43631.8
A17: 13 | B17: 45898 | D17: =+ROUND(G16*0.01,1) -> 436.3 | E17: =ROUNDUP($C$4/72,1) -> 727.2 | F17: =+ROUND(D17+E17,1) -> 1163.5 | G17: =+ROUND(G16-E17,1) -> 42904.6
A18: 14 | B18: 45929 | D18: =+ROUND(G17*0.01,1) -> 429 | E18: =ROUNDUP($C$4/72,1) -> 727.2 | F18: =+ROUND(D18+E18,1) -> 1156.2 | G18: =+ROUND(G17-E18,1) -> 42177.4
A19: 15 | B19: 45959 | D19: =+ROUND(G18*0.01,1) -> 421.8 | E19: =ROUNDUP($C$4/72,1) -> 727.2 | F19: =+ROUND(D19+E19,1) -> 1149 | G19: =+ROUND(G18-E19,1) -> 41450.2
... A76: 72 | B76: 47693 | D76: =+ROUND(G75*0.01,1) -> 7.3 | E76: =ROUNDUP($C$4/72,1) -> 727.2 | F76: =+ROUND(D76+E76,1) -> 734.5 | G76: =+ROUND(G75-E76,1) -> -0.2
A77: TOTAL | D77: =+SUM(D5:D76) -> 19110.8 | E77: =+SUM(E5:E76) -> 52358.4 | F77: =+SUM(F5:F76) -> 71469.2

Sheet 19
A1: SOCIO: TANIA JANET DIAZ VERA
A2: FEBRERO 2025 - PRÉSTAMO
A3: PLAZO | B3: FECHA | C3: PRÉSTAMO S/. | D3: INTERES | E3: ABONO DE CAPITAL | F3: CUOTA | G3: SALDO
A4: 0 | B4: 29/02/2025 | C4: =+J7 -> 40010.1 | D4: 0.01 | G4: =+C4 -> 40010.1
A5: 1 | B5: 45745 | D5: =+ROUND(G4*0.01,1) -> 400.1 | E5: =ROUNDDOWN($C$4/60,1) -> 666.8 | F5: =+ROUND(D5+E5,1) -> 1066.9 | G5: =+ROUND(G4-E5,1) -> 39343.3 | I5: SALDO | J5: 40010.1
A6: 2 | B6: 45776 | D6: =+ROUND(G5*0.01,1) -> 393.4 | E6: =ROUNDDOWN($C$4/60,1) -> 666.8 | F6: =+ROUND(D6+E6,1) -> 1060.2 | G6: =+ROUND(G5-E6,1) -> 38676.5 | I6: PRESTAMO | J6: 0
A7: 3 | B7: 45806 | D7: =+ROUND(G6*0.01,1) -> 386.8 | E7: =ROUNDDOWN($C$4/60,1) -> 666.8 | F7: =+ROUND(D7+E7,1) -> 1053.6 | G7: =+ROUND(G6-E7,1) -> 38009.7 | I7: TOTAL | J7: =+SUM(J5:J6) -> 40010.1
A8: 4 | B8: 45837 | D8: =+ROUND(G7*0.01,1) -> 380.1 | E8: =ROUNDDOWN($C$4/60,1) -> 666.8 | F8: =+ROUND(D8+E8,1) -> 1046.9 | G8: =+ROUND(G7-E8,1) -> 37342.9
A9: 5 | B9: 45867 | D9: =+ROUND(G8*0.01,1) -> 373.4 | E9: =ROUNDDOWN($C$4/60,1) -> 666.8 | F9: =+ROUND(D9+E9,1) -> 1040.2 | G9: =+ROUND(G8-E9,1) -> 36676.1
A10: 6 | B10: 45898 | D10: =+ROUND(G9*0.01,1) -> 366.8 | E10: =ROUNDDOWN($C$4/60,1) -> 666.8 | F10: =+ROUND(D10+E10,1) -> 1033.6 | G10: =+ROUND(G9-E10,1) -> 36009.3
A11: 7 | B11: 45929 | D11: =+ROUND(G10*0.01,1) -> 360.1 | E11: =ROUNDDOWN($C$4/60,1) -> 666.8 | F11: =+ROUND(D11+E11,1) -> 1026.9 | G11: =+ROUND(G10-E11,1) -> 35342.5
A12: 8 | B12: 45959 | D12: =+ROUND(G11*0.01,1) -> 353.4 | E12: =ROUNDDOWN($C$4/60,1) -> 666.8 | F12: =+ROUND(D12+E12,1) -> 1020.2 | G12: =+ROUND(G11-E12,1) -> 34675.7
A13: 9 | B13: 45990 | D13: =+ROUND(G12*0.01,1) -> 346.8 | E13: =ROUNDDOWN($C$4/60,1) -> 666.8 | F13: =+ROUND(D13+E13,1) -> 1013.6 | G13: =+ROUND(G12-E13,1) -> 34008.9
A14: 10 | B14: 46020 | D14: =+ROUND(G13*0.01,1) -> 340.1 | E14: =ROUNDDOWN($C$4/60,1) -> 666.8 | F14: =+ROUND(D14+E14,1) -> 1006.9 | G14: =+ROUND(G13-E14,1) -> 33342.1
A15: 11 | B15: 46051 | D15: =+ROUND(G14*0.01,1) -> 333.4 | E15: =ROUNDDOWN($C$4/60,1) -> 666.8 | F15: =+ROUND(D15+E15,1) -> 1000.2 | G15: =+ROUND(G14-E15,1) -> 32675.3
A16: 12 | B16: 46081 | D16: =+ROUND(G15*0.01,1) -> 326.8 | E16: =ROUNDDOWN($C$4/60,1) -> 666.8 | F16: =+ROUND(D16+E16,1) -> 993.6 | G16: =+ROUND(G15-E16,1) -> 32008.5
A17: 13 | B17: 46110 | D17: =+ROUND(G16*0.01,1) -> 320.1 | E17: =ROUNDDOWN($C$4/60,1) -> 666.8 | F17: =+ROUND(D17+E17,1) -> 986.9 | G17: =+ROUND(G16-E17,1) -> 31341.7
A18: 14 | B18: 46141 | D18: =+ROUND(G17*0.01,1) -> 313.4 | E18: =ROUNDDOWN($C$4/60,1) -> 666.8 | F18: =+ROUND(D18+E18,1) -> 980.2 | G18: =+ROUND(G17-E18,1) -> 30674.9
A19: 15 | B19: 46171 | D19: =+ROUND(G18*0.01,1) -> 306.7 | E19: =ROUNDDOWN($C$4/60,1) -> 666.8 | F19: =+ROUND(D19+E19,1) -> 973.5 | G19: =+ROUND(G18-E19,1) -> 30008.1
... A63: 59 | B63: 47512 | D63: =+ROUND(G62*0.01,1) -> 13.4 | E63: =ROUNDDOWN($C$4/60,1) -> 666.8 | F63: =+ROUND(D63+E63,1) -> 680.2 | G63: =+ROUND(G62-E63,1) -> 668.9
A64: 60 | B64: 47542 | D64: =+ROUND(G63*0.01,1) -> 6.7 | E64: =ROUNDDOWN($C$4/60,1)+2.1 -> 668.9 | F64: =+ROUND(D64+E64,1) -> 675.6 | G64: =+ROUND(G63-E64,1) -> 0
A65: TOTAL | D65: =+SUM(D5:D64) -> 12203.7 | E65: =+SUM(E5:E64) -> 40010.1 | F65: =+SUM(F5:F64) -> 52213.8

Sheet 20
A1: SOCIO: WILSER FILADELFIO MONTOYA CHAVEZ
A2: AGOSTO 2025 - PRÉSTAMO
A3: PLAZO | B3: FECHA | C3: PRÉSTAMO S/. | D3: INTERES | E3: ABONO DE CAPITAL | F3: CUOTA | G3: SALDO
A4: 0 | B4: 45898 | C4: =+J7 -> 55904.3 | D4: 0.01 | G4: =+C4 -> 55904.3
A5: 1 | B5: 45929 | D5: =+ROUND(G4*0.01,1) -> 559 | E5: =ROUNDDOWN($C$4/84,1) -> 665.5 | F5: =+ROUND(D5+E5,1) -> 1224.5 | G5: =+ROUND(G4-E5,1) -> 55238.8 | I5: SALDO | J5: 53125.9
A6: 2 | B6: 45959 | D6: =+ROUND(G5*0.01,1) -> 552.4 | E6: =ROUNDDOWN($C$4/84,1) -> 665.5 | F6: =+ROUND(D6+E6,1) -> 1217.9 | G6: =+ROUND(G5-E6,1) -> 54573.3 | I6: PRESTAMO | J6: 2778.4
A7: 3 | B7: 45990 | D7: =+ROUND(G6*0.01,1) -> 545.7 | E7: =ROUNDDOWN($C$4/84,1) -> 665.5 | F7: =+ROUND(D7+E7,1) -> 1211.2 | G7: =+ROUND(G6-E7,1) -> 53907.8 | I7: TOTAL | J7: =+SUM(J5:J6) -> 55904.3
A8: 4 | B8: 46020 | D8: =+ROUND(G7*0.01,1) -> 539.1 | E8: =ROUNDDOWN($C$4/84,1) -> 665.5 | F8: =+ROUND(D8+E8,1) -> 1204.6 | G8: =+ROUND(G7-E8,1) -> 53242.3
A9: 5 | B9: 46051 | D9: =+ROUND(G8*0.01,1) -> 532.4 | E9: =ROUNDDOWN($C$4/84,1) -> 665.5 | F9: =+ROUND(D9+E9,1) -> 1197.9 | G9: =+ROUND(G8-E9,1) -> 52576.8
A10: 6 | B10: 46081 | D10: =+ROUND(G9*0.01,1) -> 525.8 | E10: =ROUNDDOWN($C$4/84,1) -> 665.5 | F10: =+ROUND(D10+E10,1) -> 1191.3 | G10: =+ROUND(G9-E10,1) -> 51911.3
A11: 7 | B11: 46110 | D11: =+ROUND(G10*0.01,1) -> 519.1 | E11: =ROUNDDOWN($C$4/84,1) -> 665.5 | F11: =+ROUND(D11+E11,1) -> 1184.6 | G11: =+ROUND(G10-E11,1) -> 51245.8
A12: 8 | B12: 46141 | D12: =+ROUND(G11*0.01,1) -> 512.5 | E12: =ROUNDDOWN($C$4/84,1) -> 665.5 | F12: =+ROUND(D12+E12,1) -> 1178 | G12: =+ROUND(G11-E12,1) -> 50580.3
A13: 9 | B13: 46171 | D13: =+ROUND(G12*0.01,1) -> 505.8 | E13: =ROUNDDOWN($C$4/84,1) -> 665.5 | F13: =+ROUND(D13+E13,1) -> 1171.3 | G13: =+ROUND(G12-E13,1) -> 49914.8
A14: 10 | B14: 46202 | D14: =+ROUND(G13*0.01,1) -> 499.1 | E14: =ROUNDDOWN($C$4/84,1) -> 665.5 | F14: =+ROUND(D14+E14,1) -> 1164.6 | G14: =+ROUND(G13-E14,1) -> 49249.3
A15: 11 | B15: 46232 | D15: =+ROUND(G14*0.01,1) -> 492.5 | E15: =ROUNDDOWN($C$4/84,1) -> 665.5 | F15: =+ROUND(D15+E15,1) -> 1158 | G15: =+ROUND(G14-E15,1) -> 48583.8
A16: 12 | B16: 46263 | D16: =+ROUND(G15*0.01,1) -> 485.8 | E16: =ROUNDDOWN($C$4/84,1) -> 665.5 | F16: =+ROUND(D16+E16,1) -> 1151.3 | G16: =+ROUND(G15-E16,1) -> 47918.3
A17: 13 | B17: 46294 | D17: =+ROUND(G16*0.01,1) -> 479.2 | E17: =ROUNDDOWN($C$4/84,1) -> 665.5 | F17: =+ROUND(D17+E17,1) -> 1144.7 | G17: =+ROUND(G16-E17,1) -> 47252.8
A18: 14 | B18: 46324 | D18: =+ROUND(G17*0.01,1) -> 472.5 | E18: =ROUNDDOWN($C$4/84,1) -> 665.5 | F18: =+ROUND(D18+E18,1) -> 1138 | G18: =+ROUND(G17-E18,1) -> 46587.3
A19: 15 | B19: 46355 | D19: =+ROUND(G18*0.01,1) -> 465.9 | E19: =ROUNDDOWN($C$4/84,1) -> 665.5 | F19: =+ROUND(D19+E19,1) -> 1131.4 | G19: =+ROUND(G18-E19,1) -> 45921.8
... A87: 83 | B87: 48424 | D87: =+ROUND(G86*0.01,1) -> 13.3 | E87: =ROUNDDOWN($C$4/84,1) -> 665.5 | F87: =+ROUND(D87+E87,1) -> 678.8 | G87: =+ROUND(G86-E87,1) -> 667.8
A88: 84 | B88: 48455 | D88: =+ROUND(G87*0.01,1) -> 6.7 | E88: =ROUNDDOWN($C$4/84,1)+2.3 -> 667.8 | F88: =+ROUND(D88+E88,1) -> 674.5 | G88: =+ROUND(G87-E88,1) -> 0
A89: TOTAL | D89: =+SUM(D5:D88) -> 23760.2 | E89: =+SUM(E5:E88) -> 55904.3 | F89: =+SUM(F5:F88) -> 79664.5

Sheet 21
A1: SOCIO: LUIS FERNANDO MONTOYA CRISOLOGO
A2: ABRIL 2025 - PRÉSTAMO
A3: PLAZO | B3: FECHA | C3: PRÉSTAMO S/. | D3: INTERES | E3: ABONO DE CAPITAL | F3: CUOTA | G3: SALDO
A4: 0 | B4: 45776 | C4: =+J7 -> 36925.1 | D4: 0.01 | G4: =+C4 -> 36925.1
A5: 1 | B5: 45806 | D5: =+ROUND(G4*0.01,1) -> 369.3 | E5: =ROUNDDOWN($C$4/60,1) -> 615.4 | F5: =+ROUND(D5+E5,1) -> 984.7 | G5: =+ROUND(G4-E5,1) -> 36309.7 | I5: SALDO | J5: 21874.3
A6: 2 | B6: 45837 | D6: =+ROUND(G5*0.01,1) -> 363.1 | E6: =ROUNDDOWN($C$4/60,1) -> 615.4 | F6: =+ROUND(D6+E6,1) -> 978.5 | G6: =+ROUND(G5-E6,1) -> 35694.3 | I6: PRESTAMO | J6: 15050.8
A7: 3 | B7: 45867 | D7: =+ROUND(G6*0.01,1) -> 356.9 | E7: =ROUNDDOWN($C$4/60,1) -> 615.4 | F7: =+ROUND(D7+E7,1) -> 972.3 | G7: =+ROUND(G6-E7,1) -> 35078.9 | I7: TOTAL | J7: =+SUM(J5:J6) -> 36925.1
A8: 4 | B8: 45898 | D8: =+ROUND(G7*0.01,1) -> 350.8 | E8: =ROUNDDOWN($C$4/60,1) -> 615.4 | F8: =+ROUND(D8+E8,1) -> 966.2 | G8: =+ROUND(G7-E8,1) -> 34463.5
A9: 5 | B9: 45929 | D9: =+ROUND(G8*0.01,1) -> 344.6 | E9: =ROUNDDOWN($C$4/60,1) -> 615.4 | F9: =+ROUND(D9+E9,1) -> 960 | G9: =+ROUND(G8-E9,1) -> 33848.1
A10: 6 | B10: 45959 | D10: =+ROUND(G9*0.01,1) -> 338.5 | E10: =ROUNDDOWN($C$4/60,1) -> 615.4 | F10: =+ROUND(D10+E10,1) -> 953.9 | G10: =+ROUND(G9-E10,1) -> 33232.7
A11: 7 | B11: 45990 | D11: =+ROUND(G10*0.01,1) -> 332.3 | E11: =ROUNDDOWN($C$4/60,1) -> 615.4 | F11: =+ROUND(D11+E11,1) -> 947.7 | G11: =+ROUND(G10-E11,1) -> 32617.3
A12: 8 | B12: 46020 | D12: =+ROUND(G11*0.01,1) -> 326.2 | E12: =ROUNDDOWN($C$4/60,1) -> 615.4 | F12: =+ROUND(D12+E12,1) -> 941.6 | G12: =+ROUND(G11-E12,1) -> 32001.9
A13: 9 | B13: 46051 | D13: =+ROUND(G12*0.01,1) -> 320 | E13: =ROUNDDOWN($C$4/60,1) -> 615.4 | F13: =+ROUND(D13+E13,1) -> 935.4 | G13: =+ROUND(G12-E13,1) -> 31386.5
A14: 10 | B14: 46081 | D14: =+ROUND(G13*0.01,1) -> 313.9 | E14: =ROUNDDOWN($C$4/60,1) -> 615.4 | F14: =+ROUND(D14+E14,1) -> 929.3 | G14: =+ROUND(G13-E14,1) -> 30771.1
A15: 11 | B15: 46110 | D15: =+ROUND(G14*0.01,1) -> 307.7 | E15: =ROUNDDOWN($C$4/60,1) -> 615.4 | F15: =+ROUND(D15+E15,1) -> 923.1 | G15: =+ROUND(G14-E15,1) -> 30155.7
A16: 12 | B16: 46141 | D16: =+ROUND(G15*0.01,1) -> 301.6 | E16: =ROUNDDOWN($C$4/60,1) -> 615.4 | F16: =+ROUND(D16+E16,1) -> 917 | G16: =+ROUND(G15-E16,1) -> 29540.3
A17: 13 | B17: 46171 | D17: =+ROUND(G16*0.01,1) -> 295.4 | E17: =ROUNDDOWN($C$4/60,1) -> 615.4 | F17: =+ROUND(D17+E17,1) -> 910.8 | G17: =+ROUND(G16-E17,1) -> 28924.9
A18: 14 | B18: 46202 | D18: =+ROUND(G17*0.01,1) -> 289.2 | E18: =ROUNDDOWN($C$4/60,1) -> 615.4 | F18: =+ROUND(D18+E18,1) -> 904.6 | G18: =+ROUND(G17-E18,1) -> 28309.5
A19: 15 | B19: 46232 | D19: =+ROUND(G18*0.01,1) -> 283.1 | E19: =ROUNDDOWN($C$4/60,1) -> 615.4 | F19: =+ROUND(D19+E19,1) -> 898.5 | G19: =+ROUND(G18-E19,1) -> 27694.1
... A63: 59 | B63: 47571 | D63: =+ROUND(G62*0.01,1) -> 12.3 | E63: =ROUNDDOWN($C$4/60,1) -> 615.4 | F63: =+ROUND(D63+E63,1) -> 627.7 | G63: =+ROUND(G62-E63,1) -> 616.5
A64: 60 | B64: 47602 | D64: =+ROUND(G63*0.01,1) -> 6.2 | E64: =ROUNDDOWN($C$4/60,1)+1.1 -> 616.5 | F64: =+ROUND(D64+E64,1) -> 622.7 | G64: =+ROUND(G63-E64,1) -> 0
A65: TOTAL | D65: =+SUM(D5:D64) -> 11262.5 | E65: =+SUM(E5:E64) -> 36925.1 | F65: =+SUM(F5:F64) -> 48187.6

Sheet 22
A1: SOCIO: HUGO DELESMIRO MONTOYA MACHUCA
A2: FEBRERO 2025 - PRÉSTAMO
A3: PLAZO | B3: FECHA | C3: PRÉSTAMO S/. | D3: INTERES | E3: ABONO DE CAPITAL | F3: CUOTA | G3: SALDO
A4: 0 | B4: 29/02/2025 | C4: =+J7 -> 12049.4 | D4: 0.01 | G4: =+C4 -> 12049.4
A5: 1 | B5: 45745 | D5: =+ROUND(G4*0.01,1) -> 120.5 | E5: =ROUNDDOWN($C$4/60,1) -> 200.8 | F5: =+ROUND(D5+E5,1) -> 321.3 | G5: =+ROUND(G4-E5,1) -> 11848.6 | I5: SALDO | J5: 6577.2
A6: 2 | B6: 45776 | D6: =+ROUND(G5*0.01,1) -> 118.5 | E6: =ROUNDDOWN($C$4/60,1) -> 200.8 | F6: =+ROUND(D6+E6,1) -> 319.3 | G6: =+ROUND(G5-E6,1) -> 11647.8 | I6: PRESTAMO | J6: 5472.2
A7: 3 | B7: 45806 | D7: =+ROUND(G6*0.01,1) -> 116.5 | E7: =ROUNDDOWN($C$4/60,1) -> 200.8 | F7: =+ROUND(D7+E7,1) -> 317.3 | G7: =+ROUND(G6-E7,1) -> 11447 | I7: TOTAL | J7: =+SUM(J5:J6) -> 12049.4
A8: 4 | B8: 45837 | D8: =+ROUND(G7*0.01,1) -> 114.5 | E8: =ROUNDDOWN($C$4/60,1) -> 200.8 | F8: =+ROUND(D8+E8,1) -> 315.3 | G8: =+ROUND(G7-E8,1) -> 11246.2
A9: 5 | B9: 45867 | D9: =+ROUND(G8*0.01,1) -> 112.5 | E9: =ROUNDDOWN($C$4/60,1) -> 200.8 | F9: =+ROUND(D9+E9,1) -> 313.3 | G9: =+ROUND(G8-E9,1) -> 11045.4
A10: 6 | B10: 45898 | D10: =+ROUND(G9*0.01,1) -> 110.5 | E10: =ROUNDDOWN($C$4/60,1) -> 200.8 | F10: =+ROUND(D10+E10,1) -> 311.3 | G10: =+ROUND(G9-E10,1) -> 10844.6
A11: 7 | B11: 45929 | D11: =+ROUND(G10*0.01,1) -> 108.4 | E11: =ROUNDDOWN($C$4/60,1) -> 200.8 | F11: =+ROUND(D11+E11,1) -> 309.2 | G11: =+ROUND(G10-E11,1) -> 10643.8 | I11: INTERES | J11: =SUM(D5:D12) -> 907.8
A12: 8 | B12: 45959 | D12: =+ROUND(G11*0.01,1) -> 106.4 | E12: =ROUNDDOWN($C$4/60,1) -> 200.8 | F12: =+ROUND(D12+E12,1) -> 307.2 | G12: =+ROUND(G11-E12,1) -> 10443 | I12: SALDO | J12: =G12 -> 10443
A13: 9 | B13: 45990 | D13: =+ROUND(G12*0.01,1) -> 104.4 | E13: =ROUNDDOWN($C$4/60,1) -> 200.8 | F13: =+ROUND(D13+E13,1) -> 305.2 | G13: =+ROUND(G12-E13,1) -> 10242.2
A14: 10 | B14: 46020 | D14: =+ROUND(G13*0.01,1) -> 102.4 | E14: =ROUNDDOWN($C$4/60,1) -> 200.8 | F14: =+ROUND(D14+E14,1) -> 303.2 | G14: =+ROUND(G13-E14,1) -> 10041.4
A15: 11 | B15: 46051 | D15: =+ROUND(G14*0.01,1) -> 100.4 | E15: =ROUNDDOWN($C$4/60,1) -> 200.8 | F15: =+ROUND(D15+E15,1) -> 301.2 | G15: =+ROUND(G14-E15,1) -> 9840.6
A16: 12 | B16: 46081 | D16: =+ROUND(G15*0.01,1) -> 98.4 | E16: =ROUNDDOWN($C$4/60,1) -> 200.8 | F16: =+ROUND(D16+E16,1) -> 299.2 | G16: =+ROUND(G15-E16,1) -> 9639.8
A17: 13 | B17: 46110 | D17: =+ROUND(G16*0.01,1) -> 96.4 | E17: =ROUNDDOWN($C$4/60,1) -> 200.8 | F17: =+ROUND(D17+E17,1) -> 297.2 | G17: =+ROUND(G16-E17,1) -> 9439
A18: 14 | B18: 46141 | D18: =+ROUND(G17*0.01,1) -> 94.4 | E18: =ROUNDDOWN($C$4/60,1) -> 200.8 | F18: =+ROUND(D18+E18,1) -> 295.2 | G18: =+ROUND(G17-E18,1) -> 9238.2
A19: 15 | B19: 46171 | D19: =+ROUND(G18*0.01,1) -> 92.4 | E19: =ROUNDDOWN($C$4/60,1) -> 200.8 | F19: =+ROUND(D19+E19,1) -> 293.2 | G19: =+ROUND(G18-E19,1) -> 9037.4
A20: 16 | B20: 46202 | D20: =+ROUND(G19*0.01,1) -> 90.4 | E20: =ROUNDDOWN($C$4/60,1) -> 200.8 | F20: =+ROUND(D20+E20,1) -> 291.2 | G20: =+ROUND(G19-E20,1) -> 8836.6
A21: 17 | B21: 46232 | D21: =+ROUND(G20*0.01,1) -> 88.4 | E21: =ROUNDDOWN($C$4/60,1) -> 200.8 | F21: =+ROUND(D21+E21,1) -> 289.2 | G21: =+ROUND(G20-E21,1) -> 8635.8
A22: 18 | B22: 46263 | D22: =+ROUND(G21*0.01,1) -> 86.4 | E22: =ROUNDDOWN($C$4/60,1) -> 200.8 | F22: =+ROUND(D22+E22,1) -> 287.2 | G22: =+ROUND(G21-E22,1) -> 8435
A23: 19 | B23: 46294 | D23: =+ROUND(G22*0.01,1) -> 84.4 | E23: =ROUNDDOWN($C$4/60,1) -> 200.8 | F23: =+ROUND(D23+E23,1) -> 285.2 | G23: =+ROUND(G22-E23,1) -> 8234.2
A24: 20 | B24: 46324 | D24: =+ROUND(G23*0.01,1) -> 82.3 | E24: =ROUNDDOWN($C$4/60,1) -> 200.8 | F24: =+ROUND(D24+E24,1) -> 283.1 | G24: =+ROUND(G23-E24,1) -> 8033.4
... A63: 59 | B63: 47512 | D63: =+ROUND(G62*0.01,1) -> 4 | E63: =ROUNDDOWN($C$4/60,1) -> 200.8 | F63: =+ROUND(D63+E63,1) -> 204.8 | G63: =+ROUND(G62-E63,1) -> 202.2
A64: 60 | B64: 47542 | D64: =+ROUND(G63*0.01,1) -> 2 | E64: =ROUNDDOWN($C$4/60,1)+1.4 -> 202.2 | F64: =+ROUND(D64+E64,1) -> 204.2 | G64: =+ROUND(G63-E64,1) -> 0
A65: TOTAL | D65: =+SUM(D5:D64) -> 3675.6 | E65: =+SUM(E5:E64) -> 12049.4 | F65: =+SUM(F5:F64) -> 15725
A68: SOCIO: HUGO DELESMIRO MONTOYA MACHUCA
A69: OCTUBRE 2025 - PRÉSTAMO
A70: PLAZO | B70: FECHA | C70: PRÉSTAMO S/. | D70: INTERES | E70: ABONO DE CAPITAL | F70: CUOTA | G70: SALDO
A71: 0 | B71: 45959 | C71: =J74 -> 20443 | D71: 0.01 | G71: =C71 -> 20443
A72: 1 | B72: 45990 | D72: =+ROUND(G71*0.01,1) -> 204.4 | E72: =ROUNDDOWN($C$71/60,1) -> 340.7 | F72: =+ROUND(D72+E72,1) -> 545.1 | G72: =+ROUND(G71-E72,1) -> 20102.3 | I72: SALDO | J72: =G12 -> 10443
A73: 2 | B73: 46020 | D73: =+ROUND(G72*0.01,1) -> 201 | E73: =ROUNDDOWN($C$71/60,1) -> 340.7 | F73: =+ROUND(D73+E73,1) -> 541.7 | G73: =+ROUND(G72-E73,1) -> 19761.6 | I73: PRESTAMO | J73: 10000
A74: 3 | B74: 46051 | D74: =+ROUND(G73*0.01,1) -> 197.6 | E74: =ROUNDDOWN($C$71/60,1) -> 340.7 | F74: =+ROUND(D74+E74,1) -> 538.3 | G74: =+ROUND(G73-E74,1) -> 19420.9 | I74: TOTAL | J74: =J72+J73 -> 20443
A75: 4 | B75: 46081 | D75: =+ROUND(G74*0.01,1) -> 194.2 | E75: =ROUNDDOWN($C$71/60,1) -> 340.7 | F75: =+ROUND(D75+E75,1) -> 534.9 | G75: =+ROUND(G74-E75,1) -> 19080.2
A76: 5 | B76: 46110 | D76: =+ROUND(G75*0.01,1) -> 190.8 | E76: =ROUNDDOWN($C$71/60,1) -> 340.7 | F76: =+ROUND(D76+E76,1) -> 531.5 | G76: =+ROUND(G75-E76,1) -> 18739.5
A77: 6 | B77: 46141 | D77: =+ROUND(G76*0.01,1) -> 187.4 | E77: =ROUNDDOWN($C$71/60,1) -> 340.7 | F77: =+ROUND(D77+E77,1) -> 528.1 | G77: =+ROUND(G76-E77,1) -> 18398.8
A78: 7 | B78: 46171 | D78: =+ROUND(G77*0.01,1) -> 184 | E78: =ROUNDDOWN($C$71/60,1) -> 340.7 | F78: =+ROUND(D78+E78,1) -> 524.7 | G78: =+ROUND(G77-E78,1) -> 18058.1
A79: 8 | B79: 46202 | D79: =+ROUND(G78*0.01,1) -> 180.6 | E79: =ROUNDDOWN($C$71/60,1) -> 340.7 | F79: =+ROUND(D79+E79,1) -> 521.3 | G79: =+ROUND(G78-E79,1) -> 17717.4
A80: 9 | B80: 46232 | D80: =+ROUND(G79*0.01,1) -> 177.2 | E80: =ROUNDDOWN($C$71/60,1) -> 340.7 | F80: =+ROUND(D80+E80,1) -> 517.9 | G80: =+ROUND(G79-E80,1) -> 17376.7
A81: 10 | B81: 46263 | D81: =+ROUND(G80*0.01,1) -> 173.8 | E81: =ROUNDDOWN($C$71/60,1) -> 340.7 | F81: =+ROUND(D81+E81,1) -> 514.5 | G81: =+ROUND(G80-E81,1) -> 17036
A82: 11 | B82: 46294 | D82: =+ROUND(G81*0.01,1) -> 170.4 | E82: =ROUNDDOWN($C$71/60,1) -> 340.7 | F82: =+ROUND(D82+E82,1) -> 511.1 | G82: =+ROUND(G81-E82,1) -> 16695.3
A83: 12 | B83: 46324 | D83: =+ROUND(G82*0.01,1) -> 167 | E83: =ROUNDDOWN($C$71/60,1) -> 340.7 | F83: =+ROUND(D83+E83,1) -> 507.7 | G83: =+ROUND(G82-E83,1) -> 16354.6
A84: 13 | B84: 46355 | D84: =+ROUND(G83*0.01,1) -> 163.5 | E84: =ROUNDDOWN($C$71/60,1) -> 340.7 | F84: =+ROUND(D84+E84,1) -> 504.2 | G84: =+ROUND(G83-E84,1) -> 16013.9
A85: 14 | B85: 46385 | D85: =+ROUND(G84*0.01,1) -> 160.1 | E85: =ROUNDDOWN($C$71/60,1) -> 340.7 | F85: =+ROUND(D85+E85,1) -> 500.8 | G85: =+ROUND(G84-E85,1) -> 15673.2
A86: 15 | B86: 46416 | D86: =+ROUND(G85*0.01,1) -> 156.7 | E86: =ROUNDDOWN($C$71/60,1) -> 340.7 | F86: =+ROUND(D86+E86,1) -> 497.4 | G86: =+ROUND(G85-E86,1) -> 15332.5
... A130: 59 | B130: 47755 | D130: =+ROUND(G129*0.01,1) -> 6.8 | E130: =ROUNDDOWN($C$71/60,1) -> 340.7 | F130: =+ROUND(D130+E130,1) -> 347.5 | G130: =+ROUND(G129-E130,1) -> 341.7
A131: 60 | B131: 47785 | D131: =+ROUND(G130*0.01,1) -> 3.4 | E131: =ROUNDDOWN($C$71/60,1)+1 -> 341.7 | F131: =+ROUND(D131+E131,1) -> 345.1 | G131: =+ROUND(G130-E131,1) -> 0
A132: TOTAL | D132: =+SUM(D72:D131) -> 6235.4 | E132: =+SUM(E72:E131) -> 20443 | F132: =+SUM(F72:F131) -> 26678.4

Sheet 23
A1: SOCIO: JHONATAN GUILLERMO PEREYRA CHAVEZ
A2: SETIEMBRE 2024 - PRÉSTAMO
A3: PLAZO | B3: FECHA | C3: PRÉSTAMO S/. | D3: INTERES | E3: ABONO DE CAPITAL | F3: CUOTA | G3: SALDO
A4: 0 | B4: 45564 | C4: =+J7 -> 18680.5 | D4: 0.01 | G4: =+C4 -> 18680.5
A5: 1 | B5: 45594 | D5: =+ROUND(G4*0.01,1) -> 186.8 | E5: =ROUNDDOWN($C$4/60,1) -> 311.3 | F5: =+ROUND(D5+E5,1) -> 498.1 | G5: =+ROUND(G4-E5,1) -> 18369.2 | I5: SALDO | J5: 9610
A6: 2 | B6: 45625 | D6: =+ROUND(G5*0.01,1) -> 183.7 | E6: =ROUNDDOWN($C$4/60,1) -> 311.3 | F6: =+ROUND(D6+E6,1) -> 495 | G6: =+ROUND(G5-E6,1) -> 18057.9 | I6: PRÉSTAMO | J6: 9070.5
A7: 3 | B7: 45655 | D7: =+ROUND(G6*0.01,1) -> 180.6 | E7: =ROUNDDOWN($C$4/60,1) -> 311.3 | F7: =+ROUND(D7+E7,1) -> 491.9 | G7: =+ROUND(G6-E7,1) -> 17746.6 | I7: TOTAL | J7: =+SUM(J5:J6) -> 18680.5
A8: 4 | B8: 45686 | D8: =+ROUND(G7*0.01,1) -> 177.5 | E8: =ROUNDDOWN($C$4/60,1) -> 311.3 | F8: =+ROUND(D8+E8,1) -> 488.8 | G8: =+ROUND(G7-E8,1) -> 17435.3
A9: 5 | B9: 45716 | D9: =+ROUND(G8*0.01,1) -> 174.4 | E9: =ROUNDDOWN($C$4/60,1) -> 311.3 | F9: =+ROUND(D9+E9,1) -> 485.7 | G9: =+ROUND(G8-E9,1) -> 17124
A10: 6 | B10: 45745 | D10: =+ROUND(G9*0.01,1) -> 171.2 | E10: =ROUNDDOWN($C$4/60,1) -> 311.3 | F10: =+ROUND(D10+E10,1) -> 482.5 | G10: =+ROUND(G9-E10,1) -> 16812.7
A11: 7 | B11: 45776 | D11: =+ROUND(G10*0.01,1) -> 168.1 | E11: =ROUNDDOWN($C$4/60,1) -> 311.3 | F11: =+ROUND(D11+E11,1) -> 479.4 | G11: =+ROUND(G10-E11,1) -> 16501.4
A12: 8 | B12: 45806 | D12: =+ROUND(G11*0.01,1) -> 165 | E12: =ROUNDDOWN($C$4/60,1) -> 311.3 | F12: =+ROUND(D12+E12,1) -> 476.3 | G12: =+ROUND(G11-E12,1) -> 16190.1
A13: 9 | B13: 45837 | D13: =+ROUND(G12*0.01,1) -> 161.9 | E13: =ROUNDDOWN($C$4/60,1) -> 311.3 | F13: =+ROUND(D13+E13,1) -> 473.2 | G13: =+ROUND(G12-E13,1) -> 15878.8
A14: 10 | B14: 45867 | D14: =+ROUND(G13*0.01,1) -> 158.8 | E14: =ROUNDDOWN($C$4/60,1) -> 311.3 | F14: =+ROUND(D14+E14,1) -> 470.1 | G14: =+ROUND(G13-E14,1) -> 15567.5
A15: 11 | B15: 45898 | D15: =+ROUND(G14*0.01,1) -> 155.7 | E15: =ROUNDDOWN($C$4/60,1) -> 311.3 | F15: =+ROUND(D15+E15,1) -> 467 | G15: =+ROUND(G14-E15,1) -> 15256.2
A16: 12 | B16: 45929 | D16: =+ROUND(G15*0.01,1) -> 152.6 | E16: =ROUNDDOWN($C$4/60,1) -> 311.3 | F16: =+ROUND(D16+E16,1) -> 463.9 | G16: =+ROUND(G15-E16,1) -> 14944.9
A17: 13 | B17: 45959 | D17: =+ROUND(G16*0.01,1) -> 149.4 | E17: =ROUNDDOWN($C$4/60,1) -> 311.3 | F17: =+ROUND(D17+E17,1) -> 460.7 | G17: =+ROUND(G16-E17,1) -> 14633.6
A18: 14 | B18: 45990 | D18: =+ROUND(G17*0.01,1) -> 146.3 | E18: =ROUNDDOWN($C$4/60,1) -> 311.3 | F18: =+ROUND(D18+E18,1) -> 457.6 | G18: =+ROUND(G17-E18,1) -> 14322.3
A19: 15 | B19: 46020 | D19: =+ROUND(G18*0.01,1) -> 143.2 | E19: =ROUNDDOWN($C$4/60,1) -> 311.3 | F19: =+ROUND(D19+E19,1) -> 454.5 | G19: =+ROUND(G18-E19,1) -> 14011 | I19: INTERES | J19: =SUM(D5:D20) -> 2615.3
A20: 16 | B20: 46051 | D20: =+ROUND(G19*0.01,1) -> 140.1 | E20: =ROUNDDOWN($C$4/60,1) -> 311.3 | F20: =+ROUND(D20+E20,1) -> 451.4 | G20: =+ROUND(G19-E20,1) -> 13699.7 | I20: SALDO | J20: =G20 -> 13699.7
A21: 17 | B21: 46081 | D21: =+ROUND(G20*0.01,1) -> 137 | E21: =ROUNDDOWN($C$4/60,1) -> 311.3 | F21: =+ROUND(D21+E21,1) -> 448.3 | G21: =+ROUND(G20-E21,1) -> 13388.4
A22: 18 | B22: 46110 | D22: =+ROUND(G21*0.01,1) -> 133.9 | E22: =ROUNDDOWN($C$4/60,1) -> 311.3 | F22: =+ROUND(D22+E22,1) -> 445.2 | G22: =+ROUND(G21-E22,1) -> 13077.1
A23: 19 | B23: 46141 | D23: =+ROUND(G22*0.01,1) -> 130.8 | E23: =ROUNDDOWN($C$4/60,1) -> 311.3 | F23: =+ROUND(D23+E23,1) -> 442.1 | G23: =+ROUND(G22-E23,1) -> 12765.8
A24: 20 | B24: 46171 | D24: =+ROUND(G23*0.01,1) -> 127.7 | E24: =ROUNDDOWN($C$4/60,1) -> 311.3 | F24: =+ROUND(D24+E24,1) -> 439 | G24: =+ROUND(G23-E24,1) -> 12454.5
A25: 21 | B25: 46202 | D25: =+ROUND(G24*0.01,1) -> 124.5 | E25: =ROUNDDOWN($C$4/60,1) -> 311.3 | F25: =+ROUND(D25+E25,1) -> 435.8 | G25: =+ROUND(G24-E25,1) -> 12143.2
A26: 22 | B26: 46232 | D26: =+ROUND(G25*0.01,1) -> 121.4 | E26: =ROUNDDOWN($C$4/60,1) -> 311.3 | F26: =+ROUND(D26+E26,1) -> 432.7 | G26: =+ROUND(G25-E26,1) -> 11831.9
A27: 23 | B27: 46263 | D27: =+ROUND(G26*0.01,1) -> 118.3 | E27: =ROUNDDOWN($C$4/60,1) -> 311.3 | F27: =+ROUND(D27+E27,1) -> 429.6 | G27: =+ROUND(G26-E27,1) -> 11520.6
A28: 24 | B28: 46294 | D28: =+ROUND(G27*0.01,1) -> 115.2 | E28: =ROUNDDOWN($C$4/60,1) -> 311.3 | F28: =+ROUND(D28+E28,1) -> 426.5 | G28: =+ROUND(G27-E28,1) -> 11209.3
A29: 25 | B29: 46324 | D29: =+ROUND(G28*0.01,1) -> 112.1 | E29: =ROUNDDOWN($C$4/60,1) -> 311.3 | F29: =+ROUND(D29+E29,1) -> 423.4 | G29: =+ROUND(G28-E29,1) -> 10898
A30: 26 | B30: 46355 | D30: =+ROUND(G29*0.01,1) -> 109 | E30: =ROUNDDOWN($C$4/60,1) -> 311.3 | F30: =+ROUND(D30+E30,1) -> 420.3 | G30: =+ROUND(G29-E30,1) -> 10586.7
A31: 27 | B31: 46385 | D31: =+ROUND(G30*0.01,1) -> 105.9 | E31: =ROUNDDOWN($C$4/60,1) -> 311.3 | F31: =+ROUND(D31+E31,1) -> 417.2 | G31: =+ROUND(G30-E31,1) -> 10275.4
A32: 28 | B32: 46416 | D32: =+ROUND(G31*0.01,1) -> 102.8 | E32: =ROUNDDOWN($C$4/60,1) -> 311.3 | F32: =+ROUND(D32+E32,1) -> 414.1 | G32: =+ROUND(G31-E32,1) -> 9964.1
... A63: 59 | B63: 47359 | D63: =+ROUND(G62*0.01,1) -> 6.3 | E63: =ROUNDDOWN($C$4/60,1) -> 311.3 | F63: =+ROUND(D63+E63,1) -> 317.6 | G63: =+ROUND(G62-E63,1) -> 313.8
A64: 60 | B64: 47390 | D64: =+ROUND(G63*0.01,1) -> 3.1 | E64: =ROUNDDOWN($C$4/60,1)+2.5 -> 313.8 | F64: =+ROUND(D64+E64,1) -> 316.9 | G64: =+ROUND(G63-E64,1) -> 0
A65: TOTAL | D65: =+SUM(D5:D64) -> 5698.4 | E65: =+SUM(E5:E64) -> 18680.5 | F65: =+SUM(F5:F64) -> 24378.9
A67: SOCIO: WILSER FILADELFIO MONTOYA CHAVEZ
A68: ENERO 2026 - PRÉSTAMO
A69: PLAZO | B69: FECHA | C69: PRÉSTAMO S/. | D69: INTERES | E69: ABONO DE CAPITAL | F69: CUOTA | G69: SALDO
A70: 0 | B70: 46051 | C70: =+J73 -> 21001.4 | D70: 0.01 | G70: =+C70 -> 21001.4
A71: 1 | B71: 46081 | D71: =+ROUND(G70*0.01,1) -> 210 | E71: =ROUND($C$70/84,1) -> 250 | F71: =+ROUND(D71+E71,1) -> 460 | G71: =+ROUND(G70-E71,1) -> 20751.4 | I71: SALDO | J71: =G20 -> 13699.7
A72: 2 | B72: 46110 | D72: =+ROUND(G71*0.01,1) -> 207.5 | E72: =ROUND($C$70/84,1) -> 250 | F72: =+ROUND(D72+E72,1) -> 457.5 | G72: =+ROUND(G71-E72,1) -> 20501.4 | I72: PRESTAMO | J72: 7301.7
A73: 3 | B73: 46141 | D73: =+ROUND(G72*0.01,1) -> 205 | E73: =ROUND($C$70/84,1) -> 250 | F73: =+ROUND(D73+E73,1) -> 455 | G73: =+ROUND(G72-E73,1) -> 20251.4 | I73: TOTAL | J73: =+SUM(J71:J72) -> 21001.4
A74: 4 | B74: 46171 | D74: =+ROUND(G73*0.01,1) -> 202.5 | E74: =ROUND($C$70/84,1) -> 250 | F74: =+ROUND(D74+E74,1) -> 452.5 | G74: =+ROUND(G73-E74,1) -> 20001.4
A75: 5 | B75: 46202 | D75: =+ROUND(G74*0.01,1) -> 200 | E75: =ROUND($C$70/84,1) -> 250 | F75: =+ROUND(D75+E75,1) -> 450 | G75: =+ROUND(G74-E75,1) -> 19751.4
A76: 6 | B76: 46232 | D76: =+ROUND(G75*0.01,1) -> 197.5 | E76: =ROUND($C$70/84,1) -> 250 | F76: =+ROUND(D76+E76,1) -> 447.5 | G76: =+ROUND(G75-E76,1) -> 19501.4
A77: 7 | B77: 46263 | D77: =+ROUND(G76*0.01,1) -> 195 | E77: =ROUND($C$70/84,1) -> 250 | F77: =+ROUND(D77+E77,1) -> 445 | G77: =+ROUND(G76-E77,1) -> 19251.4
A78: 8 | B78: 46294 | D78: =+ROUND(G77*0.01,1) -> 192.5 | E78: =ROUND($C$70/84,1) -> 250 | F78: =+ROUND(D78+E78,1) -> 442.5 | G78: =+ROUND(G77-E78,1) -> 19001.4
A79: 9 | B79: 46324 | D79: =+ROUND(G78*0.01,1) -> 190 | E79: =ROUND($C$70/84,1) -> 250 | F79: =+ROUND(D79+E79,1) -> 440 | G79: =+ROUND(G78-E79,1) -> 18751.4
A80: 10 | B80: 46355 | D80: =+ROUND(G79*0.01,1) -> 187.5 | E80: =ROUND($C$70/84,1) -> 250 | F80: =+ROUND(D80+E80,1) -> 437.5 | G80: =+ROUND(G79-E80,1) -> 18501.4
A81: 11 | B81: 46385 | D81: =+ROUND(G80*0.01,1) -> 185 | E81: =ROUND($C$70/84,1) -> 250 | F81: =+ROUND(D81+E81,1) -> 435 | G81: =+ROUND(G80-E81,1) -> 18251.4
A82: 12 | B82: 46416 | D82: =+ROUND(G81*0.01,1) -> 182.5 | E82: =ROUND($C$70/84,1) -> 250 | F82: =+ROUND(D82+E82,1) -> 432.5 | G82: =+ROUND(G81-E82,1) -> 18001.4
A83: 13 | B83: 46446 | D83: =+ROUND(G82*0.01,1) -> 180 | E83: =ROUND($C$70/84,1) -> 250 | F83: =+ROUND(D83+E83,1) -> 430 | G83: =+ROUND(G82-E83,1) -> 17751.4
A84: 14 | B84: 46475 | D84: =+ROUND(G83*0.01,1) -> 177.5 | E84: =ROUND($C$70/84,1) -> 250 | F84: =+ROUND(D84+E84,1) -> 427.5 | G84: =+ROUND(G83-E84,1) -> 17501.4
A85: 15 | B85: 46506 | D85: =+ROUND(G84*0.01,1) -> 175 | E85: =ROUND($C$70/84,1) -> 250 | F85: =+ROUND(D85+E85,1) -> 425 | G85: =+ROUND(G84-E85,1) -> 17251.4
... A153: 83 | B153: 48577 | D153: =+ROUND(G152*0.01,1) -> 5 | E153: =ROUND($C$70/84,1) -> 250 | F153: =+ROUND(D153+E153,1) -> 255 | G153: =+ROUND(G152-E153,1) -> 251.4
A154: 84 | B154: 48608 | D154: =+ROUND(G153*0.01,1) -> 2.5 | E154: =ROUND($C$70/84,1)+1.4 -> 251.4 | F154: =+ROUND(D154+E154,1) -> 253.9 | G154: =+ROUND(G153-E154,1) -> 0
A155: TOTAL | D155: =+SUM(D71:D154) -> 8925 | E155: =+SUM(E71:E154) -> 21001.4 | F155: =+SUM(F71:F154) -> 29926.4

Sheet 24
A1: SOCIA: PEREYRA RODRIGUEZ, BERTHA ESTHER
A2: AGOSTO 2024 - PRÉSTAMO
A3: PLAZO | B3: FECHA | C3: PRÉSTAMO S/. | D3: INTERES | E3: ABONO DE CAPITAL | F3: CUOTA | G3: SALDO
A4: 0 | B4: 45533 | C4: =+J7 -> 14956.1 | D4: 0.01 | G4: =+C4 -> 14956.1
A5: 1 | B5: 45564 | D5: =+ROUND(G4*0.01,1) -> 149.6 | E5: =ROUNDUP($C$4/48,1) -> 311.6 | F5: =+ROUND(D5+E5,1) -> 461.2 | G5: =+ROUND(G4-E5,1) -> 14644.5 | I5: SALDO | J5: 3170.1
A6: 2 | B6: 45594 | D6: =+ROUND(G5*0.01,1) -> 146.4 | E6: =ROUNDUP($C$4/48,1) -> 311.6 | F6: =+ROUND(D6+E6,1) -> 458 | G6: =+ROUND(G5-E6,1) -> 14332.9 | I6: PRESTAMO | J6: 11786
A7: 3 | B7: 45625 | D7: =+ROUND(G6*0.01,1) -> 143.3 | E7: =ROUNDUP($C$4/48,1) -> 311.6 | F7: =+ROUND(D7+E7,1) -> 454.9 | G7: =+ROUND(G6-E7,1) -> 14021.3 | I7: TOTAL | J7: =+SUM(J5:J6) -> 14956.1
A8: 4 | B8: 45655 | D8: =+ROUND(G7*0.01,1) -> 140.2 | E8: =ROUNDUP($C$4/48,1) -> 311.6 | F8: =+ROUND(D8+E8,1) -> 451.8 | G8: =+ROUND(G7-E8,1) -> 13709.7
A9: 5 | B9: 45686 | D9: =+ROUND(G8*0.01,1) -> 137.1 | E9: =ROUNDUP($C$4/48,1) -> 311.6 | F9: =+ROUND(D9+E9,1) -> 448.7 | G9: =+ROUND(G8-E9,1) -> 13398.1
A10: 6 | B10: 45716 | D10: =+ROUND(G9*0.01,1) -> 134 | E10: =ROUNDUP($C$4/48,1) -> 311.6 | F10: =+ROUND(D10+E10,1) -> 445.6 | G10: =+ROUND(G9-E10,1) -> 13086.5
A11: 7 | B11: 45745 | D11: =+ROUND(G10*0.01,1) -> 130.9 | E11: =ROUNDUP($C$4/48,1) -> 311.6 | F11: =+ROUND(D11+E11,1) -> 442.5 | G11: =+ROUND(G10-E11,1) -> 12774.9
A12: 8 | B12: 45776 | D12: =+ROUND(G11*0.01,1) -> 127.7 | E12: =ROUNDUP($C$4/48,1) -> 311.6 | F12: =+ROUND(D12+E12,1) -> 439.3 | G12: =+ROUND(G11-E12,1) -> 12463.3
A13: 9 | B13: 45806 | D13: =+ROUND(G12*0.01,1) -> 124.6 | E13: =ROUNDUP($C$4/48,1) -> 311.6 | F13: =+ROUND(D13+E13,1) -> 436.2 | G13: =+ROUND(G12-E13,1) -> 12151.7
A14: 10 | B14: 45837 | D14: =+ROUND(G13*0.01,1) -> 121.5 | E14: =ROUNDUP($C$4/48,1) -> 311.6 | F14: =+ROUND(D14+E14,1) -> 433.1 | G14: =+ROUND(G13-E14,1) -> 11840.1
A15: 11 | B15: 45867 | D15: =+ROUND(G14*0.01,1) -> 118.4 | E15: =ROUNDUP($C$4/48,1) -> 311.6 | F15: =+ROUND(D15+E15,1) -> 430 | G15: =+ROUND(G14-E15,1) -> 11528.5
A16: 12 | B16: 45898 | D16: =+ROUND(G15*0.01,1) -> 115.3 | E16: =ROUNDUP($C$4/48,1) -> 311.6 | F16: =+ROUND(D16+E16,1) -> 426.9 | G16: =+ROUND(G15-E16,1) -> 11216.9
A17: 13 | B17: 45929 | D17: =+ROUND(G16*0.01,1) -> 112.2 | E17: =ROUNDUP($C$4/48,1) -> 311.6 | F17: =+ROUND(D17+E17,1) -> 423.8 | G17: =+ROUND(G16-E17,1) -> 10905.3
A18: 14 | B18: 45959 | D18: =+ROUND(G17*0.01,1) -> 109.1 | E18: =ROUNDUP($C$4/48,1) -> 311.6 | F18: =+ROUND(D18+E18,1) -> 420.7 | G18: =+ROUND(G17-E18,1) -> 10593.7 | I18: INTERES | J18: =SUM(D5:D20) -> 2019
A19: 15 | B19: 45990 | D19: =+ROUND(G18*0.01,1) -> 105.9 | E19: =ROUNDUP($C$4/48,1) -> 311.6 | F19: =+ROUND(D19+E19,1) -> 417.5 | G19: =+ROUND(G18-E19,1) -> 10282.1 | I19: SALDO | J19: =G20 -> 9970.5
A20: 16 | B20: 46020 | D20: =+ROUND(G19*0.01,1) -> 102.8 | E20: =ROUNDUP($C$4/48,1) -> 311.6 | F20: =+ROUND(D20+E20,1) -> 414.4 | G20: =+ROUND(G19-E20,1) -> 9970.5
A21: 17 | B21: 46051 | D21: =+ROUND(G20*0.01,1) -> 99.7 | E21: =ROUNDUP($C$4/48,1) -> 311.6 | F21: =+ROUND(D21+E21,1) -> 411.3 | G21: =+ROUND(G20-E21,1) -> 9658.9
A22: 18 | B22: 46081 | D22: =+ROUND(G21*0.01,1) -> 96.6 | E22: =ROUNDUP($C$4/48,1) -> 311.6 | F22: =+ROUND(D22+E22,1) -> 408.2 | G22: =+ROUND(G21-E22,1) -> 9347.3
A23: 19 | B23: 46110 | D23: =+ROUND(G22*0.01,1) -> 93.5 | E23: =ROUNDUP($C$4/48,1) -> 311.6 | F23: =+ROUND(D23+E23,1) -> 405.1 | G23: =+ROUND(G22-E23,1) -> 9035.7
A24: 20 | B24: 46141 | D24: =+ROUND(G23*0.01,1) -> 90.4 | E24: =ROUNDUP($C$4/48,1) -> 311.6 | F24: =+ROUND(D24+E24,1) -> 402 | G24: =+ROUND(G23-E24,1) -> 8724.1
A25: 21 | B25: 46171 | D25: =+ROUND(G24*0.01,1) -> 87.2 | E25: =ROUNDUP($C$4/48,1) -> 311.6 | F25: =+ROUND(D25+E25,1) -> 398.8 | G25: =+ROUND(G24-E25,1) -> 8412.5
A26: 22 | B26: 46202 | D26: =+ROUND(G25*0.01,1) -> 84.1 | E26: =ROUNDUP($C$4/48,1) -> 311.6 | F26: =+ROUND(D26+E26,1) -> 395.7 | G26: =+ROUND(G25-E26,1) -> 8100.9
A27: 23 | B27: 46232 | D27: =+ROUND(G26*0.01,1) -> 81 | E27: =ROUNDUP($C$4/48,1) -> 311.6 | F27: =+ROUND(D27+E27,1) -> 392.6 | G27: =+ROUND(G26-E27,1) -> 7789.3
A28: 24 | B28: 46263 | D28: =+ROUND(G27*0.01,1) -> 77.9 | E28: =ROUNDUP($C$4/48,1) -> 311.6 | F28: =+ROUND(D28+E28,1) -> 389.5 | G28: =+ROUND(G27-E28,1) -> 7477.7
A29: 25 | B29: 46294 | D29: =+ROUND(G28*0.01,1) -> 74.8 | E29: =ROUNDUP($C$4/48,1) -> 311.6 | F29: =+ROUND(D29+E29,1) -> 386.4 | G29: =+ROUND(G28-E29,1) -> 7166.1
A30: 26 | B30: 46324 | D30: =+ROUND(G29*0.01,1) -> 71.7 | E30: =ROUNDUP($C$4/48,1) -> 311.6 | F30: =+ROUND(D30+E30,1) -> 383.3 | G30: =+ROUND(G29-E30,1) -> 6854.5
A31: 27 | B31: 46355 | D31: =+ROUND(G30*0.01,1) -> 68.5 | E31: =ROUNDUP($C$4/48,1) -> 311.6 | F31: =+ROUND(D31+E31,1) -> 380.1 | G31: =+ROUND(G30-E31,1) -> 6542.9
... A52: 48 | B52: 46994 | D52: =+ROUND(G51*0.01,1) -> 3.1 | E52: =ROUNDUP($C$4/48,1) -> 311.6 | F52: =+ROUND(D52+E52,1) -> 314.7 | G52: =+ROUND(G51-E52,1) -> -0.7
A53: TOTAL | D53: =+SUM(D5:D52) -> 3664 | E53: =+SUM(E5:E52) -> 14956.8 | F53: =+SUM(F5:F52) -> 18620.8
A55: SOCIO: HUGO DELESMIRO MONTOYA MACHUCA
A56: OCTUBRE 2025 - PRÉSTAMO
A57: PLAZO | B57: FECHA | C57: PRÉSTAMO S/. | D57: INTERES | E57: ABONO DE CAPITAL | F57: CUOTA | G57: SALDO
A58: 0 | B58: 46020 | C58: =J60 -> 22233.2 | D58: 0.01 | G58: =C58 -> 22233.2 | I58: SALDO | J58: =J19 -> 9970.5
A59: 1 | B59: 46051 | D59: =+ROUND(G58*0.01,1) -> 222.3 | E59: =ROUND($C$58/60,1) -> 370.6 | F59: =+ROUND(D59+E59,1) -> 592.9 | G59: =+ROUND(G58-E59,1) -> 21862.6 | I59: PRESTAMO | J59: 12262.7
A60: 2 | B60: 46081 | D60: =+ROUND(G59*0.01,1) -> 218.6 | E60: =ROUND($C$58/60,1) -> 370.6 | F60: =+ROUND(D60+E60,1) -> 589.2 | G60: =+ROUND(G59-E60,1) -> 21492 | I60: TOTAL | J60: =J59+J58 -> 22233.2
A61: 3 | B61: 46110 | D61: =+ROUND(G60*0.01,1) -> 214.9 | E61: =ROUND($C$58/60,1) -> 370.6 | F61: =+ROUND(D61+E61,1) -> 585.5 | G61: =+ROUND(G60-E61,1) -> 21121.4
A62: 4 | B62: 46141 | D62: =+ROUND(G61*0.01,1) -> 211.2 | E62: =ROUND($C$58/60,1) -> 370.6 | F62: =+ROUND(D62+E62,1) -> 581.8 | G62: =+ROUND(G61-E62,1) -> 20750.8
A63: 5 | B63: 46171 | D63: =+ROUND(G62*0.01,1) -> 207.5 | E63: =ROUND($C$58/60,1) -> 370.6 | F63: =+ROUND(D63+E63,1) -> 578.1 | G63: =+ROUND(G62-E63,1) -> 20380.2
A64: 6 | B64: 46202 | D64: =+ROUND(G63*0.01,1) -> 203.8 | E64: =ROUND($C$58/60,1) -> 370.6 | F64: =+ROUND(D64+E64,1) -> 574.4 | G64: =+ROUND(G63-E64,1) -> 20009.6
A65: 7 | B65: 46232 | D65: =+ROUND(G64*0.01,1) -> 200.1 | E65: =ROUND($C$58/60,1) -> 370.6 | F65: =+ROUND(D65+E65,1) -> 570.7 | G65: =+ROUND(G64-E65,1) -> 19639
A66: 8 | B66: 46263 | D66: =+ROUND(G65*0.01,1) -> 196.4 | E66: =ROUND($C$58/60,1) -> 370.6 | F66: =+ROUND(D66+E66,1) -> 567 | G66: =+ROUND(G65-E66,1) -> 19268.4
A67: 9 | B67: 46294 | D67: =+ROUND(G66*0.01,1) -> 192.7 | E67: =ROUND($C$58/60,1) -> 370.6 | F67: =+ROUND(D67+E67,1) -> 563.3 | G67: =+ROUND(G66-E67,1) -> 18897.8
A68: 10 | B68: 46324 | D68: =+ROUND(G67*0.01,1) -> 189 | E68: =ROUND($C$58/60,1) -> 370.6 | F68: =+ROUND(D68+E68,1) -> 559.6 | G68: =+ROUND(G67-E68,1) -> 18527.2
A69: 11 | B69: 46355 | D69: =+ROUND(G68*0.01,1) -> 185.3 | E69: =ROUND($C$58/60,1) -> 370.6 | F69: =+ROUND(D69+E69,1) -> 555.9 | G69: =+ROUND(G68-E69,1) -> 18156.6
A70: 12 | B70: 46385 | D70: =+ROUND(G69*0.01,1) -> 181.6 | E70: =ROUND($C$58/60,1) -> 370.6 | F70: =+ROUND(D70+E70,1) -> 552.2 | G70: =+ROUND(G69-E70,1) -> 17786
A71: 13 | B71: 46416 | D71: =+ROUND(G70*0.01,1) -> 177.9 | E71: =ROUND($C$58/60,1) -> 370.6 | F71: =+ROUND(D71+E71,1) -> 548.5 | G71: =+ROUND(G70-E71,1) -> 17415.4
A72: 14 | B72: 46446 | D72: =+ROUND(G71*0.01,1) -> 174.2 | E72: =ROUND($C$58/60,1) -> 370.6 | F72: =+ROUND(D72+E72,1) -> 544.8 | G72: =+ROUND(G71-E72,1) -> 17044.8
... A117: 59 | B117: 47816 | D117: =+ROUND(G116*0.01,1) -> 7.4 | E117: =ROUND($C$58/60,1) -> 370.6 | F117: =+ROUND(D117+E117,1) -> 378 | G117: =+ROUND(G116-E117,1) -> 367.8
A118: 60 | B118: 47846 | D118: =+ROUND(G117*0.01,1) -> 3.7 | E118: =ROUND($C$58/60,1)-2.8 -> 367.8 | F118: =+ROUND(D118+E118,1) -> 371.5 | G118: =+ROUND(G117-E118,1) -> 0
A119: TOTAL | D119: =+SUM(D59:D118) -> 6780.3 | E119: =+SUM(E59:E118) -> 22233.2 | F119: =+SUM(F59:F118) -> 29013.5

Sheet 25
A1: SOCIA: HILDA PEREYRA RODRIGUEZ
A2: JUNIO 2025 - PRÉSTAMO
A3: PLAZO | B3: FECHA | C3: PRÉSTAMO S/. | D3: INTERES | E3: ABONO DE CAPITAL | F3: CUOTA | G3: SALDO
A4: 0 | B4: 45837 | C4: =+J7 -> 23029.1 | D4: 0.01 | G4: =+C4 -> 23029.1
A5: 1 | B5: 45867 | D5: =+ROUND(G4*0.01,1) -> 230.3 | E5: =ROUNDUP($C$4/84,1) -> 274.2 | F5: =+ROUND(D5+E5,1) -> 504.5 | G5: =+ROUND(G4-E5,1) -> 22754.9 | I5: SALDO | J5: 10029.1
A6: 2 | B6: 45898 | D6: =+ROUND(G5*0.01,1) -> 227.5 | E6: =ROUNDUP($C$4/84,1) -> 274.2 | F6: =+ROUND(D6+E6,1) -> 501.7 | G6: =+ROUND(G5-E6,1) -> 22480.7 | I6: PRESTAMO | J6: 13000
A7: 3 | B7: 45929 | D7: =+ROUND(G6*0.01,1) -> 224.8 | E7: =ROUNDUP($C$4/84,1) -> 274.2 | F7: =+ROUND(D7+E7,1) -> 499 | G7: =+ROUND(G6-E7,1) -> 22206.5 | I7: TOTAL | J7: =+SUM(J5:J6) -> 23029.1
A8: 4 | B8: 45959 | D8: =+ROUND(G7*0.01,1) -> 222.1 | E8: =ROUNDUP($C$4/84,1) -> 274.2 | F8: =+ROUND(D8+E8,1) -> 496.3 | G8: =+ROUND(G7-E8,1) -> 21932.3
A9: 5 | B9: 45990 | D9: =+ROUND(G8*0.01,1) -> 219.3 | E9: =ROUNDUP($C$4/84,1) -> 274.2 | F9: =+ROUND(D9+E9,1) -> 493.5 | G9: =+ROUND(G8-E9,1) -> 21658.1
A10: 6 | B10: 46020 | D10: =+ROUND(G9*0.01,1) -> 216.6 | E10: =ROUNDUP($C$4/84,1) -> 274.2 | F10: =+ROUND(D10+E10,1) -> 490.8 | G10: =+ROUND(G9-E10,1) -> 21383.9
A11: 7 | B11: 46051 | D11: =+ROUND(G10*0.01,1) -> 213.8 | E11: =ROUNDUP($C$4/84,1) -> 274.2 | F11: =+ROUND(D11+E11,1) -> 488 | G11: =+ROUND(G10-E11,1) -> 21109.7
A12: 8 | B12: 46081 | D12: =+ROUND(G11*0.01,1) -> 211.1 | E12: =ROUNDUP($C$4/84,1) -> 274.2 | F12: =+ROUND(D12+E12,1) -> 485.3 | G12: =+ROUND(G11-E12,1) -> 20835.5
A13: 9 | B13: 46110 | D13: =+ROUND(G12*0.01,1) -> 208.4 | E13: =ROUNDUP($C$4/84,1) -> 274.2 | F13: =+ROUND(D13+E13,1) -> 482.6 | G13: =+ROUND(G12-E13,1) -> 20561.3
A14: 10 | B14: 46141 | D14: =+ROUND(G13*0.01,1) -> 205.6 | E14: =ROUNDUP($C$4/84,1) -> 274.2 | F14: =+ROUND(D14+E14,1) -> 479.8 | G14: =+ROUND(G13-E14,1) -> 20287.1
A15: 11 | B15: 46171 | D15: =+ROUND(G14*0.01,1) -> 202.9 | E15: =ROUNDUP($C$4/84,1) -> 274.2 | F15: =+ROUND(D15+E15,1) -> 477.1 | G15: =+ROUND(G14-E15,1) -> 20012.9
A16: 12 | B16: 46202 | D16: =+ROUND(G15*0.01,1) -> 200.1 | E16: =ROUNDUP($C$4/84,1) -> 274.2 | F16: =+ROUND(D16+E16,1) -> 474.3 | G16: =+ROUND(G15-E16,1) -> 19738.7
A17: 13 | B17: 46232 | D17: =+ROUND(G16*0.01,1) -> 197.4 | E17: =ROUNDUP($C$4/84,1) -> 274.2 | F17: =+ROUND(D17+E17,1) -> 471.6 | G17: =+ROUND(G16-E17,1) -> 19464.5
A18: 14 | B18: 46263 | D18: =+ROUND(G17*0.01,1) -> 194.6 | E18: =ROUNDUP($C$4/84,1) -> 274.2 | F18: =+ROUND(D18+E18,1) -> 468.8 | G18: =+ROUND(G17-E18,1) -> 19190.3
A19: 15 | B19: 46294 | D19: =+ROUND(G18*0.01,1) -> 191.9 | E19: =ROUNDUP($C$4/84,1) -> 274.2 | F19: =+ROUND(D19+E19,1) -> 466.1 | G19: =+ROUND(G18-E19,1) -> 18916.1
... A87: 83 | B87: 48363 | D87: =+ROUND(G86*0.01,1) -> 5.4 | E87: =ROUNDUP($C$4/84,1) -> 274.2 | F87: =+ROUND(D87+E87,1) -> 279.6 | G87: =+ROUND(G86-E87,1) -> 270.5
A88: 84 | B88: 48394 | D88: =+ROUND(G87*0.01,1) -> 2.7 | E88: =ROUNDUP($C$4/84,1)-3.7 -> 270.5 | F88: =+ROUND(D88+E88,1) -> 273.2 | G88: =+ROUND(G87-E88,1) -> 0
A89: TOTAL | D89: =+SUM(D5:D88) -> 9785.8 | E89: =+SUM(E5:E88) -> 23029.1 | F89: =+SUM(F5:F88) -> 32814.9

Sheet 26
A1: SOCIO: RONCAL ALBARRAN, Alejandro
A2: MARZO 2024 - PRÉSTAMO
A3: PLAZO | B3: FECHA | C3: PRÉSTAMO S/. | D3: INTERES | E3: ABONO DE CAPITAL | F3: CUOTA | G3: SALDO
A4: 0 | B4: 45380 | C4: =+J7 -> 34156.9 | D4: 0.01 | G4: =+C4 -> 34156.9
A5: 1 | B5: 45411 | D5: =+ROUND(G4*0.01,1) -> 341.6 | E5: =ROUNDUP($C$4/48,1) -> 711.7 | F5: =+ROUND(D5+E5,1) -> 1053.3 | G5: =+ROUND(G4-E5,1) -> 33445.2 | I5: SALDO | J5: 24156.9
A6: 2 | B6: 45441 | D6: =+ROUND(G5*0.01,1) -> 334.5 | E6: =ROUNDDOWN($C$4/48,1) -> 711.6 | F6: =+ROUND(D6+E6,1) -> 1046.1 | G6: =+ROUND(G5-E6,1) -> 32733.6 | I6: PRÉSTAMO | J6: 10000
A7: 3 | B7: 45472 | D7: =+ROUND(G6*0.01,1) -> 327.3 | E7: =ROUNDDOWN($C$4/48,1) -> 711.6 | F7: =+ROUND(D7+E7,1) -> 1038.9 | G7: =+ROUND(G6-E7,1) -> 32022 | I7: TOTAL | J7: =+SUM(J5:J6) -> 34156.9
A8: 4 | B8: 45502 | D8: =+ROUND(G7*0.01,1) -> 320.2 | E8: =ROUNDDOWN($C$4/48,1) -> 711.6 | F8: =+ROUND(D8+E8,1) -> 1031.8 | G8: =+ROUND(G7-E8,1) -> 31310.4
A9: 5 | B9: 45533 | D9: =+ROUND(G8*0.01,1) -> 313.1 | E9: =ROUNDDOWN($C$4/48,1) -> 711.6 | F9: =+ROUND(D9+E9,1) -> 1024.7 | G9: =+ROUND(G8-E9,1) -> 30598.8
A10: 6 | B10: 45564 | D10: =+ROUND(G9*0.01,1) -> 306 | E10: =ROUNDDOWN($C$4/48,1) -> 711.6 | F10: =+ROUND(D10+E10,1) -> 1017.6 | G10: =+ROUND(G9-E10,1) -> 29887.2
A11: 7 | B11: 45594 | D11: =+ROUND(G10*0.01,1) -> 298.9 | E11: =ROUNDDOWN($C$4/48,1) -> 711.6 | F11: =+ROUND(D11+E11,1) -> 1010.5 | G11: =+ROUND(G10-E11,1) -> 29175.6
A12: 8 | B12: 45625 | D12: =+ROUND(G11*0.01,1) -> 291.8 | E12: =ROUNDDOWN($C$4/48,1) -> 711.6 | F12: =+ROUND(D12+E12,1) -> 1003.4 | G12: =+ROUND(G11-E12,1) -> 28464
A13: 9 | B13: 45655 | D13: =+ROUND(G12*0.01,1) -> 284.6 | E13: =ROUNDDOWN($C$4/48,1) -> 711.6 | F13: =+ROUND(D13+E13,1) -> 996.2 | G13: =+ROUND(G12-E13,1) -> 27752.4
A14: 10 | B14: 45686 | D14: =+ROUND(G13*0.01,1) -> 277.5 | E14: =ROUNDDOWN($C$4/48,1) -> 711.6 | F14: =+ROUND(D14+E14,1) -> 989.1 | G14: =+ROUND(G13-E14,1) -> 27040.8
A15: 11 | B15: 45716 | D15: =+ROUND(G14*0.01,1) -> 270.4 | E15: =ROUNDDOWN($C$4/48,1) -> 711.6 | F15: =+ROUND(D15+E15,1) -> 982 | G15: =+ROUND(G14-E15,1) -> 26329.2
A16: 12 | B16: 45745 | D16: =+ROUND(G15*0.01,1) -> 263.3 | E16: =ROUNDDOWN($C$4/48,1) -> 711.6 | F16: =+ROUND(D16+E16,1) -> 974.9 | G16: =+ROUND(G15-E16,1) -> 25617.6
A17: 13 | B17: 45776 | D17: =+ROUND(G16*0.01,1) -> 256.2 | E17: =ROUNDDOWN($C$4/48,1) -> 711.6 | F17: =+ROUND(D17+E17,1) -> 967.8 | G17: =+ROUND(G16-E17,1) -> 24906
A18: 14 | B18: 45806 | D18: =+ROUND(G17*0.01,1) -> 249.1 | E18: =ROUNDDOWN($C$4/48,1) -> 711.6 | F18: =+ROUND(D18+E18,1) -> 960.7 | G18: =+ROUND(G17-E18,1) -> 24194.4
A19: 15 | B19: 45837 | D19: =+ROUND(G18*0.01,1) -> 241.9 | E19: =ROUNDDOWN($C$4/48,1) -> 711.6 | F19: =+ROUND(D19+E19,1) -> 953.5 | G19: =+ROUND(G18-E19,1) -> 23482.8
... A21: 17 | B21: 45898 | D21: =+ROUND(G20*0.01,1) -> 227.7 | E21: =ROUNDDOWN($C$4/48,1) -> 711.6 | F21: =+ROUND(D21+E21,1) -> 939.3 | G21: =+ROUND(G20-E21,1) -> 22059.6
A22: 18 | B22: 45929 | D22: =+ROUND(G21*0.01,1) -> 220.6 | E22: =ROUNDDOWN($C$4/48,1) -> 711.6 | F22: =+ROUND(D22+E22,1) -> 932.2 | G22: =+ROUND(G21-E22,1) -> 21348 | I22: INTERES | J22: =SUM(D5:D24) -> 5479.4
A23: 19 | B23: 45959 | D23: =+ROUND(G22*0.01,1) -> 213.5 | E23: =ROUNDDOWN($C$4/48,1) -> 711.6 | F23: =+ROUND(D23+E23,1) -> 925.1 | G23: =+ROUND(G22-E23,1) -> 20636.4 | I23: SALDO | J23: =G24 -> 19924.8
A24: 20 | B24: 45990 | D24: =+ROUND(G23*0.01,1) -> 206.4 | E24: =ROUNDDOWN($C$4/48,1) -> 711.6 | F24: =+ROUND(D24+E24,1) -> 918 | G24: =+ROUND(G23-E24,1) -> 19924.8
A25: 21 | B25: 46020 | D25: =+ROUND(G24*0.01,1) -> 199.2 | E25: =ROUNDDOWN($C$4/48,1) -> 711.6 | F25: =+ROUND(D25+E25,1) -> 910.8 | G25: =+ROUND(G24-E25,1) -> 19213.2
A26: 22 | B26: 46051 | D26: =+ROUND(G25*0.01,1) -> 192.1 | E26: =ROUNDDOWN($C$4/48,1) -> 711.6 | F26: =+ROUND(D26+E26,1) -> 903.7 | G26: =+ROUND(G25-E26,1) -> 18501.6
A27: 23 | B27: 46081 | D27: =+ROUND(G26*0.01,1) -> 185 | E27: =ROUNDDOWN($C$4/48,1) -> 711.6 | F27: =+ROUND(D27+E27,1) -> 896.6 | G27: =+ROUND(G26-E27,1) -> 17790
A28: 24 | B28: 46110 | D28: =+ROUND(G27*0.01,1) -> 177.9 | E28: =ROUNDDOWN($C$4/48,1) -> 711.6 | F28: =+ROUND(D28+E28,1) -> 889.5 | G28: =+ROUND(G27-E28,1) -> 17078.4
A29: 25 | B29: 46141 | D29: =+ROUND(G28*0.01,1) -> 170.8 | E29: =ROUNDDOWN($C$4/48,1) -> 711.6 | F29: =+ROUND(D29+E29,1) -> 882.4 | G29: =+ROUND(G28-E29,1) -> 16366.8
A30: 26 | B30: 46171 | D30: =+ROUND(G29*0.01,1) -> 163.7 | E30: =ROUNDDOWN($C$4/48,1) -> 711.6 | F30: =+ROUND(D30+E30,1) -> 875.3 | G30: =+ROUND(G29-E30,1) -> 15655.2
A31: 27 | B31: 46202 | D31: =+ROUND(G30*0.01,1) -> 156.6 | E31: =ROUNDDOWN($C$4/48,1) -> 711.6 | F31: =+ROUND(D31+E31,1) -> 868.2 | G31: =+ROUND(G30-E31,1) -> 14943.6
A32: 28 | B32: 46232 | D32: =+ROUND(G31*0.01,1) -> 149.4 | E32: =ROUNDDOWN($C$4/48,1) -> 711.6 | F32: =+ROUND(D32+E32,1) -> 861 | G32: =+ROUND(G31-E32,1) -> 14232
A33: 29 | B33: 46263 | D33: =+ROUND(G32*0.01,1) -> 142.3 | E33: =ROUNDDOWN($C$4/48,1) -> 711.6 | F33: =+ROUND(D33+E33,1) -> 853.9 | G33: =+ROUND(G32-E33,1) -> 13520.4
A34: 30 | B34: 46294 | D34: =+ROUND(G33*0.01,1) -> 135.2 | E34: =ROUNDDOWN($C$4/48,1) -> 711.6 | F34: =+ROUND(D34+E34,1) -> 846.8 | G34: =+ROUND(G33-E34,1) -> 12808.8
A35: 31 | B35: 46324 | D35: =+ROUND(G34*0.01,1) -> 128.1 | E35: =ROUNDDOWN($C$4/48,1) -> 711.6 | F35: =+ROUND(D35+E35,1) -> 839.7 | G35: =+ROUND(G34-E35,1) -> 12097.2
... A52: 48 | B52: 46841 | D52: =+ROUND(G51*0.01,1) -> 7.1 | E52: =ROUNDDOWN($C$4/48,1) -> 711.6 | F52: =+ROUND(D52+E52,1) -> 718.7 | G52: =+ROUND(G51-E52,1) -> 0
A53: TOTAL | D53: =+SUM(D5:D52) -> 8368.4 | E53: =+SUM(E5:E52) -> 34156.9 | F53: =+SUM(F5:F52) -> 42525.3
A55: SOCIO: ALEJANDRO RONCAL ALBARRAN
A56: NOVIEMBRE 2025 - PRÉSTAMO
A57: PLAZO | B57: FECHA | C57: PRÉSTAMO S/. | D57: INTERES | E57: ABONO DE CAPITAL | F57: CUOTA | G57: SALDO
A58: 0 | B58: 45990 | C58: =+J61 -> 46479.2 | D58: 0.01 | G58: =+C58 -> 46479.2
A59: 1 | B59: 46020 | D59: =+ROUND(G58*0.01,1) -> 464.8 | E59: =ROUNDUP($C$58/36,1) -> 1291.1 | F59: =+ROUND(D59+E59,1) -> 1755.9 | G59: =+ROUND(G58-E59,1) -> 45188.1 | I59: SALDO | J59: =J23 -> 19924.8
A60: 2 | B60: 46051 | D60: =+ROUND(G59*0.01,1) -> 451.9 | E60: =ROUNDUP($C$58/36,1) -> 1291.1 | F60: =+ROUND(D60+E60,1) -> 1743 | G60: =+ROUND(G59-E60,1) -> 43897 | I60: PRESTAMO | J60: 26554.4
A61: 3 | B61: 46081 | D61: =+ROUND(G60*0.01,1) -> 439 | E61: =ROUNDUP($C$58/36,1) -> 1291.1 | F61: =+ROUND(D61+E61,1) -> 1730.1 | G61: =+ROUND(G60-E61,1) -> 42605.9 | I61: TOTAL | J61: =J60+J59 -> 46479.2
A62: 4 | B62: 46110 | D62: =+ROUND(G61*0.01,1) -> 426.1 | E62: =ROUNDUP($C$58/36,1) -> 1291.1 | F62: =+ROUND(D62+E62,1) -> 1717.2 | G62: =+ROUND(G61-E62,1) -> 41314.8
A63: 5 | B63: 46141 | D63: =+ROUND(G62*0.01,1) -> 413.1 | E63: =ROUNDUP($C$58/36,1) -> 1291.1 | F63: =+ROUND(D63+E63,1) -> 1704.2 | G63: =+ROUND(G62-E63,1) -> 40023.7
A64: 6 | B64: 46171 | D64: =+ROUND(G63*0.01,1) -> 400.2 | E64: =ROUNDUP($C$58/36,1) -> 1291.1 | F64: =+ROUND(D64+E64,1) -> 1691.3 | G64: =+ROUND(G63-E64,1) -> 38732.6
A65: 7 | B65: 46202 | D65: =+ROUND(G64*0.01,1) -> 387.3 | E65: =ROUNDUP($C$58/36,1) -> 1291.1 | F65: =+ROUND(D65+E65,1) -> 1678.4 | G65: =+ROUND(G64-E65,1) -> 37441.5
A66: 8 | B66: 46232 | D66: =+ROUND(G65*0.01,1) -> 374.4 | E66: =ROUNDUP($C$58/36,1) -> 1291.1 | F66: =+ROUND(D66+E66,1) -> 1665.5 | G66: =+ROUND(G65-E66,1) -> 36150.4
A67: 9 | B67: 46263 | D67: =+ROUND(G66*0.01,1) -> 361.5 | E67: =ROUNDUP($C$58/36,1) -> 1291.1 | F67: =+ROUND(D67+E67,1) -> 1652.6 | G67: =+ROUND(G66-E67,1) -> 34859.3
A68: 10 | B68: 46294 | D68: =+ROUND(G67*0.01,1) -> 348.6 | E68: =ROUNDUP($C$58/36,1) -> 1291.1 | F68: =+ROUND(D68+E68,1) -> 1639.7 | G68: =+ROUND(G67-E68,1) -> 33568.2
A69: 11 | B69: 46324 | D69: =+ROUND(G68*0.01,1) -> 335.7 | E69: =ROUNDUP($C$58/36,1) -> 1291.1 | F69: =+ROUND(D69+E69,1) -> 1626.8 | G69: =+ROUND(G68-E69,1) -> 32277.1
A70: 12 | B70: 46355 | D70: =+ROUND(G69*0.01,1) -> 322.8 | E70: =ROUNDUP($C$58/36,1) -> 1291.1 | F70: =+ROUND(D70+E70,1) -> 1613.9 | G70: =+ROUND(G69-E70,1) -> 30986
A71: 13 | B71: 46385 | D71: =+ROUND(G70*0.01,1) -> 309.9 | E71: =ROUNDUP($C$58/36,1) -> 1291.1 | F71: =+ROUND(D71+E71,1) -> 1601 | G71: =+ROUND(G70-E71,1) -> 29694.9
A72: 14 | B72: 46416 | D72: =+ROUND(G71*0.01,1) -> 296.9 | E72: =ROUNDUP($C$58/36,1) -> 1291.1 | F72: =+ROUND(D72+E72,1) -> 1588 | G72: =+ROUND(G71-E72,1) -> 28403.8
A73: 15 | B73: 46446 | D73: =+ROUND(G72*0.01,1) -> 284 | E73: =ROUNDUP($C$58/36,1) -> 1291.1 | F73: =+ROUND(D73+E73,1) -> 1575.1 | G73: =+ROUND(G72-E73,1) -> 27112.7
... A93: 35 | B93: 47055 | D93: =+ROUND(G92*0.01,1) -> 25.8 | E93: =ROUNDUP($C$58/36,1) -> 1291.1 | F93: =+ROUND(D93+E93,1) -> 1316.9 | G93: =+ROUND(G92-E93,1) -> 1290.7
A94: 36 | B94: 47086 | D94: =+ROUND(G93*0.01,1) -> 12.9 | E94: =ROUNDUP($C$58/36,1)-0.4 -> 1290.7 | F94: =+ROUND(D94+E94,1) -> 1303.6 | G94: =+ROUND(G93-E94,1) -> 0
A95: TOTAL | D95: =+SUM(D59:D94) -> 8598.6 | E95: =+SUM(E59:E94) -> 46479.2 | F95: =+SUM(F59:F94) -> 55077.8

Sheet 27
A1: SOCIO: LUIS ALBERTO SANCHEZ ZAVALETA
A2: SETIEMBRE 2025 - PRÉSTAMO
A3: PLAZO | B3: FECHA | C3: PRÉSTAMO S/. | D3: INTERES | E3: ABONO DE CAPITAL | F3: CUOTA | G3: SALDO
A4: 0 | B4: 45929 | C4: =+J7 -> 42623.9 | D4: 0.01 | G4: =+C4 -> 42623.9
A5: 1 | B5: 45959 | D5: =+ROUND(G4*0.01,1) -> 426.2 | E5: =ROUNDDOWN($C$4/84,1) -> 507.4 | F5: =+ROUND(D5+E5,1) -> 933.6 | G5: =+ROUND(G4-E5,1) -> 42116.5 | I5: SALDO | J5: 34623.9
A6: 2 | B6: 45990 | D6: =+ROUND(G5*0.01,1) -> 421.2 | E6: =ROUNDDOWN($C$4/84,1) -> 507.4 | F6: =+ROUND(D6+E6,1) -> 928.6 | G6: =+ROUND(G5-E6,1) -> 41609.1 | I6: PRESTAMO | J6: 8000
A7: 3 | B7: 46020 | D7: =+ROUND(G6*0.01,1) -> 416.1 | E7: =ROUNDDOWN($C$4/84,1) -> 507.4 | F7: =+ROUND(D7+E7,1) -> 923.5 | G7: =+ROUND(G6-E7,1) -> 41101.7 | I7: TOTAL | J7: =+SUM(J5:J6) -> 42623.9
A8: 4 | B8: 46051 | D8: =+ROUND(G7*0.01,1) -> 411 | E8: =ROUNDDOWN($C$4/84,1) -> 507.4 | F8: =+ROUND(D8+E8,1) -> 918.4 | G8: =+ROUND(G7-E8,1) -> 40594.3
A9: 5 | B9: 46081 | D9: =+ROUND(G8*0.01,1) -> 405.9 | E9: =ROUNDDOWN($C$4/84,1) -> 507.4 | F9: =+ROUND(D9+E9,1) -> 913.3 | G9: =+ROUND(G8-E9,1) -> 40086.9
A10: 6 | B10: 46110 | D10: =+ROUND(G9*0.01,1) -> 400.9 | E10: =ROUNDDOWN($C$4/84,1) -> 507.4 | F10: =+ROUND(D10+E10,1) -> 908.3 | G10: =+ROUND(G9-E10,1) -> 39579.5
A11: 7 | B11: 46141 | D11: =+ROUND(G10*0.01,1) -> 395.8 | E11: =ROUNDDOWN($C$4/84,1) -> 507.4 | F11: =+ROUND(D11+E11,1) -> 903.2 | G11: =+ROUND(G10-E11,1) -> 39072.1
A12: 8 | B12: 46171 | D12: =+ROUND(G11*0.01,1) -> 390.7 | E12: =ROUNDDOWN($C$4/84,1) -> 507.4 | F12: =+ROUND(D12+E12,1) -> 898.1 | G12: =+ROUND(G11-E12,1) -> 38564.7
A13: 9 | B13: 46202 | D13: =+ROUND(G12*0.01,1) -> 385.6 | E13: =ROUNDDOWN($C$4/84,1) -> 507.4 | F13: =+ROUND(D13+E13,1) -> 893 | G13: =+ROUND(G12-E13,1) -> 38057.3
A14: 10 | B14: 46232 | D14: =+ROUND(G13*0.01,1) -> 380.6 | E14: =ROUNDDOWN($C$4/84,1) -> 507.4 | F14: =+ROUND(D14+E14,1) -> 888 | G14: =+ROUND(G13-E14,1) -> 37549.9
A15: 11 | B15: 46263 | D15: =+ROUND(G14*0.01,1) -> 375.5 | E15: =ROUNDDOWN($C$4/84,1) -> 507.4 | F15: =+ROUND(D15+E15,1) -> 882.9 | G15: =+ROUND(G14-E15,1) -> 37042.5
A16: 12 | B16: 46294 | D16: =+ROUND(G15*0.01,1) -> 370.4 | E16: =ROUNDDOWN($C$4/84,1) -> 507.4 | F16: =+ROUND(D16+E16,1) -> 877.8 | G16: =+ROUND(G15-E16,1) -> 36535.1
A17: 13 | B17: 46324 | D17: =+ROUND(G16*0.01,1) -> 365.4 | E17: =ROUNDDOWN($C$4/84,1) -> 507.4 | F17: =+ROUND(D17+E17,1) -> 872.8 | G17: =+ROUND(G16-E17,1) -> 36027.7
A18: 14 | B18: 46355 | D18: =+ROUND(G17*0.01,1) -> 360.3 | E18: =ROUNDDOWN($C$4/84,1) -> 507.4 | F18: =+ROUND(D18+E18,1) -> 867.7 | G18: =+ROUND(G17-E18,1) -> 35520.3
A19: 15 | B19: 46385 | D19: =+ROUND(G18*0.01,1) -> 355.2 | E19: =ROUNDDOWN($C$4/84,1) -> 507.4 | F19: =+ROUND(D19+E19,1) -> 862.6 | G19: =+ROUND(G18-E19,1) -> 35012.9
... A87: 83 | B87: 48455 | D87: =+ROUND(G86*0.01,1) -> 10.2 | E87: =ROUNDDOWN($C$4/84,1) -> 507.4 | F87: =+ROUND(D87+E87,1) -> 517.6 | G87: =+ROUND(G86-E87,1) -> 509.7
A88: 84 | B88: 48486 | D88: =+ROUND(G87*0.01,1) -> 5.1 | E88: =ROUNDDOWN($C$4/84,1)+2.3 -> 509.7 | F88: =+ROUND(D88+E88,1) -> 514.8 | G88: =+ROUND(G87-E88,1) -> 0
A89: TOTAL | D89: =+SUM(D5:D88) -> 18116.1 | E89: =+SUM(E5:E88) -> 42623.9 | F89: =+SUM(F5:F88) -> 60740

Sheet 28
A1: SOCIA: ESPERANZA TAMBO RABANAL
A2: MAYO 2025 - PRÉSTAMO
A3: PLAZO | B3: FECHA | C3: PRÉSTAMO S/. | D3: INTERES | E3: ABONO DE CAPITAL | F3: CUOTA | G3: SALDO
A4: 0 | B4: 45806 | C4: =+J7 -> 34227.1 | D4: 0.01 | G4: =+C4 -> 34227.1
A5: 1 | B5: 45837 | D5: =+ROUND(G4*0.01,1) -> 342.3 | E5: =ROUNDUP($C$4/84,1) -> 407.5 | F5: =+ROUND(D5+E5,1) -> 749.8 | G5: =+ROUND(G4-E5,1) -> 33819.6 | I5: SALDO | J5: 11556
A6: 2 | B6: 45867 | D6: =+ROUND(G5*0.01,1) -> 338.2 | E6: =ROUNDUP($C$4/84,1) -> 407.5 | F6: =+ROUND(D6+E6,1) -> 745.7 | G6: =+ROUND(G5-E6,1) -> 33412.1 | I6: PRESTAMO | J6: 22671.1
A7: 3 | B7: 45898 | D7: =+ROUND(G6*0.01,1) -> 334.1 | E7: =ROUNDUP($C$4/84,1) -> 407.5 | F7: =+ROUND(D7+E7,1) -> 741.6 | G7: =+ROUND(G6-E7,1) -> 33004.6 | I7: TOTAL | J7: =+SUM(J5:J6) -> 34227.1
A8: 4 | B8: 45929 | D8: =+ROUND(G7*0.01,1) -> 330 | E8: =ROUNDUP($C$4/84,1) -> 407.5 | F8: =+ROUND(D8+E8,1) -> 737.5 | G8: =+ROUND(G7-E8,1) -> 32597.1
A9: 5 | B9: 45959 | D9: =+ROUND(G8*0.01,1) -> 326 | E9: =ROUNDUP($C$4/84,1) -> 407.5 | F9: =+ROUND(D9+E9,1) -> 733.5 | G9: =+ROUND(G8-E9,1) -> 32189.6
A10: 6 | B10: 45990 | D10: =+ROUND(G9*0.01,1) -> 321.9 | E10: =ROUNDUP($C$4/84,1) -> 407.5 | F10: =+ROUND(D10+E10,1) -> 729.4 | G10: =+ROUND(G9-E10,1) -> 31782.1
A11: 7 | B11: 46020 | D11: =+ROUND(G10*0.01,1) -> 317.8 | E11: =ROUNDUP($C$4/84,1) -> 407.5 | F11: =+ROUND(D11+E11,1) -> 725.3 | G11: =+ROUND(G10-E11,1) -> 31374.6
A12: 8 | B12: 46051 | D12: =+ROUND(G11*0.01,1) -> 313.7 | E12: =ROUNDUP($C$4/84,1) -> 407.5 | F12: =+ROUND(D12+E12,1) -> 721.2 | G12: =+ROUND(G11-E12,1) -> 30967.1
A13: 9 | B13: 46081 | D13: =+ROUND(G12*0.01,1) -> 309.7 | E13: =ROUNDUP($C$4/84,1) -> 407.5 | F13: =+ROUND(D13+E13,1) -> 717.2 | G13: =+ROUND(G12-E13,1) -> 30559.6
A14: 10 | B14: 46110 | D14: =+ROUND(G13*0.01,1) -> 305.6 | E14: =ROUNDUP($C$4/84,1) -> 407.5 | F14: =+ROUND(D14+E14,1) -> 713.1 | G14: =+ROUND(G13-E14,1) -> 30152.1
A15: 11 | B15: 46141 | D15: =+ROUND(G14*0.01,1) -> 301.5 | E15: =ROUNDUP($C$4/84,1) -> 407.5 | F15: =+ROUND(D15+E15,1) -> 709 | G15: =+ROUND(G14-E15,1) -> 29744.6
A16: 12 | B16: 46171 | D16: =+ROUND(G15*0.01,1) -> 297.4 | E16: =ROUNDUP($C$4/84,1) -> 407.5 | F16: =+ROUND(D16+E16,1) -> 704.9 | G16: =+ROUND(G15-E16,1) -> 29337.1
A17: 13 | B17: 46202 | D17: =+ROUND(G16*0.01,1) -> 293.4 | E17: =ROUNDUP($C$4/84,1) -> 407.5 | F17: =+ROUND(D17+E17,1) -> 700.9 | G17: =+ROUND(G16-E17,1) -> 28929.6
A18: 14 | B18: 46232 | D18: =+ROUND(G17*0.01,1) -> 289.3 | E18: =ROUNDUP($C$4/84,1) -> 407.5 | F18: =+ROUND(D18+E18,1) -> 696.8 | G18: =+ROUND(G17-E18,1) -> 28522.1
A19: 15 | B19: 46263 | D19: =+ROUND(G18*0.01,1) -> 285.2 | E19: =ROUNDUP($C$4/84,1) -> 407.5 | F19: =+ROUND(D19+E19,1) -> 692.7 | G19: =+ROUND(G18-E19,1) -> 28114.6
... A87: 83 | B87: 48333 | D87: =+ROUND(G86*0.01,1) -> 8.1 | E87: =ROUNDUP($C$4/84,1) -> 407.5 | F87: =+ROUND(D87+E87,1) -> 415.6 | G87: =+ROUND(G86-E87,1) -> 404.6
A88: 84 | B88: 48363 | D88: =+ROUND(G87*0.01,1) -> 4 | E88: =ROUNDUP($C$4/84,1)-2.9 -> 404.6 | F88: =+ROUND(D88+E88,1) -> 408.6 | G88: =+ROUND(G87-E88,1) -> 0
A89: TOTAL | D89: =+SUM(D5:D88) -> 14544.6 | E89: =+SUM(E5:E88) -> 34227.1 | F89: =+SUM(F5:F88) -> 48771.7

Sheet 29
A1: SOCIO: JHONATAN EDINSON TAPIA DIAZ
A2: SETIEMBRE 2025 - PRÉSTAMO
A3: PLAZO | B3: FECHA | C3: PRÉSTAMO S/. | D3: INTERES | E3: ABONO DE CAPITAL | F3: CUOTA | G3: SALDO
A4: 0 | B4: 45929 | C4: =+J7 -> 29925.5 | D4: 0.01 | G4: =+C4 -> 29925.5
A5: 1 | B5: 45959 | D5: =+ROUND(G4*0.01,1) -> 299.3 | E5: =ROUNDUP($C$4/84,1) -> 356.3 | F5: =+ROUND(D5+E5,1) -> 655.6 | G5: =+ROUND(G4-E5,1) -> 29569.2 | I5: SALDO | J5: 21925.5
A6: 2 | B6: 45990 | D6: =+ROUND(G5*0.01,1) -> 295.7 | E6: =ROUNDUP($C$4/84,1) -> 356.3 | F6: =+ROUND(D6+E6,1) -> 652 | G6: =+ROUND(G5-E6,1) -> 29212.9 | I6: PRESTAMO | J6: 8000
A7: 3 | B7: 46020 | D7: =+ROUND(G6*0.01,1) -> 292.1 | E7: =ROUNDUP($C$4/84,1) -> 356.3 | F7: =+ROUND(D7+E7,1) -> 648.4 | G7: =+ROUND(G6-E7,1) -> 28856.6 | I7: TOTAL | J7: =+SUM(J5:J6) -> 29925.5
A8: 4 | B8: 46051 | D8: =+ROUND(G7*0.01,1) -> 288.6 | E8: =ROUNDUP($C$4/84,1) -> 356.3 | F8: =+ROUND(D8+E8,1) -> 644.9 | G8: =+ROUND(G7-E8,1) -> 28500.3
A9: 5 | B9: 46081 | D9: =+ROUND(G8*0.01,1) -> 285 | E9: =ROUNDUP($C$4/84,1) -> 356.3 | F9: =+ROUND(D9+E9,1) -> 641.3 | G9: =+ROUND(G8-E9,1) -> 28144
A10: 6 | B10: 46110 | D10: =+ROUND(G9*0.01,1) -> 281.4 | E10: =ROUNDUP($C$4/84,1) -> 356.3 | F10: =+ROUND(D10+E10,1) -> 637.7 | G10: =+ROUND(G9-E10,1) -> 27787.7
A11: 7 | B11: 46141 | D11: =+ROUND(G10*0.01,1) -> 277.9 | E11: =ROUNDUP($C$4/84,1) -> 356.3 | F11: =+ROUND(D11+E11,1) -> 634.2 | G11: =+ROUND(G10-E11,1) -> 27431.4
A12: 8 | B12: 46171 | D12: =+ROUND(G11*0.01,1) -> 274.3 | E12: =ROUNDUP($C$4/84,1) -> 356.3 | F12: =+ROUND(D12+E12,1) -> 630.6 | G12: =+ROUND(G11-E12,1) -> 27075.1
A13: 9 | B13: 46202 | D13: =+ROUND(G12*0.01,1) -> 270.8 | E13: =ROUNDUP($C$4/84,1) -> 356.3 | F13: =+ROUND(D13+E13,1) -> 627.1 | G13: =+ROUND(G12-E13,1) -> 26718.8
A14: 10 | B14: 46232 | D14: =+ROUND(G13*0.01,1) -> 267.2 | E14: =ROUNDUP($C$4/84,1) -> 356.3 | F14: =+ROUND(D14+E14,1) -> 623.5 | G14: =+ROUND(G13-E14,1) -> 26362.5
A15: 11 | B15: 46263 | D15: =+ROUND(G14*0.01,1) -> 263.6 | E15: =ROUNDUP($C$4/84,1) -> 356.3 | F15: =+ROUND(D15+E15,1) -> 619.9 | G15: =+ROUND(G14-E15,1) -> 26006.2
A16: 12 | B16: 46294 | D16: =+ROUND(G15*0.01,1) -> 260.1 | E16: =ROUNDUP($C$4/84,1) -> 356.3 | F16: =+ROUND(D16+E16,1) -> 616.4 | G16: =+ROUND(G15-E16,1) -> 25649.9
A17: 13 | B17: 46324 | D17: =+ROUND(G16*0.01,1) -> 256.5 | E17: =ROUNDUP($C$4/84,1) -> 356.3 | F17: =+ROUND(D17+E17,1) -> 612.8 | G17: =+ROUND(G16-E17,1) -> 25293.6
A18: 14 | B18: 46355 | D18: =+ROUND(G17*0.01,1) -> 252.9 | E18: =ROUNDUP($C$4/84,1) -> 356.3 | F18: =+ROUND(D18+E18,1) -> 609.2 | G18: =+ROUND(G17-E18,1) -> 24937.3
A19: 15 | B19: 46385 | D19: =+ROUND(G18*0.01,1) -> 249.4 | E19: =ROUNDUP($C$4/84,1) -> 356.3 | F19: =+ROUND(D19+E19,1) -> 605.7 | G19: =+ROUND(G18-E19,1) -> 24581
... A87: 83 | B87: 48455 | D87: =+ROUND(G86*0.01,1) -> 7.1 | E87: =ROUNDUP($C$4/84,1) -> 356.3 | F87: =+ROUND(D87+E87,1) -> 363.4 | G87: =+ROUND(G86-E87,1) -> 352.6
A88: 84 | B88: 48486 | D88: =+ROUND(G87*0.01,1) -> 3.5 | E88: =ROUNDUP($C$4/84,1)-3.7 -> 352.6 | F88: =+ROUND(D88+E88,1) -> 356.1 | G88: =+ROUND(G87-E88,1) -> 0
A89: TOTAL | D89: =+SUM(D5:D88) -> 12716.9 | E89: =+SUM(E5:E88) -> 29925.5 | F89: =+SUM(F5:F88) -> 42642.4

Sheet 30
A1: SOCIA: VERA ARAUJO CRISTINA
A2: ENERO 2025 - PRÉSTAMO
A3: PLAZO | B3: FECHA | C3: PRÉSTAMO S/. | D3: INTERES | E3: ABONO DE CAPITAL | F3: CUOTA | G3: SALDO
A4: 0 | B4: 45686 | C4: =+J7 -> 21465.1 | D4: 0.01 | G4: =+C4 -> 21465.1
A5: 1 | B5: 45716 | D5: =+ROUND(G4*0.01,1) -> 214.7 | E5: =ROUNDUP($C$4/36,1) -> 596.3 | F5: =+ROUND(D5+E5,1) -> 811 | G5: =+ROUND(G4-E5,1) -> 20868.8 | I5: SALDO | J5: 18406.6
A6: 2 | B6: 45745 | D6: =+ROUND(G5*0.01,1) -> 208.7 | E6: =ROUNDUP($C$4/36,1) -> 596.3 | F6: =+ROUND(D6+E6,1) -> 805 | G6: =+ROUND(G5-E6,1) -> 20272.5 | I6: PRESTAMO | J6: 3058.5
A7: 3 | B7: 45776 | D7: =+ROUND(G6*0.01,1) -> 202.7 | E7: =ROUNDUP($C$4/36,1) -> 596.3 | F7: =+ROUND(D7+E7,1) -> 799 | G7: =+ROUND(G6-E7,1) -> 19676.2 | I7: TOTAL | J7: =+SUM(J5:J6) -> 21465.1
A8: 4 | B8: 45806 | D8: =+ROUND(G7*0.01,1) -> 196.8 | E8: =ROUNDUP($C$4/36,1) -> 596.3 | F8: =+ROUND(D8+E8,1) -> 793.1 | G8: =+ROUND(G7-E8,1) -> 19079.9
A9: 5 | B9: 45837 | D9: =+ROUND(G8*0.01,1) -> 190.8 | E9: =ROUNDUP($C$4/36,1) -> 596.3 | F9: =+ROUND(D9+E9,1) -> 787.1 | G9: =+ROUND(G8-E9,1) -> 18483.6
A10: 6 | B10: 45867 | D10: =+ROUND(G9*0.01,1) -> 184.8 | E10: =ROUNDUP($C$4/36,1) -> 596.3 | F10: =+ROUND(D10+E10,1) -> 781.1 | G10: =+ROUND(G9-E10,1) -> 17887.3
A11: 7 | B11: 45898 | D11: =+ROUND(G10*0.01,1) -> 178.9 | E11: =ROUNDUP($C$4/36,1) -> 596.3 | F11: =+ROUND(D11+E11,1) -> 775.2 | G11: =+ROUND(G10-E11,1) -> 17291
A12: 8 | B12: 45929 | D12: =+ROUND(G11*0.01,1) -> 172.9 | E12: =ROUNDUP($C$4/36,1) -> 596.3 | F12: =+ROUND(D12+E12,1) -> 769.2 | G12: =+ROUND(G11-E12,1) -> 16694.7
A13: 9 | B13: 45959 | D13: =+ROUND(G12*0.01,1) -> 166.9 | E13: =ROUNDUP($C$4/36,1) -> 596.3 | F13: =+ROUND(D13+E13,1) -> 763.2 | G13: =+ROUND(G12-E13,1) -> 16098.4
A14: 10 | B14: 45990 | D14: =+ROUND(G13*0.01,1) -> 161 | E14: =ROUNDUP($C$4/36,1) -> 596.3 | F14: =+ROUND(D14+E14,1) -> 757.3 | G14: =+ROUND(G13-E14,1) -> 15502.1
A15: 11 | B15: 46020 | D15: =+ROUND(G14*0.01,1) -> 155 | E15: =ROUNDUP($C$4/36,1) -> 596.3 | F15: =+ROUND(D15+E15,1) -> 751.3 | G15: =+ROUND(G14-E15,1) -> 14905.8
A16: 12 | B16: 46051 | D16: =+ROUND(G15*0.01,1) -> 149.1 | E16: =ROUNDUP($C$4/36,1) -> 596.3 | F16: =+ROUND(D16+E16,1) -> 745.4 | G16: =+ROUND(G15-E16,1) -> 14309.5 | I16: INTERES | J16: =SUM(D5:D17) -> 2325.4
A17: 13 | B17: 46081 | D17: =+ROUND(G16*0.01,1) -> 143.1 | E17: =ROUNDUP($C$4/36,1) -> 596.3 | F17: =+ROUND(D17+E17,1) -> 739.4 | G17: =+ROUND(G16-E17,1) -> 13713.2 | I17: SALDO | J17: =G17 -> 13713.2
A18: 14 | B18: 46110 | D18: =+ROUND(G17*0.01,1) -> 137.1 | E18: =ROUNDUP($C$4/36,1) -> 596.3 | F18: =+ROUND(D18+E18,1) -> 733.4 | G18: =+ROUND(G17-E18,1) -> 13116.9
A19: 15 | B19: 46141 | D19: =+ROUND(G18*0.01,1) -> 131.2 | E19: =ROUNDUP($C$4/36,1) -> 596.3 | F19: =+ROUND(D19+E19,1) -> 727.5 | G19: =+ROUND(G18-E19,1) -> 12520.6
A20: 16 | B20: 46171 | D20: =+ROUND(G19*0.01,1) -> 125.2 | E20: =ROUNDUP($C$4/36,1) -> 596.3 | F20: =+ROUND(D20+E20,1) -> 721.5 | G20: =+ROUND(G19-E20,1) -> 11924.3
A21: 17 | B21: 46202 | D21: =+ROUND(G20*0.01,1) -> 119.2 | E21: =ROUNDUP($C$4/36,1) -> 596.3 | F21: =+ROUND(D21+E21,1) -> 715.5 | G21: =+ROUND(G20-E21,1) -> 11328
A22: 18 | B22: 46232 | D22: =+ROUND(G21*0.01,1) -> 113.3 | E22: =ROUNDUP($C$4/36,1) -> 596.3 | F22: =+ROUND(D22+E22,1) -> 709.6 | G22: =+ROUND(G21-E22,1) -> 10731.7
A23: 19 | B23: 46263 | D23: =+ROUND(G22*0.01,1) -> 107.3 | E23: =ROUNDUP($C$4/36,1) -> 596.3 | F23: =+ROUND(D23+E23,1) -> 703.6 | G23: =+ROUND(G22-E23,1) -> 10135.4
A24: 20 | B24: 46294 | D24: =+ROUND(G23*0.01,1) -> 101.4 | E24: =ROUNDUP($C$4/36,1) -> 596.3 | F24: =+ROUND(D24+E24,1) -> 697.7 | G24: =+ROUND(G23-E24,1) -> 9539.1
A25: 21 | B25: 46324 | D25: =+ROUND(G24*0.01,1) -> 95.4 | E25: =ROUNDUP($C$4/36,1) -> 596.3 | F25: =+ROUND(D25+E25,1) -> 691.7 | G25: =+ROUND(G24-E25,1) -> 8942.8
A26: 22 | B26: 46355 | D26: =+ROUND(G25*0.01,1) -> 89.4 | E26: =ROUNDUP($C$4/36,1) -> 596.3 | F26: =+ROUND(D26+E26,1) -> 685.7 | G26: =+ROUND(G25-E26,1) -> 8346.5
A27: 23 | B27: 46385 | D27: =+ROUND(G26*0.01,1) -> 83.5 | E27: =ROUNDUP($C$4/36,1) -> 596.3 | F27: =+ROUND(D27+E27,1) -> 679.8 | G27: =+ROUND(G26-E27,1) -> 7750.2
A28: 24 | B28: 46416 | D28: =+ROUND(G27*0.01,1) -> 77.5 | E28: =ROUNDUP($C$4/36,1) -> 596.3 | F28: =+ROUND(D28+E28,1) -> 673.8 | G28: =+ROUND(G27-E28,1) -> 7153.9
A29: 25 | B29: 46446 | D29: =+ROUND(G28*0.01,1) -> 71.5 | E29: =ROUNDUP($C$4/36,1) -> 596.3 | F29: =+ROUND(D29+E29,1) -> 667.8 | G29: =+ROUND(G28-E29,1) -> 6557.6
... A39: 35 | B39: 46750 | D39: =+ROUND(G38*0.01,1) -> 11.9 | E39: =ROUNDUP($C$4/36,1) -> 596.3 | F39: =+ROUND(D39+E39,1) -> 608.2 | G39: =+ROUND(G38-E39,1) -> 594.6
A40: 36 | B40: 46781 | D40: =+ROUND(G39*0.01,1) -> 5.9 | E40: =ROUNDUP($C$4/36,1)-1.7 -> 594.6 | F40: =+ROUND(D40+E40,1) -> 600.5 | G40: =+ROUND(G39-E40,1) -> 0
A41: TOTAL | D41: =+SUM(D5:D40) -> 3970.8 | E41: =+SUM(E5:E40) -> 21465.1 | F41: =+SUM(F5:F40) -> 25435.9
A43: SOCIA: VERA ARAUJO CRISTINA
A44: ENERO 2025 - PRÉSTAMO
A45: PLAZO | B45: FECHA | C45: PRÉSTAMO S/. | D45: INTERES | E45: ABONO DE CAPITAL | F45: CUOTA | G45: SALDO
A46: 0 | B46: 46081 | C46: =+J49 -> 24415.6 | D46: 0.01 | G46: =+C46 -> 24415.6
A47: 1 | B47: 46110 | D47: =+ROUND(G46*0.01,1) -> 244.2 | E47: =ROUND($C$46/36,1) -> 678.2 | F47: =+ROUND(D47+E47,1) -> 922.4 | G47: =+ROUND(G46-E47,1) -> 23737.4 | I47: SALDO | J47: =G17 -> 13713.2
A48: 2 | B48: 46141 | D48: =+ROUND(G47*0.01,1) -> 237.4 | E48: =ROUND($C$46/36,1) -> 678.2 | F48: =+ROUND(D48+E48,1) -> 915.6 | G48: =+ROUND(G47-E48,1) -> 23059.2 | I48: PRESTAMO | J48: 10702.4
A49: 3 | B49: 46171 | D49: =+ROUND(G48*0.01,1) -> 230.6 | E49: =ROUND($C$46/36,1) -> 678.2 | F49: =+ROUND(D49+E49,1) -> 908.8 | G49: =+ROUND(G48-E49,1) -> 22381 | I49: TOTAL | J49: =+SUM(J47:J48) -> 24415.6
A50: 4 | B50: 46202 | D50: =+ROUND(G49*0.01,1) -> 223.8 | E50: =ROUND($C$46/36,1) -> 678.2 | F50: =+ROUND(D50+E50,1) -> 902 | G50: =+ROUND(G49-E50,1) -> 21702.8
A51: 5 | B51: 46232 | D51: =+ROUND(G50*0.01,1) -> 217 | E51: =ROUND($C$46/36,1) -> 678.2 | F51: =+ROUND(D51+E51,1) -> 895.2 | G51: =+ROUND(G50-E51,1) -> 21024.6
A52: 6 | B52: 46263 | D52: =+ROUND(G51*0.01,1) -> 210.2 | E52: =ROUND($C$46/36,1) -> 678.2 | F52: =+ROUND(D52+E52,1) -> 888.4 | G52: =+ROUND(G51-E52,1) -> 20346.4
A53: 7 | B53: 46294 | D53: =+ROUND(G52*0.01,1) -> 203.5 | E53: =ROUND($C$46/36,1) -> 678.2 | F53: =+ROUND(D53+E53,1) -> 881.7 | G53: =+ROUND(G52-E53,1) -> 19668.2
A54: 8 | B54: 46324 | D54: =+ROUND(G53*0.01,1) -> 196.7 | E54: =ROUND($C$46/36,1) -> 678.2 | F54: =+ROUND(D54+E54,1) -> 874.9 | G54: =+ROUND(G53-E54,1) -> 18990
A55: 9 | B55: 46355 | D55: =+ROUND(G54*0.01,1) -> 189.9 | E55: =ROUND($C$46/36,1) -> 678.2 | F55: =+ROUND(D55+E55,1) -> 868.1 | G55: =+ROUND(G54-E55,1) -> 18311.8
A56: 10 | B56: 46385 | D56: =+ROUND(G55*0.01,1) -> 183.1 | E56: =ROUND($C$46/36,1) -> 678.2 | F56: =+ROUND(D56+E56,1) -> 861.3 | G56: =+ROUND(G55-E56,1) -> 17633.6
A57: 11 | B57: 46416 | D57: =+ROUND(G56*0.01,1) -> 176.3 | E57: =ROUND($C$46/36,1) -> 678.2 | F57: =+ROUND(D57+E57,1) -> 854.5 | G57: =+ROUND(G56-E57,1) -> 16955.4
A58: 12 | B58: 46446 | D58: =+ROUND(G57*0.01,1) -> 169.6 | E58: =ROUND($C$46/36,1) -> 678.2 | F58: =+ROUND(D58+E58,1) -> 847.8 | G58: =+ROUND(G57-E58,1) -> 16277.2
A59: 13 | B59: 46475 | D59: =+ROUND(G58*0.01,1) -> 162.8 | E59: =ROUND($C$46/36,1) -> 678.2 | F59: =+ROUND(D59+E59,1) -> 841 | G59: =+ROUND(G58-E59,1) -> 15599
A60: 14 | B60: 46506 | D60: =+ROUND(G59*0.01,1) -> 156 | E60: =ROUND($C$46/36,1) -> 678.2 | F60: =+ROUND(D60+E60,1) -> 834.2 | G60: =+ROUND(G59-E60,1) -> 14920.8
A61: 15 | B61: 46536 | D61: =+ROUND(G60*0.01,1) -> 149.2 | E61: =ROUND($C$46/36,1) -> 678.2 | F61: =+ROUND(D61+E61,1) -> 827.4 | G61: =+ROUND(G60-E61,1) -> 14242.6
... A81: 35 | B81: 47147 | D81: =+ROUND(G80*0.01,1) -> 13.6 | E81: =ROUND($C$46/36,1) -> 678.2 | F81: =+ROUND(D81+E81,1) -> 691.8 | G81: =+ROUND(G80-E81,1) -> 678.6
A82: 36 | B82: 47177 | D82: =+ROUND(G81*0.01,1) -> 6.8 | E82: =ROUND($C$46/36,1)+0.4 -> 678.6 | F82: =+ROUND(D82+E82,1) -> 685.4 | G82: =+ROUND(G81-E82,1) -> 0
A83: TOTAL | D83: =+SUM(D47:D82) -> 4517.1 | E83: =+SUM(E47:E82) -> 24415.6 | F83: =+SUM(F47:F82) -> 28932.7
